Workbook
Name CARTONAL: Tabla3[CARTONAL]
Name CELOVEN: INTERNACIONAL_PAPER[CELOVEN]
Name CLIENTE: #REF!
Name EUROPACIFIC: Tabla5[EUROPACIFIC]
Name FLEXAM: INTERNACIONAL_PAPER[FLEXAM]
Name INTERNACIONAL_PAPEL: #REF!
Name MCLTLP: INTERNACIONAL_PAPER[MCLTLP]
Name MORROCEL: INTERNACIONAL_PAPER[MORROCEL]
Name OPPFILM: INTERNACIONAL_PAPER[OPPFILM]
Name PLASTICOS.DE.EMPAQUE: INTERNACIONAL_PAPER[PLASTICOS.DE.EMPAQUE]
Name plasticos.del.litoral: INTERNACIONAL_PAPER[plasticos.del.litoral]
Name PRODUCTO: #REF!
Name PRODUCTO: #REF!
Name PRODUCTO: #REF!
Name PRODUCTOS: #REF!
Name PRODUCTOS: #REF!
Name PRODUCTOS: #REF!
Name PRODUCTOS.: #REF!
Name Proveedor: Tabla1[Proveedor]
Name QUIMATIC.SPA.IMP: INTERNACIONAL_PAPER[QUIMATIC.SPA.IMP]
Name RETANA: INTERNACIONAL_PAPER[RETANA]
Name TECHNOFILM: INTERNACIONAL_PAPER[[#All],[TECHNOFILM]]
Name TELEPLASTIC: INTERNACIONAL_PAPER[TELEPLASTIC]
Name trabajo: Tabla2[lista]

Sheet OEE
B2: =D6 -> 0.58156597 | C2: =E6 -> 0.82564126 | D2: =F6 -> 0.91040658
B3: Eficiencia General de los Equipos
B4: (OEE - Overall Equipment Effectiveness)
B5: CUREX | C5: O.E.E | D5: Disponibilidad | E5: Rendimiento | F5: Calidad
C6: =B2*C2*D2 -> 0.43714525 | D6: =((OLYMPIA!AF28-OLYMPIA!AC28-OLYMPIA!Q28)+(NOVOFLEX.!AF72-NOVOFLEX.!AC72-NOVOFLEX.!Q72))/(OLYMPIA!D8+NOVOFLEX.!D7) -> 0.58156597 | E6: =(NOVOFLEX.!BV72+OLYMPIA!BV28)/(75+68) -> 0.82564126 | F6: =100%-(NOVOFLEX.!CA72+OLYMPIA!CA28)/(NOVOFLEX.!BO72+OLYMPIA!BO28) -> 0.91040658
C10: O.E.E | D10: Disponibilidad | E10: Rendimiento | F10: Calidad
B11: Novoflex | C11: =NOVOFLEX.!I5 -> 0.72536539 | D11: =NOVOFLEX.!D5 -> 0.92923611 | E11: =NOVOFLEX.!E5 -> 0.8596378 | F11: =NOVOFLEX.!F5 -> 0.90806147
B12: Olympia | C12: =OLYMPIA!I7 -> 0.16949709 | D12: =OLYMPIA!D7 -> 0.23389583 | E12: =OLYMPIA!E7 -> 0.78814509 | F12: =OLYMPIA!F7 -> 0.91946156

Sheet OLYMPIA
A5: INFORME MENSUAL DE PRODUCCION | CJ5: 72m/m | CK5: 0.12
A6: OLYMPIA | D6: Disponibilidad | E6: Rendimiento | F6: Calidad | I6: OEE OLYMPIA | N6: =D7 -> 0.23389583 | O6: =E7 -> 0.78814509 | P6: =F7 -> 0.91946156
A7: MES: | B7: MARZO | D7: =(AF28-AC28-Q28)/D8 -> 0.23389583 | E7: =((BK28/(AF28-AC28-Q28-W28))/68) -> 0.78814509 | F7: =100%-CB28 -> 0.91946156 | I7: =(N6*O6*P6) -> 0.16949709
A8: DIAS TRABAJADOS : | C8: 20 | D8: =C8*24*60 -> 28800 | E8: =C8*24 -> 480
A9: PEDIDO | B9: CODIGO DE MAQUINA | C9: FECHA | D9: CODIGO PRODUCTO | E9: O/P | F9: DESTINO | G9: N° DE TRABAJOS | H9: COMPAÑÍA | I9: NOMBRE DEL CLIENTE | J9: PRODUCTO | K9: CLIENTE Kg | L9: TIEMPO DE PARADAS EN MINUTOS | AD9: TOTAL TIEMPO PARADAS min. | AE9: TIEMPO EFECTIVO PRODUCCION min. | AF9: TOTAL TIEMPO PRODUCCION min. | AG9: DIAS TRABAJADOS | AH9: EFICIENCIA DE MAQUINA | AI9: ENTRADA DE MATERIA PRIMA | AZ9: SALIDA DE MATERIALES | BR9: DATOS DE TINTA Kg. | BU9: VELOCIDAD m/min. | BW9: DESPERDICIO | CE9: OBSERVACIONES
L10: PREPARACION | M10: PRE-PRENSA | N10: COLORIMETRIA | O10: CALIDAD | P10: MANTENIMIENTO | Q10: Limpieza general de Maquina | R10: PLANIFICACION | S10: LIMPIEZA DE PLANCHA | T10: LIMPIEZA DE RODILLO | U10: LIMPIEZA DE TAMBOR CENTRAL | V10: PRODUCCION | W10: PRUEBAS | X10: LOGISTICA | Y10: FALLAS ELECT | Z10: APROBACIONES | AA10: ESTANDAR DE COLOR | AB10: RRHH | AC10: FALTA DE INSUMO /PEDIDO
AI11: PELICULAS | AN11: TINTAS Kg | AW11: CONSUMO | AX11: SOLVENTE Lts | AZ11: PELICULA DEVOLUCION | BC11: TINTAS KG EN DEVOLUCION | BK11: PRODUCTO TERMINADO | BP11: SOLVENTE Lts | BR11: CONSUMO DE TINTA BLANCO | BS11: CONSUMO DE TINTA VARIAS | BT11: CONSUMO TOTAL | BU11: VELOCIDAD DE MAQUINA TEORICA ML/min. | BV11: VELOCIDAD DE MAQUINA REAL ML/min. | BW11: m/l | BY11: m2 | CA11: Kg
AI12: m/l | AJ12: GRAMAJE g/m2 | AK12: ANCHO mm | AL12: m2 | AM12: Kg | AN12: # COLORES | AO12: BLANCO | AP12: AZUL REFLEX | AQ12: MAGENTA | AR12: AMARILLO | AS12: CYAN | AT12: ROJO | AU12: OTRAS | AV12: TOTAL | AX12: PRODUCCION | AY12: LIMPIEZA | AZ12: m/l | BA12: m2 | BB12: Kg | BC12: BLANCO | BD12: AZUL REFLEX | BE12: MAGENTA | BF12: AMARILLO | BG12: CYAN | BH12: ROJO | BI12: OTRAS | BJ12: TOTAL | BK12: m/l | BL12: GRAMAJE g/m2 | BM12: ANCHO mm | BN12: m2 | BO12: Kg | BP12: PRODUCCION | BQ12: LIMPIEZA
BW13: CANT | BX13: % | BY13: CANT | BZ13: % | CA13: CANT | CB13: % | CC13: MAT. OBSERVACION | CD13: MAT. RECHAZADO | CF13: Tipo de Trabajo | CG13: nº de pantone | CH13: Aplic Tinta Humeda | CI13: M/L Estandar de Dsp | CJ13: Metros de Dsp | CK13: Cumplimiento Estandar | CL13: fecha de entrega | CM13: cumplimiento entrega | CN13: metros op | CO13: Cumplimiento Fabricado | CP13: material reciclado | CQ13: Proveedor | CR13: Material
AF14: +
A15: 21-0575 | B15: OF | C15: 46118 | D15: =IFERROR(VLOOKUP($A15,Hoja3!$A$3:$F$6000,2,FALSE),"") -> TXSPSP035B002 | E15: 16619 | F15: =IFERROR(VLOOKUP($A15,Hoja3!$A$3:$F$6000,6,FALSE),"") -> LAMINACION | G15: 1 | H15: =IFERROR(VLOOKUP($A15,Hoja3!$A$3:$F$6000,5,FALSE),"") -> CX | I15: =IFERROR(VLOOKUP($A15,Hoja3!$A$3:$F$6000,3,FALSE),"") -> C.A. SUCESORA DE JOSE PUIG & CIA | J15: =IFERROR(VLOOKUP($A15,Hoja3!$A$3:$F$6000,4,FALSE),"") -> ENVOLTORIO EXTERNO IMPRESO SODA PUIG 240g | K15: 5000 | L15: =90+40+60+40 -> 230 | M15: =20+40+60+240+40 -> 400 | N15: =120+35+35+20+45 -> 255 | O15: 30 | P15: =30+30+60 -> 120 | Q15: 0 | R15: 0 | S15: =15+15+15+15+15+20+15 -> 110 | T15: 10 | U15: 10 | V15: =20+30+15+20+60+30 -> 175 | W15: 0 | X15: =30+40 -> 70 | Y15: 0 | Z15: 0 | AA15: 0 | AB15: =30+60+30+30+60 -> 210 | AC15: 0 | AD15: =SUM(L15:AC15) -> 1620 | AE15: 1350 | AF15: =SUM(AD15:AE15) -> 2970 | AG15: =AF15/(60*24) -> 2.0625 | AH15: =IFERROR(AE15/AF15,0) -> 0.45454545 | AI15: =124530+84300 -> 208830 | AJ15: 14 | AK15: 1090 | AL15: =IF(AM15=0,0,(+AI15*AK15/1000)) -> 227624.7 | AM15: =1276+1878 -> 3154 | AN15: 5 | AO15: 560 | AP15: 73 | AQ15: 40 | AR15: 40 | AS15: 0 | AT15: 0 | AU15: 33 | AV15: =SUM(AO15:AU15) -> 746 | AW15: =+(AM15+(BR15*50/100))+(BS15*30/100)-BB15 -> 3403.9 | AX15: 0 | AY15: 0 | AZ15: 0 | BA15: 0 | BB15: 0 | BC15: 140 | BD15: 12 | BE15: 11 | BF15: 13 | BG15: 0 | BH15: 0 | BI15: 17 | BJ15: =SUM(BC15:BI15) -> 193 | BK15: =(72280+117730)-10914 -> 179096 | BL15: =IFERROR(+BO15*1000/((BK15)*(BM15/1000)),0) -> 14.749918 | BM15: =AK15 -> 1090 | BN15: =+BK15*BM15/1000 -> 195214.64 | BO15: =(1153+1901)-174.6 -> 2879.4 | BP15: 0 | BQ15: 0 | BR15: =AO15-BC15 -> 420 | BS15: =(AP15+AQ15+AR15+AS15+AT15+AU15)-(BD15+BE15+BF15+BG15+BH15+BI15) -> 133 | BT15: =BR15+BS15 -> 553 | BU15: =IFERROR(+BK15/AE15,0) -> 132.6637 | BV15: =IFERROR(+BK15/(AF15),0) -> 60.301684 | BW15: =IFERROR(+(AI15-AZ15)-BK15,0) -> 29734 | BX15: =IFERROR(+BW15/BK15,0) -> 0.16602269 | BY15: =IFERROR(+(AL15-BA15)-BN15,0) -> 32410.06 | BZ15: =IFERROR(+BY15/BN15,0) -> 0.16602269 | CA15: =IFERROR(+AW15-(BO15),0) -> 524.5 | CB15: =IFERROR(+CA15/BO15,1) -> 0.182156 | CC15: 0 | CD15: 0 | CE15: apariencia defectuosa en tramas por exceso decrecorrido en planchas, porosidad color azul, sucio color magenta en un solo ejemplar | CF15: REPETICION | CG15: 0 | CH15: =IFERROR((BT15*1000)/BN15,"") -> 2.8327793 | CI15: 3500 | CJ15: =IF(BW15=0,"",CI15-BW15) -> -26234 | CK15: {=_xlfn.IFS(CJ15>0,"CUMPLE",CJ15<0,"NO CUMPLE",CJ15="","")} -> NO CUMPLE | CL15: 46125 | CM15: {=_xlfn.IFS(CL15-C15 > 0,"CUMPLE",CL15-C15 < 0,"NO CUMPLE")} -> CUMPLE | CN15: 190000 | CO15: =BK15-CN15 -> -10904 | CP15: 900 | CQ15: OPPFILM | CR15: BOPP SC TRANSPARENTE
A16: 01-6075 | B16: OF | C16: 46125 | D16: =IFERROR(VLOOKUP($A16,Hoja3!$A$3:$F$6000,2,FALSE),"") -> TMMCGP228A000 | E16: 16620 | F16: =IFERROR(VLOOKUP($A16,Hoja3!$A$3:$F$6000,6,FALSE),"") -> LAMINACION | G16: 1 | H16: =IFERROR(VLOOKUP($A16,Hoja3!$A$3:$F$6000,5,FALSE),"") -> MCL | I16: =IFERROR(VLOOKUP($A16,Hoja3!$A$3:$F$6000,3,FALSE),"") -> MORROCEL, C.A. | J16: =IFERROR(VLOOKUP($A16,Hoja3!$A$3:$F$6000,4,FALSE),"") -> LINNER MTP IMPRESO GARANTIA DE PUREZA | K16: 5000 | L16: 70 | M16: 0 | N16: 20 | O16: 0 | P16: 0 | Q16: 0 | R16: 0 | S16: 0 | T16: 0 | U16: 0 | V16: =70+70 -> 140 | W16: 0 | X16: 25 | Y16: 0 | Z16: 0 | AA16: 0 | AB16: 0 | AC16: 0 | AD16: =SUM(L16:AC16) -> 255 | AE16: 225 | AF16: =SUM(AD16:AE16) -> 480 | AG16: =AF16/(60*24) -> 0.33333333 | AH16: =IFERROR(AE16/AF16,0) -> 0.46875 | AI16: 18076 | AJ16: 168 | AK16: 965 | AL16: =IF(AM16=0,0,(+AI16*AK16/1000)) -> 17443.34 | AM16: 4079.6 | AN16: 1 | AO16: 0 | AP16: 0 | AQ16: 0 | AR16: 0 | AS16: 0 | AT16: 28 | AU16: 0 | AV16: =SUM(AO16:AU16) -> 28 | AW16: =+(AM16+(BR16*50/100))+(BS16*30/100)-BB16 -> 4082.3 | AX16: 0 | AY16: 0 | AZ16: 0 | BA16: 0 | BB16: 0 | BC16: 0 | BD16: 0 | BE16: 0 | BF16: 0 | BG16: 0 | BH16: 19 | BI16: 0 | BJ16: =SUM(BC16:BI16) -> 19 | BK16: 17897 | BL16: =IFERROR(+BO16*1000/((BK16)*(BM16/1000)),0) -> 232.12273 | BM16: =AK16 -> 965 | BN16: =+BK16*BM16/1000 -> 17270.605 | BO16: 4008.9 | BP16: 0 | BQ16: 0 | BR16: =AO16-BC16 -> 0 | BS16: =(AP16+AQ16+AR16+AS16+AT16+AU16)-(BD16+BE16+BF16+BG16+BH16+BI16) -> 9 | BT16: =BR16+BS16 -> 9 | BU16: =IFERROR(+BK16/AE16,0) -> 79.542222 | BV16: =IFERROR(+BK16/(AF16),0) -> 37.285417 | BW16: =IFERROR(+(AI16-AZ16)-BK16,0) -> 179 | BX16: =IFERROR(+BW16/BK16,0) -> 0.010001676 | BY16: =IFERROR(+(AL16-BA16)-BN16,0) -> 172.735 | BZ16: =IFERROR(+BY16/BN16,0) -> 0.010001676 | CA16: =IFERROR(+AW16-(BO16),0) -> 73.4 | CB16: =IFERROR(+CA16/BO16,1) -> 0.018309262 | CC16: 0 | CD16: 0 | CE16: se culmina sin novedad | CF16: REPETICION | CG16: 0 | CH16: =IFERROR((BT16*1000)/BN16,"") -> 0.52111666 | CI16: 3500 | CJ16: =IF(BW16=0,"",CI16-BW16) -> 3321 | CK16: {=_xlfn.IFS(CJ16>0,"CUMPLE",CJ16<0,"NO CUMPLE",CJ16="","")} -> CUMPLE | CL16: 46132 | CM16: {=_xlfn.IFS(CL16-C16 > 0,"CUMPLE",CL16-C16 < 0,"NO CUMPLE")} -> CUMPLE | CN16: 22000 | CO16: =BK16-CN16 -> -4103 | CP16: 0 | CQ16: MORROCEL | CR16: LINNER MTP GARANTIA DE PUREZA
A17: 01-6019 | B17: OP | C17: 46126 | D17: =IFERROR(VLOOKUP($A17,Hoja3!$A$3:$F$6000,2,FALSE),"") -> TMARMZ044B001 | E17: 16557. | F17: =IFERROR(VLOOKUP($A17,Hoja3!$A$3:$F$6000,6,FALSE),"") -> LAMINACION | G17: 1 | H17: =IFERROR(VLOOKUP($A17,Hoja3!$A$3:$F$6000,5,FALSE),"") -> MCL | I17: =IFERROR(VLOOKUP($A17,Hoja3!$A$3:$F$6000,3,FALSE),"") -> ALFONZO RIVAS & CIA, C.A. | J17: =IFERROR(VLOOKUP($A17,Hoja3!$A$3:$F$6000,4,FALSE),"") -> LAMINACION IMPRESA MAIZINA 400g | K17: 0 | L17: 60 | M17: 0 | N17: 0 | O17: 15 | P17: 25 | Q17: 0 | R17: 0 | S17: 10 | T17: 0 | U17: 5 | V17: 0 | W17: 0 | X17: =45+50 -> 95 | Y17: 0 | Z17: 0 | AA17: 0 | AB17: 0 | AC17: 0 | AD17: =SUM(L17:AC17) -> 210 | AE17: 184.8 | AF17: =SUM(AD17:AE17) -> 394.8 | AG17: =AF17/(60*24) -> 0.27416667 | AH17: =IFERROR(AE17/AF17,0) -> 0.46808511 | AI17: 27624 | AJ17: 44 | AK17: 940 | AL17: =IF(AM17=0,0,(+AI17*AK17/1000)) -> 25966.56 | AM17: 1128.2 | AN17: 1 | AO17: 0 | AP17: 0 | AQ17: 0 | AR17: 0 | AS17: 0 | AT17: 0 | AU17: 140 | AV17: =SUM(AO17:AU17) -> 140 | AW17: =+(AM17+(BR17*50/100))+(BS17*30/100)-BB17 -> 1137.8 | AX17: 0 | AY17: 0 | AZ17: 0 | BA17: 0 | BB17: 0 | BC17: 0 | BD17: 0 | BE17: 0 | BF17: 0 | BG17: 0 | BH17: 0 | BI17: 108 | BJ17: =SUM(BC17:BI17) -> 108 | BK17: 26749 | BL17: =IFERROR(+BO17*1000/((BK17)*(BM17/1000)),0) -> 43.863242 | BM17: =AK17 -> 940 | BN17: =+BK17*BM17/1000 -> 25144.06 | BO17: 1102.9 | BP17: 0 | BQ17: 0 | BR17: =AO17-BC17 -> 0 | BS17: =(AP17+AQ17+AR17+AS17+AT17+AU17)-(BD17+BE17+BF17+BG17+BH17+BI17) -> 32 | BT17: =BR17+BS17 -> 32 | BU17: =IFERROR(+BK17/AE17,0) -> 144.74567 | BV17: =IFERROR(+BK17/(AF17),0) -> 67.753293 | BW17: =IFERROR(+(AI17-AZ17)-BK17,0) -> 875 | BX17: =IFERROR(+BW17/BK17,0) -> 0.032711503 | BY17: =IFERROR(+(AL17-BA17)-BN17,0) -> 822.5 | BZ17: =IFERROR(+BY17/BN17,0) -> 0.032711503 | CA17: =IFERROR(+AW17-(BO17),0) -> 34.9 | CB17: =IFERROR(+CA17/BO17,1) -> 0.031643848 | CC17: 0 | CD17: 0 | CE17: aplicación de compuesto deslizante | CF17: REPETICION | CG17: 0 | CH17: =IFERROR((BT17*1000)/BN17,"") -> 1.2726664 | CI17: 3500 | CJ17: =IF(BW17=0,"",CI17-BW17) -> 2625 | CK17: {=_xlfn.IFS(CJ17>0,"CUMPLE",CJ17<0,"NO CUMPLE",CJ17="","")} -> CUMPLE | CL17: 46132 | CM17: {=_xlfn.IFS(CL17-C17 > 0,"CUMPLE",CL17-C17 < 0,"NO CUMPLE")} -> CUMPLE | CN17: 28000 | CO17: =BK17-CN17 -> -1251 | CP17: 0 | CQ17: TELEPLASTIC | CR17: BOPP OCTS TRANSPARENTE
A18: 01-6078 | B18: OF | C18: 46127 | D18: =IFERROR(VLOOKUP($A18,Hoja3!$A$3:$F$6000,2,FALSE),"") -> TMCCTM1270001 | E18: 16621 | F18: =IFERROR(VLOOKUP($A18,Hoja3!$A$3:$F$6000,6,FALSE),"") -> LAMINACION | G18: 1 | H18: =IFERROR(VLOOKUP($A18,Hoja3!$A$3:$F$6000,5,FALSE),"") -> MCL | I18: =IFERROR(VLOOKUP($A18,Hoja3!$A$3:$F$6000,3,FALSE),"") -> PRODUCTOS ALIMENTOS COOK CHILL, C.A. | J18: =IFERROR(VLOOKUP($A18,Hoja3!$A$3:$F$6000,4,FALSE),"") -> LAMINACION TAPAS MINITINA SIN IMPRESIÓN | K18: 450 | L18: 40 | M18: 0 | N18: 0 | O18: 25 | P18: 0 | Q18: 0 | R18: 0 | S18: 0 | T18: 0 | U18: 0 | V18: 0 | W18: 0 | X18: 0 | Y18: 0 | Z18: 0 | AA18: 0 | AB18: 0 | AC18: 0 | AD18: =SUM(L18:AC18) -> 65 | AE18: 40.2 | AF18: =SUM(AD18:AE18) -> 105.2 | AG18: =AF18/(60*24) -> 0.073055556 | AH18: =IFERROR(AE18/AF18,0) -> 0.38212928 | AI18: 4090 | AJ18: 126 | AK18: 900 | AL18: =IF(AM18=0,0,(+AI18*AK18/1000)) -> 3681 | AM18: 454 | AN18: 1 | AO18: 0 | AP18: 0 | AQ18: 0 | AR18: 0 | AS18: 0 | AT18: 0 | AU18: 30 | AV18: =SUM(AO18:AU18) -> 30 | AW18: =+(AM18+(BR18*50/100))+(BS18*30/100)-BB18 -> 456.1 | AX18: 0 | AY18: 0 | AZ18: 0 | BA18: 0 | BB18: 0 | BC18: 0 | BD18: 0 | BE18: 0 | BF18: 0 | BG18: 0 | BH18: 0 | BI18: 23 | BJ18: =SUM(BC18:BI18) -> 23 | BK18: 3950 | BL18: =IFERROR(+BO18*1000/((BK18)*(BM18/1000)),0) -> 123.0661 | BM18: =AK18 -> 900 | BN18: =+BK18*BM18/1000 -> 3555 | BO18: 437.5 | BP18: 0 | BQ18: 0 | BR18: =AO18-BC18 -> 0 | BS18: =(AP18+AQ18+AR18+AS18+AT18+AU18)-(BD18+BE18+BF18+BG18+BH18+BI18) -> 7 | BT18: =BR18+BS18 -> 7 | BU18: =IFERROR(+BK18/AE18,0) -> 98.258706 | BV18: =IFERROR(+BK18/(AF18),0) -> 37.547529 | BW18: =IFERROR(+(AI18-AZ18)-BK18,0) -> 140 | BX18: =IFERROR(+BW18/BK18,0) -> 0.035443038 | BY18: =IFERROR(+(AL18-BA18)-BN18,0) -> 126 | BZ18: =IFERROR(+BY18/BN18,0) -> 0.035443038 | CA18: =IFERROR(+AW18-(BO18),0) -> 18.6 | CB18: =IFERROR(+CA18/BO18,1) -> 0.042514286 | CC18: 0 | CD18: 0 | CE18: durante la corrida se puede apreciar arrugas intermitente de bobina madre | CF18: REPETICION | CG18: 0 | CH18: =IFERROR((BT18*1000)/BN18,"") -> 1.9690577 | CI18: 3500 | CJ18: =IF(BW18=0,"",CI18-BW18) -> 3360 | CK18: {=_xlfn.IFS(CJ18>0,"CUMPLE",CJ18<0,"NO CUMPLE",CJ18="","")} -> CUMPLE | CL18: 46139 | CM18: {=_xlfn.IFS(CL18-C18 > 0,"CUMPLE",CL18-C18 < 0,"NO CUMPLE")} -> CUMPLE | CN18: 3000 | CO18: =BK18-CN18 -> 950 | CP18: 350 | CQ18: MORROCEL | CR18: LAMINACION TAPA MINITINA SIN IMPRESIÓN
A19: 01-6040 | B19: OF | C19: 46133 | D19: =IFERROR(VLOOKUP($A19,Hoja3!$A$3:$F$6000,2,FALSE),"") -> TXPCGP023B001 | E19: 16578 | F19: =IFERROR(VLOOKUP($A19,Hoja3!$A$3:$F$6000,6,FALSE),"") -> CORTE | G19: 1 | H19: =IFERROR(VLOOKUP($A19,Hoja3!$A$3:$F$6000,5,FALSE),"") -> CX | I19: =IFERROR(VLOOKUP($A19,Hoja3!$A$3:$F$6000,3,FALSE),"") -> PEPSI-COLA VENEZUELA, C.A. | J19: =IFERROR(VLOOKUP($A19,Hoja3!$A$3:$F$6000,4,FALSE),"") -> ETIQUETA IMPRESA GOLDEN PIÑA 1,5L | K19: 740 | L19: 30 | M19: 115 | N19: =15+20+20+10 -> 65 | O19: 15 | P19: 70 | Q19: 0 | R19: 0 | S19: =50+20+15+15+10+20 -> 130 | T19: 45 | U19: 0 | V19: =20+20+30 -> 70 | W19: 0 | X19: 40 | Y19: 0 | Z19: 0 | AA19: 0 | AB19: 80 | AC19: 0 | AD19: =SUM(L19:AC19) -> 660 | AE19: 385.2 | AF19: =SUM(AD19:AE19) -> 1045.2 | AG19: =AF19/(60*24) -> 0.72583333 | AH19: =IFERROR(AE19/AF19,0) -> 0.36854191 | AI19: 44598 | AJ19: 21 | AK19: 930 | AL19: =IF(AM19=0,0,(+AI19*AK19/1000)) -> 41476.14 | AM19: =927-56 -> 871 | AN19: 6 | AO19: 0 | AP19: =25+33 -> 58 | AQ19: 0 | AR19: 30 | AS19: 0 | AT19: 14 | AU19: =12+76 -> 88 | AV19: =SUM(AO19:AU19) -> 190 | AW19: =+(AM19+(BR19*50/100))+(BS19*30/100)-BB19 -> 898.3 | AX19: 0 | AY19: 0 | AZ19: 0 | BA19: 0 | BB19: 0 | BC19: 0 | BD19: =17+15 -> 32 | BE19: 0 | BF19: 15 | BG19: 0 | BH19: 13 | BI19: =11+28 -> 39 | BJ19: =SUM(BC19:BI19) -> 99 | BK19: 33349 | BL19: =IFERROR(+BO19*1000/((BK19)*(BM19/1000)),0) -> 20.796677 | BM19: =AK19 -> 930 | BN19: =+BK19*BM19/1000 -> 31014.57 | BO19: =684.5-39.5 -> 645 | BP19: 0 | BQ19: 0 | BR19: =AO19-BC19 -> 0 | BS19: =(AP19+AQ19+AR19+AS19+AT19+AU19)-(BD19+BE19+BF19+BG19+BH19+BI19) -> 91 | BT19: =BR19+BS19 -> 91 | BU19: =IFERROR(+BK19/AE19,0) -> 86.575805 | BV19: =IFERROR(+BK19/(AF19),0) -> 31.906812 | BW19: =IFERROR(+(AI19-AZ19)-BK19,0) -> 11249 | BX19: =IFERROR(+BW19/BK19,0) -> 0.33731146 | BY19: =IFERROR(+(AL19-BA19)-BN19,0) -> 10461.57 | BZ19: =IFERROR(+BY19/BN19,0) -> 0.33731146 | CA19: =IFERROR(+AW19-(BO19),0) -> 253.3 | CB19: =IFERROR(+CA19/BO19,1) -> 0.39271318 | CC19: 0 | CD19: 0 | CE19: al mmento de registrar estac 2 no mueve registros en ninguna direccion, y estac 5 solo mueve 5 mm hacia adelante, color negro problemas de sucio por secado acelerado, por esto se realizan varias paradas por limpieza y se cambia tinta pvk por cromia, mejorando pero luego vuelve a ensuciar, se limpia tambor central por sucio del barniz y el rodillo presor no ejercia su funcion bien, falta de ptos color negro se baja plancha y se monta una nueva, limpieza de planha por sucio del color negro, bob 2 arroja 39 kg de dsp y bob 3 13 kg por sucio color negro, | CF19: REPETICION | CG19: 3 | CH19: =IFERROR((BT19*1000)/BN19,"") -> 2.9341048 | CI19: 3500 | CJ19: =IF(BW19=0,"",CI19-BW19) -> -7749 | CK19: {=_xlfn.IFS(CJ19>0,"CUMPLE",CJ19<0,"NO CUMPLE",CJ19="","")} -> NO CUMPLE | CL19: 46111 | CM19: {=_xlfn.IFS(CL19-C19 > 0,"CUMPLE",CL19-C19 < 0,"NO CUMPLE")} -> NO CUMPLE | CN19: 36000 | CO19: =BK19-CN19 -> -2651 | CP19: 0 | CQ19: TELEPLASTIC | CR19: BOPP POCT PERLADO
A20: 01-6051 | B20: OF | C20: 46134 | D20: =IFERROR(VLOOKUP($A20,Hoja3!$A$3:$F$6000,2,FALSE),"") -> TXPCGP023B001 | E20: 16589 | F20: =IFERROR(VLOOKUP($A20,Hoja3!$A$3:$F$6000,6,FALSE),"") -> CORTE | G20: 1 | H20: =IFERROR(VLOOKUP($A20,Hoja3!$A$3:$F$6000,5,FALSE),"") -> CX | I20: =IFERROR(VLOOKUP($A20,Hoja3!$A$3:$F$6000,3,FALSE),"") -> PEPSI-COLA VENEZUELA, C.A. | J20: =IFERROR(VLOOKUP($A20,Hoja3!$A$3:$F$6000,4,FALSE),"") -> ETIQUETA IMPRESA GOLDEN PIÑA 1,5L | K20: 450 | L20: 30 | M20: 0 | N20: 0 | O20: 10 | P20: 0 | Q20: 0 | R20: 0 | S20: =70+10+10 -> 90 | T20: 0 | U20: 0 | V20: 0 | W20: 0 | X20: 0 | Y20: 0 | Z20: 0 | AA20: 0 | AB20: 0 | AC20: 0 | AD20: =SUM(L20:AC20) -> 130 | AE20: 140.4 | AF20: =SUM(AD20:AE20) -> 270.4 | AG20: =AF20/(60*24) -> 0.18777778 | AH20: =IFERROR(AE20/AF20,0) -> 0.51923077 | AI20: 25881 | AJ20: 21 | AK20: 930 | AL20: =IF(AM20=0,0,(+AI20*AK20/1000)) -> 24069.33 | AM20: =469+56 -> 525 | AN20: 6 | AO20: 0 | AP20: =17+15 -> 32 | AQ20: 0 | AR20: 15 | AS20: 0 | AT20: 13 | AU20: =11+28 -> 39 | AV20: =SUM(AO20:AU20) -> 99 | AW20: =+(AM20+(BR20*50/100))+(BS20*30/100)-BB20 -> 540.6 | AX20: 0 | AY20: 0 | AZ20: 0 | BA20: 0 | BB20: 0 | BC20: 0 | BD20: =12+5 -> 17 | BE20: 0 | BF20: 7 | BG20: 0 | BH20: 12 | BI20: =10+1 -> 11 | BJ20: =SUM(BC20:BI20) -> 47 | BK20: 24118 | BL20: =IFERROR(+BO20*1000/((BK20)*(BM20/1000)),0) -> 22.737669 | BM20: =AK20 -> 930 | BN20: =+BK20*BM20/1000 -> 22429.74 | BO20: 510 | BP20: 0 | BQ20: 0 | BR20: =AO20-BC20 -> 0 | BS20: =(AP20+AQ20+AR20+AS20+AT20+AU20)-(BD20+BE20+BF20+BG20+BH20+BI20) -> 52 | BT20: =BR20+BS20 -> 52 | BU20: =IFERROR(+BK20/AE20,0) -> 171.78063 | BV20: =IFERROR(+BK20/(AF20),0) -> 89.193787 | BW20: =IFERROR(+(AI20-AZ20)-BK20,0) -> 1763 | BX20: =IFERROR(+BW20/BK20,0) -> 0.07309893 | BY20: =IFERROR(+(AL20-BA20)-BN20,0) -> 1639.59 | BZ20: =IFERROR(+BY20/BN20,0) -> 0.07309893 | CA20: =IFERROR(+AW20-(BO20),0) -> 30.6 | CB20: =IFERROR(+CA20/BO20,1) -> 0.06 | CC20: 0 | CD20: 0 | CE20: se limpan planchas del negro por sucio | CF20: REPETICION | CG20: 3 | CH20: =IFERROR((BT20*1000)/BN20,"") -> 2.3183505 | CI20: 3500 | CJ20: =IF(BW20=0,"",CI20-BW20) -> 1737 | CK20: {=_xlfn.IFS(CJ20>0,"CUMPLE",CJ20<0,"NO CUMPLE",CJ20="","")} -> CUMPLE | CL20: 46111 | CM20: {=_xlfn.IFS(CL20-C20 > 0,"CUMPLE",CL20-C20 < 0,"NO CUMPLE")} -> NO CUMPLE | CN20: 20500 | CO20: =BK20-CN20 -> 3618 | CP20: 0 | CQ20: TELEPLASTIC | CR20: BOPP POCT PERLADO
A21: 000lm | B21: OF | C21: 46134 | D21: =IFERROR(VLOOKUP($A21,Hoja3!$A$3:$F$6000,2,FALSE),"") -> 000LM | E21: 000lm | F21: =IFERROR(VLOOKUP($A21,Hoja3!$A$3:$F$6000,6,FALSE),"") -> LIMPIEZA | G21: 0 | H21: =IFERROR(VLOOKUP($A21,Hoja3!$A$3:$F$6000,5,FALSE),"") -> CX | I21: =IFERROR(VLOOKUP($A21,Hoja3!$A$3:$F$6000,3,FALSE),"") -> LIMPIEZA GENERAL DE MAQUINA | J21: =IFERROR(VLOOKUP($A21,Hoja3!$A$3:$F$6000,4,FALSE),"") -> LIMPIEZA GENERAL DE MAQUINA | K21: 0 | L21: 0 | M21: 0 | N21: 0 | O21: 0 | P21: 0 | Q21: 150 | R21: 0 | S21: 0 | T21: 0 | U21: 0 | V21: 0 | W21: 0 | X21: 0 | Y21: 0 | Z21: 0 | AA21: 0 | AB21: 0 | AC21: 0 | AD21: =SUM(L21:AC21) -> 150 | AE21: 0 | AF21: =SUM(AD21:AE21) -> 150 | AG21: =AF21/(60*24) -> 0.10416667 | AH21: =IFERROR(AE21/AF21,0) -> 0 | AI21: 0 | AK21: 0 | AL21: =IF(AM21=0,0,(+AI21*AK21/1000)) -> 0 | AM21: 0 | AN21: 0 | AO21: 0 | AQ21: 0 | AR21: 0 | AS21: 0 | AT21: 0 | AU21: 0 | AV21: =SUM(AO21:AU21) -> 0 | AW21: =+(AM21+(BR21*50/100))+(BS21*30/100)-BB21 -> 0 | AX21: 0 | AY21: 0 | AZ21: 0 | BA21: 0 | BB21: 0 | BC21: 0 | BD21: 0 | BE21: 0 | BF21: 0 | BG21: 0 | BI21: 0 | BJ21: =SUM(BC21:BI21) -> 0 | BK21: 0 | BL21: =IFERROR(+BO21*1000/((BK21)*(BM21/1000)),0) -> 0 | BM21: 0 | BN21: =+BK21*BM21/1000 -> 0 | BO21: 0 | BP21: 0 | BQ21: 0 | BR21: =AO21-BC21 -> 0 | BS21: =(AP21+AQ21+AR21+AS21+AT21+AU21)-(BD21+BE21+BF21+BG21+BH21+BI21) -> 0 | BT21: =BR21+BS21 -> 0 | BU21: =IFERROR(+BK21/AE21,0) -> 0 | BV21: =IFERROR(+BK21/(AF21),0) -> 0 | BW21: =IFERROR(+(AI21-AZ21)-BK21,0) -> 0 | BX21: =IFERROR(+BW21/BK21,0) -> 0 | BY21: =IFERROR(+(AL21-BA21)-BN21,0) -> 0 | BZ21: =IFERROR(+BY21/BN21,0) -> 0 | CA21: =IFERROR(+AW21-(BO21),0) -> 0 | CB21: =IFERROR(+CA21/BO21,1) -> 1 | CC21: 0 | CD21: 0 | CE21: limpieza general de maquina | CF21: REPETICION | CG21: 0 | CH21: 0 | CI21: 3500 | CJ21: 0 | CK21: {=_xlfn.IFS(CJ21>0,"CUMPLE",CJ21<0,"NO CUMPLE",CJ21="","")} -> #N/A | CL21: 0 | CN21: 0 | CP21: 0
A22: 01-6023 | B22: OP | C22: 46139 | D22: =IFERROR(VLOOKUP($A22,Hoja3!$A$3:$F$6000,2,FALSE),"") -> TMAHSC083C003 | E22: 16567R | F22: =IFERROR(VLOOKUP($A22,Hoja3!$A$3:$F$6000,6,FALSE),"") -> LAMINACION | G22: 1 | H22: =IFERROR(VLOOKUP($A22,Hoja3!$A$3:$F$6000,5,FALSE),"") -> MCL | I22: =IFERROR(VLOOKUP($A22,Hoja3!$A$3:$F$6000,3,FALSE),"") -> ALIMENTOS HEINZ, C.A. | J22: =IFERROR(VLOOKUP($A22,Hoja3!$A$3:$F$6000,4,FALSE),"") -> LAMINACION IMPRESA GELATINA SONRISSA FRAMBUESA 132g. | K22: 274 | L22: 60 | M22: 0 | N22: 0 | O22: =20+20 -> 40 | P22: 130 | Q22: 0 | R22: 0 | S22: 0 | T22: 0 | U22: 0 | V22: 0 | W22: 0 | X22: =40+30 -> 70 | Y22: 0 | Z22: 0 | AA22: 0 | AB22: 0 | AC22: 0 | AD22: =SUM(L22:AC22) -> 300 | AE22: 220.2 | AF22: =SUM(AD22:AE22) -> 520.2 | AG22: =AF22/(60*24) -> 0.36125 | AH22: =IFERROR(AE22/AF22,0) -> 0.42329873 | AI22: 14000 | AJ22: 83 | AK22: 243 | AL22: =IF(AM22=0,0,(+AI22*AK22/1000)) -> 3402 | AM22: 273 | AN22: 1 | AO22: 0 | AP22: 0 | AQ22: 0 | AR22: 0 | AS22: 0 | AT22: 0 | AU22: 94 | AV22: =SUM(AO22:AU22) -> 94 | AW22: =+(AM22+(BR22*50/100))+(BS22*30/100)-BB22 -> 275.1 | AX22: 0 | AY22: 0 | AZ22: 0 | BA22: 0 | BB22: 0 | BC22: 0 | BD22: 0 | BE22: 0 | BF22: 0 | BG22: 0 | BH22: 0 | BI22: 87 | BJ22: =SUM(BC22:BI22) -> 87 | BK22: 13991 | BL22: =IFERROR(+BO22*1000/((BK22)*(BM22/1000)),0) -> 80.857388 | BM22: =AK22 -> 243 | BN22: =+BK22*BM22/1000 -> 3399.813 | BO22: 274.9 | BP22: 0 | BQ22: 0 | BR22: =AO22-BC22 -> 0 | BS22: =(AP22+AQ22+AR22+AS22+AT22+AU22)-(BD22+BE22+BF22+BG22+BH22+BI22) -> 7 | BT22: =BR22+BS22 -> 7 | BU22: =IFERROR(+BK22/AE22,0) -> 63.537693 | BV22: =IFERROR(+BK22/(AF22),0) -> 26.895425 | BW22: =IFERROR(+(AI22-AZ22)-BK22,0) -> 9 | BX22: =IFERROR(+BW22/BK22,0) -> 0.00064327067 | BY22: =IFERROR(+(AL22-BA22)-BN22,0) -> 2.187 | BZ22: =IFERROR(+BY22/BN22,0) -> 0.00064327067 | CA22: =IFERROR(+AW22-(BO22),0) -> 0.2 | CB22: =IFERROR(+CA22/BO22,1) -> 0.00072753729 | CC22: 0 | CD22: 0 | CE22: aplicacionde compuesto deslizante por cara interna para mejorar cof | CF22: PROCESO | CG22: 0 | CH22: =IFERROR((BT22*1000)/BN22,"") -> 2.0589368 | CI22: 0 | CJ22: =IF(BW22=0,"",CI22-BW22) -> -9 | CK22: {=_xlfn.IFS(CJ22>0,"CUMPLE",CJ22<0,"NO CUMPLE",CJ22="","")} -> NO CUMPLE | CL22: 0 | CN22: 0 | CP22: 0
A23: 21-0570 | B23: OP | C23: 46140 | D23: =IFERROR(VLOOKUP($A23,Hoja3!$A$3:$F$6000,2,FALSE),"") -> TXSPBC050A003 | E23: 16594 | F23: =IFERROR(VLOOKUP($A23,Hoja3!$A$3:$F$6000,6,FALSE),"") -> LAMINACION | G23: 1 | H23: =IFERROR(VLOOKUP($A23,Hoja3!$A$3:$F$6000,5,FALSE),"") -> CX | I23: =IFERROR(VLOOKUP($A23,Hoja3!$A$3:$F$6000,3,FALSE),"") -> C.A. SUCESORA DE JOSE PUIG & CIA | J23: =IFERROR(VLOOKUP($A23,Hoja3!$A$3:$F$6000,4,FALSE),"") -> LAMINACION IMPRESA BROWNIES CHOCOLATE 175g | K23: 1930 | L23: 10 | M23: 0 | N23: 0 | O23: 25 | P23: =40+55 -> 95 | Q23: 0 | R23: 0 | S23: 0 | T23: 0 | U23: 0 | V23: 0 | W23: 0 | X23: 0 | Y23: 0 | Z23: 0 | AA23: 0 | AB23: 0 | AC23: 0 | AD23: =SUM(L23:AC23) -> 130 | AE23: 370 | AF23: =SUM(AD23:AE23) -> 500 | AG23: =AF23/(60*24) -> 0.34722222 | AH23: =IFERROR(AE23/AF23,0) -> 0.74 | AI23: 38813 | AJ23: 50 | AK23: 1000 | AL23: =IF(AM23=0,0,(+AI23*AK23/1000)) -> 38813 | AM23: 1952.8 | AN23: 1 | AO23: 0 | AP23: 0 | AQ23: 0 | AR23: 0 | AS23: 0 | AT23: 0 | AU23: 87 | AV23: =SUM(AO23:AU23) -> 87 | AW23: =+(AM23+(BR23*50/100))+(BS23*30/100)-BB23 -> 1966.9 | AX23: 0 | AY23: 0 | AZ23: 0 | BA23: 0 | BB23: 0 | BC23: 0 | BD23: 0 | BE23: 0 | BF23: 0 | BG23: 0 | BH23: 0 | BI23: 40 | BJ23: =SUM(BC23:BI23) -> 40 | BK23: 38361 | BL23: =IFERROR(+BO23*1000/((BK23)*(BM23/1000)),0) -> 50.34801 | BM23: =AK23 -> 1000 | BN23: =+BK23*BM23/1000 -> 38361 | BO23: 1931.4 | BP23: 0 | BQ23: 0 | BR23: =AO23-BC23 -> 0 | BS23: =(AP23+AQ23+AR23+AS23+AT23+AU23)-(BD23+BE23+BF23+BG23+BH23+BI23) -> 47 | BT23: =BR23+BS23 -> 47 | BU23: =IFERROR(+BK23/AE23,0) -> 103.67838 | BV23: =IFERROR(+BK23/(AF23),0) -> 76.722 | BW23: =IFERROR(+(AI23-AZ23)-BK23,0) -> 452 | BX23: =IFERROR(+BW23/BK23,0) -> 0.0117828 | BY23: =IFERROR(+(AL23-BA23)-BN23,0) -> 452 | BZ23: =IFERROR(+BY23/BN23,0) -> 0.0117828 | CA23: =IFERROR(+AW23-(BO23),0) -> 35.5 | CB23: =IFERROR(+CA23/BO23,1) -> 0.018380449 | CC23: 0 | CD23: 0 | CE23: aplicación compuesto deslizante | CF23: PROCESO | CG23: 0 | CH23: =IFERROR((BT23*1000)/BN23,"") -> 1.2252027 | CI23: 0 | CJ23: =IF(BW23=0,"",CI23-BW23) -> -452 | CK23: {=_xlfn.IFS(CJ23>0,"CUMPLE",CJ23<0,"NO CUMPLE",CJ23="","")} -> NO CUMPLE | CL23: 0 | CN23: 0 | CP23: 0
A24: 01-6104 | B24: OF | C24: 46141 | D24: =IFERROR(VLOOKUP($A24,Hoja3!$A$3:$F$6000,2,FALSE),"") -> TXCLCM025A001 | E24: 16639 | F24: =IFERROR(VLOOKUP($A24,Hoja3!$A$3:$F$6000,6,FALSE),"") -> CORTE | G24: 1 | H24: =IFERROR(VLOOKUP($A24,Hoja3!$A$3:$F$6000,5,FALSE),"") -> cx | I24: =IFERROR(VLOOKUP($A24,Hoja3!$A$3:$F$6000,3,FALSE),"") -> CELOVEN, C.A. | J24: =IFERROR(VLOOKUP($A24,Hoja3!$A$3:$F$6000,4,FALSE),"") -> BOPP IMPRESO CINTA MRW | K24: 500 | L24: 70 | M24: 0 | N24: 40 | O24: 0 | P24: 0 | Q24: 0 | R24: 0 | S24: 0 | T24: 0 | U24: 0 | V24: 0 | W24: 0 | X24: 0 | Y24: 0 | Z24: 80 | AA24: 60 | AB24: 0 | AC24: 0 | AD24: =SUM(L24:AC24) -> 250 | AE24: 200.4 | AF24: =SUM(AD24:AE24) -> 450.4 | AG24: =AF24/(60*24) -> 0.31277778 | AH24: =IFERROR(AE24/AF24,0) -> 0.44493783 | AI24: 24000 | AJ24: 22 | AK24: 1020 | AL24: =IF(AM24=0,0,(+AI24*AK24/1000)) -> 24480 | AM24: 557 | AN24: 2 | AO24: 0 | AP24: 33 | AQ24: 0 | AR24: 0 | AS24: 0 | AT24: 23 | AU24: 0 | AV24: =SUM(AO24:AU24) -> 56 | AW24: =+(AM24+(BR24*50/100))+(BS24*30/100)-BB24 -> 564.2 | AX24: 0 | AY24: 0 | AZ24: 0 | BA24: 0 | BB24: 0 | BC24: 0 | BD24: 13 | BE24: 0 | BF24: 0 | BG24: 0 | BH24: 19 | BI24: 0 | BJ24: =SUM(BC24:BI24) -> 32 | BK24: 23508 | BL24: =IFERROR(+BO24*1000/((BK24)*(BM24/1000)),0) -> 22.603903 | BM24: =AK24 -> 1020 | BN24: =+BK24*BM24/1000 -> 23978.16 | BO24: 542 | BP24: 0 | BQ24: 0 | BR24: =AO24-BC24 -> 0 | BS24: =(AP24+AQ24+AR24+AS24+AT24+AU24)-(BD24+BE24+BF24+BG24+BH24+BI24) -> 24 | BT24: =BR24+BS24 -> 24 | BU24: =IFERROR(+BK24/AE24,0) -> 117.30539 | BV24: =IFERROR(+BK24/(AF24),0) -> 52.193606 | BW24: =IFERROR(+(AI24-AZ24)-BK24,0) -> 492 | BX24: =IFERROR(+BW24/BK24,0) -> 0.020929045 | BY24: =IFERROR(+(AL24-BA24)-BN24,0) -> 501.84 | BZ24: =IFERROR(+BY24/BN24,0) -> 0.020929045 | CA24: =IFERROR(+AW24-(BO24),0) -> 22.2 | CB24: =IFERROR(+CA24/BO24,1) -> 0.04095941 | CC24: 0 | CD24: 0 | CE24: Aprobacion, se culmina sin novedad | CF24: APROBACION | CG24: 2 | CH24: =IFERROR((BT24*1000)/BN24,"") -> 1.0009108 | CI24: 3500 | CJ24: =IF(BW24=0,"",CI24-BW24) -> 3008 | CK24: {=_xlfn.IFS(CJ24>0,"CUMPLE",CJ24<0,"NO CUMPLE",CJ24="","")} -> CUMPLE | CL24: 21-05-2026 | CM24: {=_xlfn.IFS(CL24-C24 > 0,"CUMPLE",CL24-C24 < 0,"NO CUMPLE")} -> CUMPLE | CN24: 20000 | CO24: =BK24-CN24 -> 3508 | CP24: 0 | CQ24: CELOVEN | CR24: BOPP TRANSPARENTE
A25: 000f | B25: OF | C25: 46142 | D25: =IFERROR(VLOOKUP($A25,Hoja3!$A$3:$F$6000,2,FALSE),"") -> 000F | E25: 000f | F25: =IFERROR(VLOOKUP($A25,Hoja3!$A$3:$F$6000,6,FALSE),"") -> TODAS | G25: 0 | H25: =IFERROR(VLOOKUP($A25,Hoja3!$A$3:$F$6000,5,FALSE),"") -> MCL | I25: =IFERROR(VLOOKUP($A25,Hoja3!$A$3:$F$6000,3,FALSE),"") -> FALTA DE PEDIDOS / INSUMOS | J25: =IFERROR(VLOOKUP($A25,Hoja3!$A$3:$F$6000,4,FALSE),"") -> FALTA DE PEDIDOS / INSUMOS | K25: 0 | L25: 0 | M25: 0 | N25: 0 | O25: 0 | P25: 0 | Q25: 0 | R25: 0 | S25: 0 | T25: 0 | U25: 0 | V25: 0 | W25: 0 | X25: 0 | Y25: 0 | Z25: 0 | AA25: 0 | AB25: 0 | AC25: 21914 | AD25: =SUM(L25:AC25) -> 21914 | AE25: 0 | AF25: =SUM(AD25:AE25) -> 21914 | AG25: =AF25/(60*24) -> 15.218056 | AH25: =IFERROR(AE25/AF25,0) -> 0 | AI25: 0 | AJ25: 0 | AK25: 0 | AL25: =IF(AM25=0,0,(+AI25*AK25/1000)) -> 0 | AM25: 0 | AN25: 0 | AO25: 0 | AP25: 0 | AQ25: 0 | AR25: 0 | AS25: 0 | AT25: 0 | AU25: 0 | AV25: 0 | AW25: 0 | AX25: 0 | AY25: 0 | AZ25: 0 | BA25: 0 | BB25: 0 | BC25: 0 | BD25: 0 | BE25: 0 | BF25: 0 | BG25: 0 | BH25: 0 | BI25: 0 | BJ25: 0 | BK25: 0 | BL25: 0 | BM25: 0 | BN25: 0 | BO25: 0 | BP25: 0 | BQ25: 0 | BR25: 0 | BS25: 0 | BT25: 0 | BU25: 0 | BV25: 0 | BW25: =IFERROR(+(AI25-AZ25)-BK25,0) -> 0 | BX25: =IFERROR(+BW25/BK25,0) -> 0 | BY25: =IFERROR(+(AL25-BA25)-BN25,0) -> 0 | BZ25: =IFERROR(+BY25/BN25,0) -> 0 | CA25: =IFERROR(+AW25-(BO25),0) -> 0 | CB25: =IFERROR(+CA25/BO25,1) -> 1 | CC25: 0 | CD25: 0 | CE25: parada por falta de insumo/pedido | CF25: FALTA DE INSUMO | CG25: 0 | CH25: 0 | CI25: 0 | CJ25: 0 | CK25: 0 | CL25: 0 | CM25: {=_xlfn.IFS(CL25-C25 > 0,"CUMPLE",CL25-C25 < 0,"NO CUMPLE")} -> NO CUMPLE | CN25: 0 | CO25: =BK25-CN25 -> 0 | CP25: 0
D26: =IFERROR(VLOOKUP($A26,Hoja3!$A$3:$F$6000,2,FALSE),"") | F26: =IFERROR(VLOOKUP($A26,Hoja3!$A$3:$F$6000,6,FALSE),"") | H26: =IFERROR(VLOOKUP($A26,Hoja3!$A$3:$F$6000,5,FALSE),"") | I26: =IFERROR(VLOOKUP($A26,Hoja3!$A$3:$F$6000,3,FALSE),"") | J26: =IFERROR(VLOOKUP($A26,Hoja3!$A$3:$F$6000,4,FALSE),"") | AD26: =SUM(L26:AC26) -> 0 | AF26: =SUM(AD26:AE26) -> 0 | AG26: =AF26/(60*24) -> 0 | AH26: =IFERROR(AE26/AF26,0) -> 0 | AL26: =IF(AM26=0,0,(+AI26*AK26/1000)) -> 0 | AV26: =SUM(AO26:AU26) -> 0 | AW26: =+(AM26+(BR26*50/100))+(BS26*30/100)-BB26 -> 0 | BJ26: =SUM(BC26:BI26) -> 0 | BM26: =AK26 -> 0 | BN26: =+BK26*BM26/1000 -> 0 | BR26: =AO26-BC26 -> 0 | BS26: =(AP26+AQ26+AR26+AS26+AT26+AU26)-(BD26+BE26+BF26+BG26+BH26+BI26) -> 0 | BT26: =BR26+BS26 -> 0 | BW26: =IFERROR(+(AI26-AZ26)-BK26,0) -> 0 | BX26: =IFERROR(+BW26/BK26,0) -> 0 | BY26: =IFERROR(+(AL26-BA26)-BN26,0) -> 0 | BZ26: =IFERROR(+BY26/BN26,0) -> 0 | CA26: =IFERROR(+AW26-(BO26),0) -> 0 | CB26: =IFERROR(+CA26/BO26,1) -> 1 | CC26: 0 | CD26: 0 | CH26: =IFERROR((BT26*1000)/BN26,"") | CM26: {=_xlfn.IFS(CL26-C26 > 0,"CUMPLE",CL26-C26 < 0,"NO CUMPLE")} -> #N/A | CO26: =BK26-CN26 -> 0
I27: =IFERROR(VLOOKUP($A27,Hoja3!$A$3:$F$6000,3,FALSE),"") | J27: =IFERROR(VLOOKUP($A27,Hoja3!$A$3:$F$3998,4,FALSE),"") | AL27: =IF(AM27=0,0,(+AI27*AK27/1000)) -> 0 | AZ27: =IF(BB27=0,0,BB27/((AJ27/1000)*(AK27/1000))) -> 0 | BA27: =AZ27*BM27/1000 -> 0 | CH27: =IFERROR((BT27*1000)/BN27,"") | CJ27: =IFERROR((BT27*1000)/BN27,"") | CK27: =IFERROR((((BR27*0.5)+(BS27*0.3))*1000)/BN27,"") | CO27: =BK27-CN27 -> 0
A28: OF= OLYMPIA FINAL | E28: Numeros de trabajos= | G28: =SUM(G15:G26) -> 9 | I28: =IFERROR(VLOOKUP($A28,Hoja3!$A$3:$F$6000,3,FALSE),"") | J28: =IFERROR(VLOOKUP($A28,Hoja3!$A$3:$F$3998,4,FALSE),"") | K28: =SUM(K15:K26) -> 14344 | L28: =SUM(L15:L26) -> 600 | M28: =SUM(M15:M26) -> 515 | N28: =SUM(N15:N26) -> 380 | O28: =SUM(O15:O26) -> 160 | P28: =SUM(P15:P26) -> 440 | Q28: =SUM(Q15:Q26) -> 150 | R28: =SUM(R15:R26) -> 0 | ... AG28: =SUM(AG15:AG26) -> 20.000139 | AH28: =IFERROR(AE28/AF29,0) -> 0.10820064 | AI28: =SUM(AI15:AI26) -> 405912 | AL28: =SUM(AL15:AL26) -> 406956.07 | AM28: =SUM(AM15:AM26) -> 12994.6 | AN28: =SUM(AN15:AN26) -> 24 | AV28: =SUM(AV15:AV26) -> 1470 | AW28: =SUM(AW15:AW26) -> 13325.2 | AX28: =SUM(AX15:AX26) -> 0 | AY28: =SUM(AY15:AY26) -> 0 | AZ28: =SUM(AZ15:AZ26) -> 0 | BA28: =SUM(BA15:BA26) -> 0 | BB28: =SUM(BB15:BB26) -> 0 | BJ28: =SUM(BJ15:BJ26) -> 648 | BK28: =SUM(BK15:BK26) -> 361019 | BL28: =IFERROR(+BO28*1000/((BK28)*(BM28/1000)),0) -> 0 | BN28: =SUM(BN15:BN26) -> 360367.59 | BO28: =SUM(BO15:BO26) -> 12332 | BP28: =SUM(BP15:BP26) -> 0 | BQ28: =SUM(BQ15:BQ26) -> 0 | BR28: =SUM(BR15:BR26) -> 420 | BS28: =SUM(BS15:BS26) -> 402 | BT28: =SUM(BT15:BT26) -> 822 | BU28: =IFERROR(+BK28/AE28,0) -> 115.85232 | BV28: =BK28/(AF28-(AC28+Q28+W28)) -> 53.593866 | BW28: =IFERROR(AI28-AZ28,0)-BK28 -> 44893 | BX28: =IFERROR(+BW28/BK28,0) -> 0.1243508 | BY28: =IFERROR(AL28-BA28,0)-BN28 -> 46588.482 | BZ28: =IFERROR(+BY28/BN28,0) -> 0.12928044 | CA28: =IFERROR(+AW28-(BO28),0) -> 993.2 | CB28: =IFERROR(+CA28/BO28,0) -> 0.080538437 | CC28: =SUM(CC15:CC26) -> 0 | CD28: =SUM(CD15:CD26) -> 0 | CH28: =IFERROR((BT28*1000)/BN28,"") -> 2.2810043 | CI28: =SUM(CI15:CI26) -> 28000 | CJ28: =IFERROR((BT28*1000)/BN28,"") -> 2.2810043 | CK28: =IFERROR((((BR28*0.5)+(BS28*0.3))*1000)/BN28,"") -> 0.9173966 | CN28: =SUM(CN15:CN26) -> 319500 | CO28: =BK28-CN28 -> 41519
A29: OP= OLYMPIA PROCESO | I29: =IFERROR(VLOOKUP($A29,Hoja3!$A$3:$F$6000,3,FALSE),"") | J29: =IFERROR(VLOOKUP($A29,Hoja3!$A$3:$F$3998,4,FALSE),"") | K29: % EFICIENCIA | L29: =IFERROR(L28/AF29,0) -> 0.020833189 | M29: =IFERROR(M28/AF29,0) -> 0.01788182 | N29: =(N28/AF29) -> 0.013194353 | O29: =(O28/AF29) -> 0.005555517 | P29: =(P28/AF29) -> 0.015277672 | Q29: =(Q28/AF29) -> 0.0052082972 | R29: =(R28/AF29) -> 0 | S29: =(S28/AF29) -> 0.011805474 | T29: =(T28/AF29) -> 0.001909709 | U29: =(U28/AF29) -> 0.00052082972 | V29: =(V28/AF29) -> 0.013367963 | W29: =(W28/AF29) -> 0 | X29: =(X28/AF29) -> 0.010416594 | Y29: =(Y28/AF29) -> 0 | Z29: =(Z28/AF29) -> 0.0027777585 | AA29: =(AA28/AF29) -> 0.0020833189 | AB29: =(AB28/AF28) -> 0.010069375 | AC29: =(AC28/AF28) -> 0.76089749 | AD29: =(AD28/AF29) -> 0.89179936 | AE29: =(AE28/AF29) -> 0.10820064 | AF29: =AF28 -> 28800.2 | AG29: =AF29/60/24 -> 20.000139 | AH29: <= Tiempo dedicado | BL29: =IFERROR(+BO29*1000/((BK29)*(BM29/1000)),0) -> 0
A30: Nota: | I30: =IFERROR(VLOOKUP($A30,Hoja3!$A$3:$F$6000,3,FALSE),"") | J30: =IFERROR(VLOOKUP($A30,Hoja3!$A$3:$F$3998,4,FALSE),"") | K30: Horas | L30: =(L28/60) -> 10 | M30: =(M28/60) -> 8.5833333 | N30: =(N28/60) -> 6.3333333 | O30: =(O28/60) -> 2.6666667 | P30: =(P28/60) -> 7.3333333 | Q30: =(Q28/60) -> 2.5 | R30: =(R28/60) -> 0 | S30: =(S28/60) -> 5.6666667 | ... AF30: =(AF28/60) -> 480.00333 | AG30: =AH30/60/24 -> -0.00013888889 | AH30: =D8-(AF28) -> -0.2 | BJ30: Meta | BK30: 2000000 | BL30: m/l | BZ30: Meta Desperdicio | CB30: 0.08 | CN30: TRABAJOS QUE NO CUMPLEN CON LA FECHA DE ENTREGA | CQ30: =COUNTIF(CM15:CM119,"NO CUMPLE") -> 3
A31: EL PROMEDIO DE METROS EN TERMINOS DE EFICIENCIA POR TURNO EN FUNCION AL TIEMPO DISPONIBLE ES DE | J31: =IFERROR(BK28/(C8*3),0) -> 6016.9833 | K31: Dias | L31: =(L30/24) -> 0.41666667 | M31: =(M30/24) -> 0.35763889 | N31: =(N30/24) -> 0.26388889 | O31: =(O30/24) -> 0.11111111 | P31: =(P30/24) -> 0.30555556 | Q31: =(Q30/24) -> 0.10416667 | R31: =(R30/24) -> 0 | S31: =(S30/24) -> 0.23611111 | ... AF31: =(AF30/24) -> 20.000139 | AG31: DIAS POR TRABAJAR | CN31: TRABAJOS CUMPLEN CON LA FECHA DE ENTREGA | CQ31: =COUNTIF(CM15:CM120,"CUMPLE") -> 5
A32: EL PROMEDIO DE METROS EN TERMINOS DE EFICIENCIA POR TURNO EN FUNCION AL TIEMPO DE TRABAJO ES DE | J32: =IFERROR(BK28/(ROUND(AE31,0)*3),0) -> 60169.833
A33: =IFERROR(L30/G28,0) -> 1.1111111 | AF33: min | AG33: Hrs | AH33: Dias
AC34: Tiempo Total de Parada por Limpieza de Maquina | AF34: =Q28 -> 150 | AG34: =Q30 -> 2.5 | AH34: =Q31 -> 0.10416667
D35: PROMEDIO DE TIEMPO DE PREPARACION POR TRABAJO => | I35: =IFERROR(L28/G28,0) -> 66.666667 | P35: suspendidos
K36: Numero de aprobaciones en el mes => | O36: =COUNTIFS(Z15:Z26,">0",CF15:CF26,"APROBACION") -> 1 | P36: =COUNTIFS(Z15:Z26,">0",CF15:CF26,"SUSPENDIDO") -> 0 | R36: Trabajos suspendidos en el mes => | V36: =P36+P37 -> 0 | AC36: Tiempo Total de Parada por Produccion | AF36: =(L28+M28+N28+S28+V28+T28+U28) -> 2290 | AG36: =(L30+M30+N30+S30+V30+T30+U30) -> 38.166667 | AH36: =(L31+M31+N31+S31+V31+T31+U31) -> 1.5902778
K37: Trabajos Repetidos en el mes => | O37: =COUNTIFS(CF15:CF26,"REPETICION")+COUNTIFS(CF15:CF26,"PROCESO") -> 9 | P37: =COUNTIFS(Z15:Z27,"=0",CF15:CF27,"SUSPENDIDO") -> 0
AC38: Tiempo Total de Parada por Proceso de Apoyo | AF38: =(O28+P28+R28+W28+X28+Y28+Z28+AB28+AA28) -> 1330 | AG38: =(O30+P30+R30+W30+X30+Y30+Z30+AB30+AA30) -> 22.166667 | AH38: =(O31+P31+R31+W31+X31+Y31+Z31+AB31+AA31) -> 0.92361111
AC39: Tiempo Total de Parada por Falta de Pedido | AF39: =AC28 -> 21914 | AG39: =AC30 -> 365.23333 | AH39: =AC31 -> 15.218056
AC40: Horas TRABAJADAS | AF40: =AE28 -> 3116.2 | AG40: =AE30 -> 51.936667 | AH40: =AE31 -> 2.1640278
AD41: TOTAL | AF41: =SUM(AF34:AF40) -> 28800.2 | AG41: =SUM(AG34:AG40) -> 480.00333 | AH41: =SUM(AH34:AH40) -> 20.000139

Sheet NOVOFLEX.
A3: INFORME MENSUAL DE PRODUCCION
D4: Disponibilidad | E4: Rendimiento | F4: Calidad | I4: OEE NOVOFLEX | N4: =D5 -> 0.92923611 | O4: =E5 -> 0.8596378 | P4: =F5 -> 0.90806147
A5: NOVOFLEX | D5: =(AF72-AC72-Q72)/D7 -> 0.92923611 | E5: =((BK72/(AF72-AC72-W72-Q72))/75) -> 0.8596378 | F5: =100%-CB72 -> 0.90806147 | I5: =N4*O4*P4 -> 0.72536539
A6: MES: | B6: MARZO
A7: DIAS TRABAJADOS : | C7: 20 | D7: =C7*24*60 -> 28800 | E7: =C7*24 -> 480
A8: PEDIDO | B8: CODIGO DE MAQUINA | C8: FECHA | D8: CODIGO PRODUCTO | E8: O/P | F8: DESTINO | G8: N° DE TRABAJOS | H8: COMPAÑÍA | I8: NOMBRE DEL CLIENTE | J8: PRODUCTO | K8: CLIENTE Kg | L8: TIEMPO DE PARADAS EN MINUTOS | AD8: TOTAL TIEMPO PARADAS min. | AE8: TIEMPO EFECTIVO PRODUCCION min. | AF8: TOTAL TIEMPO PRODUCCION min. | AG8: DIAS TRABAJADOS | AH8: EFICIENCIA DE MAQUINA | AI8: ENTRADA DE MATERIA PRIMA | AZ8: SALIDA DE MATERIALES | BR8: DATOS DE TINTA Kg. | BU8: VELOCIDAD m/min. | BW8: DESPERDICIO | CE8: OBSERVACIONES
L9: PREPARACION | M9: PRE-PRENSA | N9: COLORIMETRIA | O9: CALIDAD | P9: MANTENIMIENTO | Q9: Limpieza general de Maquina | R9: PLANIFICACION | S9: LIMPIEZA DE PLANCHA | T9: LIMPIEZA DE TAMBOR CENTRAL | U9: LIMPIEZA DE RODILLO | V9: PRODUCCION | W9: PRUEBAS | X9: LOGISTICA | Y9: FALLAS ELECT | Z9: APROBACIONES | AA9: ESTANDAR DE COLOR | AB9: RRHH | AC9: FALTA DE INSUMO/PEDIDO
AI10: PELICULAS | AN10: TINTAS Kg | AW10: CONSUMO | AX10: SOLVENTE Lts | AZ10: PELICULA DEVOLUCION | BC10: TINTAS KG EN DEVOLUCION | BK10: PRODUCTO TERMINADO | BP10: SOLVENTE Lts | BR10: CONSUMO DE TINTA BLANCO | BS10: CONSUMO DE TINTA VARIAS | BT10: CONSUMO TOTAL | BU10: VELOCIDAD DE MAQUINA TEORICA ML/min. | BV10: VELOCIDAD DE MAQUINA REAL ML/min. | BW10: m/l | BY10: m2 | CA10: Kg
AI11: m/l | AJ11: GRAMAJE g/m2 | AK11: ANCHO mm | AL11: m2 | AM11: Kg | AN11: # COLORES | AO11: BLANCO | AP11: AZUL REFLEX | AQ11: MAGENTA | AR11: AMARILLO | AS11: CYAN | AT11: ROJO | AU11: OTRAS | AV11: TOTAL | AX11: PRODUCCION | AY11: LIMPIEZA | AZ11: m/l | BA11: m2 | BB11: Kg | BC11: BLANCO | BD11: AZUL REFLEX | BE11: MAGENTA | BF11: AMARILLO | BG11: CYAN | BH11: ROJO | BI11: OTRAS | BJ11: TOTAL | BK11: m/l | BL11: GRAMAJE g/m2 | BM11: ANCHO mm | BN11: m2 | BO11: Kg | BP11: PRODUCCION | BQ11: LIMPIEZA
BK12: m/l | BW12: CANT | BX12: % | BY12: CANT | BZ12: % | CA12: CANT | CB12: % | CC12: MAT. OBSERVACION | CD12: MAT. RECHAZADO | CF12: Aplic Tinta Humeda | CG12: Tipo de Trabajo | CH12: nº de pantone | CI12: M/L Estandar de Dsp | CJ12: Metros de Dsp | CK12: Cumplimiento | CL12: fecha de entrega | CM12: cumplimiento entrega | CN12: metros op | CO12: Cumplimiento | CP12: material reciclado | CQ12: Proveedor | CR12: Material
K13: Trabajos Repetidos en el mes => | AF13: +
A14: 01-6072 | B14: NF | C14: 46113 | D14: =IFERROR(VLOOKUP($A14,Hoja3!$A$3:$F$6000,2,FALSE),"") -> TMAPAL121A001 | E14: 16606 | F14: =IFERROR(VLOOKUP($A14,Hoja3!$A$3:$F$6000,6,FALSE),"") -> LAMINACION | G14: 1 | H14: =IFERROR(VLOOKUP($A14,Hoja3!$A$3:$F$6000,5,FALSE),"") -> MCL | I14: =IFERROR(VLOOKUP($A14,Hoja3!$A$3:$F$6000,3,FALSE),"") -> ALIMENTOS POLAR COMERCIAL, C.A. | J14: =IFERROR(VLOOKUP($A14,Hoja3!$A$3:$F$6000,4,FALSE),"") -> ALUMINIO LAMINADO IMPRESO MAVESA 500g | K14: 8500 | L14: =15+20 -> 35 | M14: 15 | N14: 30 | O14: 15 | P14: 0 | Q14: 0 | R14: 0 | S14: =10+15+16+15+10+15 -> 81 | T14: 10 | U14: =15+15 -> 30 | V14: =10+15+20 -> 45 | W14: 0 | X14: 0 | Y14: 0 | Z14: 0 | AA14: 0 | AB14: 0 | AC14: 0 | AD14: =SUM(L14:AC14) -> 261 | AE14: 658.8 | AF14: =SUM(AD14:AE14) -> 919.8 | AG14: =AF14/(60*24) -> 0.63875 | AH14: =IFERROR(AE14/AF14,0) -> 0.71624266 | AI14: 91250 | AJ14: 102 | AK14: 920 | AL14: =IF(AM14=0,0,(+AI14*AK14/1000)) -> 83950 | AM14: 8693.5 | AN14: 7 | AO14: 370 | AP14: 17 | AQ14: 21 | AR14: 0 | AS14: 0 | AT14: 0 | AU14: =175+41+12+12 -> 240 | AV14: =SUM(AO14:AU14) -> 648 | AW14: =+(AM14+(BR14*50/100))+(BS14*30/100)-BB14 -> 8866.8 | AX14: 0 | AY14: 0 | AZ14: 0 | BA14: 0 | BB14: 0 | BC14: 135 | BD14: 11 | BE14: 10 | BF14: 0 | BG14: 0 | BH14: 0 | BI14: =52+8+6+5 -> 71 | BJ14: =SUM(BC14:BI14) -> 227 | BK14: 89112 | BL14: =IFERROR(+BO14*1000/((BK14)*(BM14/1000)),0) -> 104.85339 | BM14: =AK14 -> 920 | BN14: =+BK14*BM14/1000 -> 81983.04 | BO14: =8726.9-130.7 -> 8596.2 | BP14: 0 | BQ14: 0 | BR14: =AO14-BC14 -> 235 | BS14: =(AP14+AQ14+AR14+AS14+AT14+AU14)-(BD14+BE14+BF14+BG14+BH14+BI14) -> 186 | BT14: =BR14+BS14 -> 421 | BU14: =IFERROR(+BK14/AE14,0) -> 135.26412 | BV14: =IFERROR(+BK14/(AF14),0) -> 96.881931 | BW14: =IFERROR(+(AI14-AZ14)-BK14,0) -> 2138 | BX14: =IFERROR(+BW14/BK14,0) -> 0.023992279 | BY14: =IFERROR(+(AL14-BA14)-BN14,0) -> 1966.96 | BZ14: =IFERROR(+BY14/BN14,0) -> 0.023992279 | CA14: =IFERROR(+AW14-(BO14),0) -> 270.6 | CB14: =IFERROR(+CA14/BO14,1) -> 0.031479026 | CC14: 0 | CD14: 0 | CE14: Se realiza produccion a 130 m/m ya que a mayor velocidad presenta arrastre de el color blanco y azul | CF14: =IFERROR((BT14*1000)/BN14,"") -> 5.1352085 | CG14: REPETICION | CH14: 2 | CI14: 3500 | CJ14: =IF(BW14=0,"",CI14-BW14) -> 1362 | CK14: {=_xlfn.IFS(CJ14>0,"CUMPLE",CJ14<0,"NO CUMPLE",CJ14="","")} -> CUMPLE | CL14: 46139 | CM14: {=_xlfn.IFS(CL14-C14 > 0,"CUMPLE",CL14-C14 < 0,"NO CUMPLE")} -> CUMPLE | CN14: 91000 | CO14: =BK14-CN14 -> -1888 | CP14: 800 | CQ14: RETANA | CR14: ALUMINIO
A15: 000lm | B15: NF | C15: 46113 | D15: =IFERROR(VLOOKUP($A15,Hoja3!$A$3:$F$6000,2,FALSE),"") -> 000LM | E15: 000lm | F15: =IFERROR(VLOOKUP($A15,Hoja3!$A$3:$F$6000,6,FALSE),"") -> LIMPIEZA | G15: 0 | H15: =IFERROR(VLOOKUP($A15,Hoja3!$A$3:$F$6000,5,FALSE),"") -> CX | I15: =IFERROR(VLOOKUP($A15,Hoja3!$A$3:$F$6000,3,FALSE),"") -> LIMPIEZA GENERAL DE MAQUINA | J15: =IFERROR(VLOOKUP($A15,Hoja3!$A$3:$F$6000,4,FALSE),"") -> LIMPIEZA GENERAL DE MAQUINA | K15: 0 | L15: 0 | M15: 0 | N15: 0 | O15: 0 | P15: 0 | Q15: 665.2 | R15: 0 | S15: 0 | T15: 0 | U15: 0 | V15: 0 | W15: 0 | X15: 0 | Y15: 0 | Z15: 0 | AA15: 0 | AB15: 0 | AC15: 0 | AD15: =SUM(L15:AC15) -> 665.2 | AE15: 0 | AF15: =SUM(AD15:AE15) -> 665.2 | AG15: =AF15/(60*24) -> 0.46194444 | AH15: =IFERROR(AE15/AF15,0) -> 0 | AI15: 0 | AJ15: 0 | AK15: 0 | AL15: =IF(AM15=0,0,(+AI15*AK15/1000)) -> 0 | AM15: 0 | AN15: 0 | AO15: 0 | AP15: 0 | AQ15: 0 | AR15: 0 | AS15: 0 | AT15: 0 | AU15: 0 | AV15: =SUM(AO15:AU15) -> 0 | AW15: =+(AM15+(BR15*50/100))+(BS15*30/100)-BB15 -> 0 | AX15: 0 | AY15: 0 | AZ15: 0 | BA15: 0 | BB15: 0 | BC15: 0 | BD15: 0 | BE15: 0 | BF15: 0 | BG15: 0 | BH15: 0 | BI15: 0 | BJ15: =SUM(BC15:BI15) -> 0 | BK15: 0 | BL15: =IFERROR(+BO15*1000/((BK15)*(BM15/1000)),0) -> 0 | BM15: =AK15 -> 0 | BN15: =+BK15*BM15/1000 -> 0 | BO15: 0 | BP15: 0 | BQ15: 0 | BR15: =AO15-BC15 -> 0 | BS15: =(AP15+AQ15+AR15+AS15+AT15+AU15)-(BD15+BE15+BF15+BG15+BH15+BI15) -> 0 | BT15: =BR15+BS15 -> 0 | BU15: =IFERROR(+BK15/AE15,0) -> 0 | BV15: =IFERROR(+BK15/(AF15),0) -> 0 | BW15: =IFERROR(+(AI15-AZ15)-BK15,0) -> 0 | BX15: =IFERROR(+BW15/BK15,0) -> 0 | BY15: =IFERROR(+(AL15-BA15)-BN15,0) -> 0 | BZ15: =IFERROR(+BY15/BN15,0) -> 0 | CA15: =IFERROR(+AW15-(BO15),0) -> 0 | CB15: =IFERROR(+CA15/BO15,1) -> 1 | CC15: 0 | CD15: 0 | CE15: se realiza limpieza general de maquina | CF15: =IFERROR((BT15*1000)/BN15,"") | CG15: LIMPIEZA | CH15: 0 | CI15: 0 | CJ15: 0 | CK15: 0 | CL15: 0 | CM15: 0 | CN15: 0 | CO15: 0 | CP15: 0
A16: 000pp | B16: NF | C16: 46113 | D16: =IFERROR(VLOOKUP($A16,Hoja3!$A$3:$F$6000,2,FALSE),"") -> 000PP | E16: 000pp | F16: =IFERROR(VLOOKUP($A16,Hoja3!$A$3:$F$6000,6,FALSE),"") -> TODAS | G16: 0 | H16: =IFERROR(VLOOKUP($A16,Hoja3!$A$3:$F$6000,5,FALSE),"") -> CX | I16: =IFERROR(VLOOKUP($A16,Hoja3!$A$3:$F$6000,3,FALSE),"") -> PARADA PROGRAMADA | J16: =IFERROR(VLOOKUP($A16,Hoja3!$A$3:$F$6000,4,FALSE),"") -> PARADA PROGRAMADA | K16: 0 | L16: 0 | M16: 0 | N16: 0 | O16: 0 | P16: 300 | Q16: 0 | R16: 0 | S16: 0 | T16: 0 | U16: 0 | V16: 0 | W16: 0 | X16: 0 | Y16: 0 | Z16: 0 | AA16: 0 | AB16: 0 | AC16: 0 | AD16: =SUM(L16:AC16) -> 300 | AE16: 0 | AF16: =SUM(AD16:AE16) -> 300 | AG16: =AF16/(60*24) -> 0.20833333 | AH16: =IFERROR(AE16/AF16,0) -> 0 | AI16: 0 | AJ16: 0 | AK16: 0 | AL16: 0 | AM16: 0 | AN16: 0 | AO16: 0 | AP16: 0 | AQ16: 0 | AR16: 0 | AS16: 0 | AT16: 0 | AU16: 0 | AV16: 0 | AW16: 0 | AX16: 0 | AY16: 0 | AZ16: 0 | BA16: 0 | BB16: 0 | BC16: 0 | BD16: 0 | BE16: 0 | BF16: 0 | BG16: 0 | BH16: 0 | BI16: 0 | BJ16: 0 | BK16: 0 | BL16: =IFERROR(+BO16*1000/((BK16)*(BM16/1000)),0) -> 0 | BM16: =AK16 -> 0 | BN16: =+BK16*BM16/1000 -> 0 | BO16: 0 | BP16: 0 | BQ16: 0 | BR16: =AO16-BC16 -> 0 | BS16: =(AP16+AQ16+AR16+AS16+AT16+AU16)-(BD16+BE16+BF16+BG16+BH16+BI16) -> 0 | BT16: =BR16+BS16 -> 0 | BU16: =IFERROR(+BK16/AE16,0) -> 0 | BV16: =IFERROR(+BK16/(AF16),0) -> 0 | BW16: =IFERROR(+(AI16-AZ16)-BK16,0) -> 0 | BX16: =IFERROR(+BW16/BK16,0) -> 0 | BY16: =IFERROR(+(AL16-BA16)-BN16,0) -> 0 | BZ16: =IFERROR(+BY16/BN16,0) -> 0 | CA16: =IFERROR(+AW16-(BO16),0) -> 0 | CB16: =IFERROR(+CA16/BO16,1) -> 1 | CC16: 0 | CD16: 0 | CE16: parada por mantenimiento y tecnico | CF16: 0 | CG16: PARADA PROGRAMADA | CH16: 0 | CI16: 0 | CJ16: 0 | CK16: 0 | CL16: 0 | CM16: 0 | CN16: 0 | CO16: =BK16-CN16 -> 0 | CP16: 0
A17: 01-6059 | B17: NF | C17: 46118 | D17: =IFERROR(VLOOKUP($A17,Hoja3!$A$3:$F$6000,2,FALSE),"") -> TXPCGU023A001 | E17: 16596 | F17: =IFERROR(VLOOKUP($A17,Hoja3!$A$3:$F$6000,6,FALSE),"") -> CORTE | G17: 1 | H17: =IFERROR(VLOOKUP($A17,Hoja3!$A$3:$F$6000,5,FALSE),"") -> CX | I17: =IFERROR(VLOOKUP($A17,Hoja3!$A$3:$F$6000,3,FALSE),"") -> PEPSI-COLA VENEZUELA, C.A. | J17: =IFERROR(VLOOKUP($A17,Hoja3!$A$3:$F$6000,4,FALSE),"") -> ETIQUETA IMPRESA GOLDEN UVA 2L | K17: 150 | L17: =180+30 -> 210 | M17: 0 | N17: 60 | O17: 20 | P17: =15+65 -> 80 | Q17: 0 | R17: 0 | S17: 20 | T17: 15 | U17: 0 | V17: =20+10 -> 30 | W17: 0 | X17: 30 | Y17: 0 | Z17: 0 | AA17: 0 | AB17: 0 | AC17: 0 | AD17: =SUM(L17:AC17) -> 465 | AE17: 39.6 | AF17: =SUM(AD17:AE17) -> 504.6 | AG17: =AF17/(60*24) -> 0.35041667 | AH17: =IFERROR(AE17/AF17,0) -> 0.078478002 | AI17: 10500 | AJ17: 21 | AK17: 1010 | AL17: =IF(AM17=0,0,(+AI17*AK17/1000)) -> 10605 | AM17: 228.5 | AN17: 7 | AO17: 0 | AP17: =13+13 -> 26 | AQ17: 0 | AR17: 0 | AS17: 0 | AT17: 13 | AU17: =10+18+16+190 -> 234 | AV17: =SUM(AO17:AU17) -> 273 | AW17: =+(AM17+(BR17*50/100))+(BS17*30/100)-BB17 -> 237.2 | AX17: 0 | AY17: 0 | AZ17: 0 | BA17: 0 | BB17: 0 | BC17: 0 | BD17: =11+12 -> 23 | BE17: 0 | BF17: 0 | BG17: 0 | BH17: 12 | BI17: =8+14+11+176 -> 209 | BJ17: =SUM(BC17:BI17) -> 244 | BK17: 7034 | BL17: =IFERROR(+BO17*1000/((BK17)*(BM17/1000)),0) -> 22.394762 | BM17: =AK17 -> 1010 | BN17: =+BK17*BM17/1000 -> 7104.34 | BO17: =165-5.9 -> 159.1 | BP17: 0 | BQ17: 0 | BR17: =AO17-BC17 -> 0 | BS17: =(AP17+AQ17+AR17+AS17+AT17+AU17)-(BD17+BE17+BF17+BG17+BH17+BI17) -> 29 | BT17: =BR17+BS17 -> 29 | BU17: =IFERROR(+BK17/AE17,0) -> 177.62626 | BV17: =IFERROR(+BK17/(AF17),0) -> 13.939754 | BW17: =IFERROR(+(AI17-AZ17)-BK17,0) -> 3466 | BX17: =IFERROR(+BW17/BK17,0) -> 0.4927495 | BY17: =IFERROR(+(AL17-BA17)-BN17,0) -> 3500.66 | BZ17: =IFERROR(+BY17/BN17,0) -> 0.4927495 | CA17: =IFERROR(+AW17-(BO17),0) -> 78.1 | CB17: =IFERROR(+CA17/BO17,1) -> 0.49088624 | CC17: 0 | CD17: 0 | CE17: rotura de material bobina virgen, movimiento de registros estac4 genera 20 kg de desp, se intercambia anilox rojo y violeta por raya en el fondo | CF17: =IFERROR((BT17*1000)/BN17,"") -> 4.0820118 | CG17: REPETICION | CH17: 5 | CI17: 3500 | CJ17: =IF(BW17=0,"",CI17-BW17) -> 34 | CK17: {=_xlfn.IFS(CJ17>0,"CUMPLE",CJ17<0,"NO CUMPLE",CJ17="","")} -> CUMPLE | CL17: 46111 | CM17: {=_xlfn.IFS(CL17-C17 > 0,"CUMPLE",CL17-C17 < 0,"NO CUMPLE")} -> NO CUMPLE | CN17: 7000 | CO17: =BK17-CN17 -> 34 | CP17: 900 | CQ17: TELEPLASTIC | CR17: BOPP POCT PERLADO
A18: 01-6060 | B18: NF | C18: 46118 | D18: =IFERROR(VLOOKUP($A18,Hoja3!$A$3:$F$6000,2,FALSE),"") -> TXPCGU023A001 | E18: 16597 | F18: =IFERROR(VLOOKUP($A18,Hoja3!$A$3:$F$6000,6,FALSE),"") -> CORTE | G18: 1 | H18: =IFERROR(VLOOKUP($A18,Hoja3!$A$3:$F$6000,5,FALSE),"") -> CX | I18: =IFERROR(VLOOKUP($A18,Hoja3!$A$3:$F$6000,3,FALSE),"") -> PEPSI-COLA VENEZUELA, C.A. | J18: =IFERROR(VLOOKUP($A18,Hoja3!$A$3:$F$6000,4,FALSE),"") -> ETIQUETA IMPRESA GOLDEN UVA 2L | K18: 150 | L18: 0 | M18: 0 | N18: 0 | O18: 0 | P18: 0 | Q18: 0 | R18: 0 | S18: =15+5 -> 20 | T18: 0 | U18: 0 | V18: 0 | W18: 0 | X18: 0 | Y18: 0 | Z18: 0 | AA18: 0 | AB18: 0 | AC18: 0 | AD18: =SUM(L18:AC18) -> 20 | AE18: 45 | AF18: =SUM(AD18:AE18) -> 65 | AG18: =AF18/(60*24) -> 0.045138889 | AH18: =IFERROR(AE18/AF18,0) -> 0.69230769 | AI18: 8300 | AJ18: 21 | AK18: 1010 | AL18: =IF(AM18=0,0,(+AI18*AK18/1000)) -> 8383 | AM18: 184 | AN18: 7 | AO18: 0 | AP18: =11+12 -> 23 | AQ18: 0 | AR18: 0 | AS18: 0 | AT18: 12 | AU18: =8+14+11+176 -> 209 | AV18: =SUM(AO18:AU18) -> 244 | AW18: =+(AM18+(BR18*50/100))+(BS18*30/100)-BB18 -> 192.7 | AX18: 0 | AY18: 0 | AZ18: 0 | BA18: 0 | BB18: 0 | BC18: 0 | BD18: =9+11 -> 20 | BE18: 0 | BF18: 0 | BG18: 0 | BH18: 11 | BI18: =6+10+6+162 -> 184 | BJ18: =SUM(BC18:BI18) -> 215 | BK18: 8000 | BL18: =IFERROR(+BO18*1000/((BK18)*(BM18/1000)),0) -> 23.762376 | BM18: =AK18 -> 1010 | BN18: =+BK18*BM18/1000 -> 8080 | BO18: 192 | BP18: 0 | BQ18: 0 | BR18: =AO18-BC18 -> 0 | BS18: =(AP18+AQ18+AR18+AS18+AT18+AU18)-(BD18+BE18+BF18+BG18+BH18+BI18) -> 29 | BT18: =BR18+BS18 -> 29 | BU18: =IFERROR(+BK18/AE18,0) -> 177.77778 | BV18: =IFERROR(+BK18/(AF18),0) -> 123.07692 | BW18: =IFERROR(+(AI18-AZ18)-BK18,0) -> 300 | BX18: =IFERROR(+BW18/BK18,0) -> 0.0375 | BY18: =IFERROR(+(AL18-BA18)-BN18,0) -> 303 | BZ18: =IFERROR(+BY18/BN18,0) -> 0.0375 | CA18: =IFERROR(+AW18-(BO18),0) -> 0.7 | CB18: =IFERROR(+CA18/BO18,1) -> 0.0036458333 | CC18: 0 | CD18: 0 | CE18: se culmina produccion sin novedad | CF18: =IFERROR((BT18*1000)/BN18,"") -> 3.5891089 | CG18: REPETICION | CH18: 0 | CI18: 3500 | CJ18: =IF(BW18=0,"",CI18-BW18) -> 3200 | CK18: {=_xlfn.IFS(CJ18>0,"CUMPLE",CJ18<0,"NO CUMPLE",CJ18="","")} -> CUMPLE | CL18: 46111 | CM18: {=_xlfn.IFS(CL18-C18 > 0,"CUMPLE",CL18-A18 < 0,"NO CUMPLE")} -> NO CUMPLE | CN18: 7000 | CO18: =BK18-CN18 -> 1000 | CP18: 0 | CQ18: TELEPLASTIC | CR18: BOPP POCT PERLADO
A19: 01-6001 | B19: NF | C19: 46118 | D19: =IFERROR(VLOOKUP($A19,Hoja3!$A$3:$F$6000,2,FALSE),"") -> TXDNTP066C001 | E19: 16547 | F19: =IFERROR(VLOOKUP($A19,Hoja3!$A$3:$F$6000,6,FALSE),"") -> LAMINACION | G19: 1 | H19: =IFERROR(VLOOKUP($A19,Hoja3!$A$3:$F$6000,5,FALSE),"") -> CX | I19: =IFERROR(VLOOKUP($A19,Hoja3!$A$3:$F$6000,3,FALSE),"") -> DISTRIBUIDORA NACIONAL 2000, C.A. | J19: =IFERROR(VLOOKUP($A19,Hoja3!$A$3:$F$6000,4,FALSE),"") -> LAMINACION IMPRESA CAFÉ ANZOATEGUI TOSTADO Y MOLIDO PREMIUM 500g | K19: 330 | L19: =30+60+30 -> 120 | M19: 70 | N19: 30 | O19: 20 | P19: 20 | Q19: 0 | R19: 0 | S19: =20+20 -> 40 | T19: 0 | U19: 0 | V19: =15 -> 15 | W19: 0 | X19: 0 | Y19: 0 | Z19: 0 | AA19: 0 | AB19: 0 | AC19: 0 | AD19: =SUM(L19:AC19) -> 315 | AE19: 90 | AF19: =SUM(AD19:AE19) -> 405 | AG19: =AF19/(60*24) -> 0.28125 | AH19: =IFERROR(AE19/AF19,0) -> 0.22222222 | AI19: 21200 | AJ19: 18 | AK19: 1000 | AL19: =IF(AM19=0,0,(+AI19*AK19/1000)) -> 21200 | AM19: 387 | AN19: 6 | AO19: 50 | AP19: 0 | AQ19: 25 | AR19: 16 | AS19: 0 | AT19: 10 | AU19: =22+15 -> 37 | AV19: =SUM(AO19:AU19) -> 138 | AW19: =+(AM19+(BR19*50/100))+(BS19*30/100)-BB19 -> 400.4 | AX19: 0 | AY19: 0 | AZ19: 0 | BA19: 0 | BB19: 0 | BC19: 40 | BD19: 0 | BE19: 21 | BF19: 8 | BG19: 0 | BH19: 7 | BI19: =13+11 -> 24 | BJ19: =SUM(BC19:BI19) -> 100 | BK19: 17264 | BL19: =IFERROR(+BO19*1000/((BK19)*(BM19/1000)),0) -> 18.75 | BM19: =AK19 -> 1000 | BN19: =+BK19*BM19/1000 -> 17264 | BO19: =345-21.3 -> 323.7 | BP19: 0 | BQ19: 0 | BR19: =AO19-BC19 -> 10 | BS19: =(AP19+AQ19+AR19+AS19+AT19+AU19)-(BD19+BE19+BF19+BG19+BH19+BI19) -> 28 | BT19: =BR19+BS19 -> 38 | BU19: =IFERROR(+BK19/AE19,0) -> 191.82222 | BV19: =IFERROR(+BK19/(AF19),0) -> 42.62716 | BW19: =IFERROR(+(AI19-AZ19)-BK19,0) -> 3936 | BX19: =IFERROR(+BW19/BK19,0) -> 0.22798888 | BY19: =IFERROR(+(AL19-BA19)-BN19,0) -> 3936 | BZ19: =IFERROR(+BY19/BN19,0) -> 0.22798888 | CA19: =IFERROR(+AW19-(BO19),0) -> 76.7 | CB19: =IFERROR(+CA19/BO19,1) -> 0.23694779 | CC19: 0 | CD19: 0 | CE19: vacio en manga color negro, falla en los extremos color rojo se cambia a daptador, limpieza color magenta y negro | CF19: =IFERROR((BT19*1000)/BN19,"") -> 2.2011121 | CG19: REPETICION | CH19: 1 | CI19: 3500 | CJ19: =IF(BW19=0,"",CI19-BW19) -> -436 | CK19: {=_xlfn.IFS(CJ19>0,"CUMPLE",CJ19<0,"NO CUMPLE",CJ19="","")} -> NO CUMPLE | CL19: 46143 | CM19: {=_xlfn.IFS(CL19-C19 > 0,"CUMPLE",CL19-A19 < 0,"NO CUMPLE")} -> CUMPLE | CN19: 18000 | CO19: =BK19-CN19 -> -736 | CP19: 1200 | CQ19: TELEPLASTIC | CR19: BOPP OCTH MATE
A20: 01-6023 | B20: NF | C20: 46119 | D20: =IFERROR(VLOOKUP($A20,Hoja3!$A$3:$F$6000,2,FALSE),"") -> TMAHSC083C003 | E20: 16567 | F20: =IFERROR(VLOOKUP($A20,Hoja3!$A$3:$F$6000,6,FALSE),"") -> LAMINACION | G20: 1 | H20: =IFERROR(VLOOKUP($A20,Hoja3!$A$3:$F$6000,5,FALSE),"") -> MCL | I20: =IFERROR(VLOOKUP($A20,Hoja3!$A$3:$F$6000,3,FALSE),"") -> ALIMENTOS HEINZ, C.A. | J20: =IFERROR(VLOOKUP($A20,Hoja3!$A$3:$F$6000,4,FALSE),"") -> LAMINACION IMPRESA GELATINA SONRISSA FRAMBUESA 132g. | K20: 1800 | L20: =30+60+25 -> 115 | M20: 0 | N20: 50 | O20: 0 | P20: 0 | Q20: 0 | R20: 0 | S20: 10 | T20: 10 | U20: 0 | V20: 0 | W20: 0 | X20: 0 | Y20: 0 | Z20: 355 | AA20: 25 | AB20: 0 | AC20: 0 | AD20: =SUM(L20:AC20) -> 565 | AE20: 95.4 | AF20: =SUM(AD20:AE20) -> 660.4 | AG20: =AF20/(60*24) -> 0.45861111 | AH20: =IFERROR(AE20/AF20,0) -> 0.1444579 | AI20: 23200 | AJ20: 18 | AK20: 1000 | AL20: =IF(AM20=0,0,(+AI20*AK20/1000)) -> 23200 | AM20: 432.7 | AN20: 6 | AO20: 60 | AP20: 17 | AQ20: 30 | AR20: 16 | AS20: 20 | AT20: 0 | AU20: 13 | AV20: =SUM(AO20:AU20) -> 156 | AW20: =+(AM20+(BR20*50/100))+(BS20*30/100)-BB20 -> 458.8 | AX20: 0 | AY20: 0 | AZ20: 0 | BA20: 0 | BB20: 0 | BC20: 30 | BD20: 14 | BE20: 9 | BF20: 10 | BG20: 17 | BH20: 0 | BI20: 9 | BJ20: =SUM(BC20:BI20) -> 89 | BK20: 21008 | BL20: =IFERROR(+BO20*1000/((BK20)*(BM20/1000)),0) -> 19.040366 | BM20: =AK20 -> 1000 | BN20: =+BK20*BM20/1000 -> 21008 | BO20: =418.6-18.6 -> 400 | BP20: 0 | BQ20: 0 | BR20: =AO20-BC20 -> 30 | BS20: =(AP20+AQ20+AR20+AS20+AT20+AU20)-(BD20+BE20+BF20+BG20+BH20+BI20) -> 37 | BT20: =BR20+BS20 -> 67 | BU20: =IFERROR(+BK20/AE20,0) -> 220.20964 | BV20: =IFERROR(+BK20/(AF20),0) -> 31.811024 | BW20: =IFERROR(+(AI20-AZ20)-BK20,0) -> 2192 | BX20: =IFERROR(+BW20/BK20,0) -> 0.1043412 | BY20: =IFERROR(+(AL20-BA20)-BN20,0) -> 2192 | BZ20: =IFERROR(+BY20/BN20,0) -> 0.1043412 | CA20: =IFERROR(+AW20-(BO20),0) -> 58.8 | CB20: =IFERROR(+CA20/BO20,1) -> 0.147 | CC20: 0 | CD20: 0 | CE20: Aprobacion se realiza estandar de color, franjas verticales en color magenta, se sacan varias muestras ajustando color cyan magenta y negro | CF20: =IFERROR((BT20*1000)/BN20,"") -> 3.1892612 | CG20: APROBACION | CH20: 1 | CI20: 3500 | CJ20: =IF(BW20=0,"",CI20-BW20) -> 1308 | CK20: {=_xlfn.IFS(CJ20>0,"CUMPLE",CJ20<0,"NO CUMPLE",CJ20="","")} -> CUMPLE | CL20: 46108 | CM20: {=_xlfn.IFS(CL20-C20 > 0,"CUMPLE",CL20-A20 < 0,"NO CUMPLE")} -> NO CUMPLE | CN20: 21500 | CO20: =BK20-CN20 -> -492 | CP20: 1200 | CQ20: OPPFILM | CR20: BOPP SC TRANSPARENTE
A21: 01-6017 | B21: NF | C21: 46120 | D21: =IFERROR(VLOOKUP($A21,Hoja3!$A$3:$F$6000,2,FALSE),"") -> TMAHSK086A002 | E21: 16565 | F21: =IFERROR(VLOOKUP($A21,Hoja3!$A$3:$F$6000,6,FALSE),"") -> LAMINACION | G21: 1 | H21: =IFERROR(VLOOKUP($A21,Hoja3!$A$3:$F$6000,5,FALSE),"") -> MCL | I21: =IFERROR(VLOOKUP($A21,Hoja3!$A$3:$F$6000,3,FALSE),"") -> ALIMENTOS HEINZ, C.A. | J21: =IFERROR(VLOOKUP($A21,Hoja3!$A$3:$F$6000,4,FALSE),"") -> LAMINACION IMPRESA SACHET KETCHUP 10g (frente) | K21: 4600 | L21: 27.5 | M21: 0 | N21: =76+5 -> 81 | O21: 0 | P21: 50 | Q21: 0 | R21: 0 | S21: 62 | T21: 10 | U21: 0 | V21: 0 | W21: 0 | X21: 10 | Y21: 0 | Z21: 70 | AA21: 20 | AB21: 0 | AC21: 0 | AD21: =SUM(L21:AC21) -> 330.5 | AE21: 267 | AF21: =SUM(AD21:AE21) -> 597.5 | AG21: =AF21/(60*24) -> 0.41493056 | AH21: =IFERROR(AE21/AF21,0) -> 0.44686192 | AI21: =111575/2 -> 55787.5 | AJ21: 17 | AK21: 990 | AL21: =IF(AM21=0,0,(+AI21*AK21/1000)) -> 55229.625 | AM21: =1853/2 -> 926.5 | AN21: 6 | AO21: 430 | AP21: 0 | AQ21: 38 | AR21: 22 | AS21: 23 | AT21: 140 | AU21: 24 | AV21: =SUM(AO21:AU21) -> 677 | AW21: =+(AM21+(BR21*50/100))+(BS21*30/100)-BB21 -> 1047.5 | AX21: 0 | AY21: 0 | AZ21: 0 | BA21: 0 | BB21: 0 | BC21: 254 | BD21: 0 | BE21: 21 | BF21: 14 | BG21: 14 | BH21: 72 | BI21: 16 | BJ21: =SUM(BC21:BI21) -> 391 | BK21: =109930/2 -> 54965 | BL21: =IFERROR(+BO21*1000/((BK21)*(BM21/1000)),0) -> 18.643636 | BM21: =AK21 -> 990 | BN21: =+BK21*BM21/1000 -> 54415.35 | BO21: =2029/2 -> 1014.5 | BP21: 0 | BQ21: 0 | BR21: =AO21-BC21 -> 176 | BS21: =(AP21+AQ21+AR21+AS21+AT21+AU21)-(BD21+BE21+BF21+BG21+BH21+BI21) -> 110 | BT21: =BR21+BS21 -> 286 | BU21: =IFERROR(+BK21/AE21,0) -> 205.86142 | BV21: =IFERROR(+BK21/(AF21),0) -> 91.991632 | BW21: =IFERROR(+(AI21-AZ21)-BK21,0) -> 822.5 | BX21: =IFERROR(+BW21/BK21,0) -> 0.014964068 | BY21: =IFERROR(+(AL21-BA21)-BN21,0) -> 814.275 | BZ21: =IFERROR(+BY21/BN21,0) -> 0.014964068 | CA21: =IFERROR(+AW21-(BO21),0) -> 33 | CB21: =IFERROR(+CA21/BO21,1) -> 0.032528339 | CC21: 0 | CD21: 0 | CE21: Aprobacion, efecto telaraña color cyan, sucio en cyan y negro, se realiza estandar de colores | CF21: =IFERROR((BT21*1000)/BN21,"") -> 5.2558699 | CG21: APROBACION | CH21: 1 | CI21: 3500 | CJ21: =IF(BW21=0,"",CI21-BW21) -> 2677.5 | CK21: {=_xlfn.IFS(CJ21>0,"CUMPLE",CJ21<0,"NO CUMPLE",CJ21="","")} -> CUMPLE | CL21: 46094 | CM21: {=_xlfn.IFS(CL21-C21 > 0,"CUMPLE",CL21-A21 < 0,"NO CUMPLE")} -> NO CUMPLE | CN21: 55000 | CO21: =BK21-CN21 -> -35 | CP21: 950 | CQ21: FLEXAM | CR21: FLEX PET TRANSPARENTE
A22: 01-6018 | B22: NF | C22: 46119 | D22: =IFERROR(VLOOKUP($A22,Hoja3!$A$3:$F$6000,2,FALSE),"") -> TMAHSK086B003 | E22: 16565 | F22: =IFERROR(VLOOKUP($A22,Hoja3!$A$3:$F$6000,6,FALSE),"") -> LAMINACION | G22: 0 | H22: =IFERROR(VLOOKUP($A22,Hoja3!$A$3:$F$6000,5,FALSE),"") -> MCL | I22: =IFERROR(VLOOKUP($A22,Hoja3!$A$3:$F$6000,3,FALSE),"") -> ALIMENTOS HEINZ, C.A. | J22: =IFERROR(VLOOKUP($A22,Hoja3!$A$3:$F$6000,4,FALSE),"") -> LAMINACION IMPRESA SACHET KETCHUP 10g (dorso) | K22: 4600 | L22: 27.5 | M22: 0 | N22: =76+5 -> 81 | O22: 0 | P22: =20+15 -> 35 | Q22: 0 | R22: 0 | S22: 62 | T22: 10 | U22: 0 | V22: 0 | W22: 0 | X22: 10 | Y22: 0 | Z22: 70 | AA22: 25 | AB22: 0 | AC22: 0 | AD22: =SUM(L22:AC22) -> 320.5 | AE22: 267 | AF22: =SUM(AD22:AE22) -> 587.5 | AG22: =AF22/(60*24) -> 0.40798611 | AH22: =IFERROR(AE22/AF22,0) -> 0.45446809 | AI22: 55788 | AJ22: 17 | AK22: 990 | AL22: =IF(AM22=0,0,(+AI22*AK22/1000)) -> 55230.12 | AM22: 926.5 | AN22: 6 | AO22: 254 | AP22: 0 | AQ22: 21 | AR22: 14 | AS22: 14 | AT22: 72 | AU22: 16 | AV22: =SUM(AO22:AU22) -> 391 | AW22: =+(AM22+(BR22*50/100))+(BS22*30/100)-BB22 -> 1047.5 | AX22: 0 | AY22: 0 | AZ22: 0 | BA22: 0 | BB22: 0 | BC22: 78 | BD22: 0 | BE22: 4 | BF22: 6 | BG22: 5 | BH22: 4 | BI22: 8 | BJ22: =SUM(BC22:BI22) -> 105 | BK22: 54965 | BL22: =IFERROR(+BO22*1000/((BK22)*(BM22/1000)),0) -> 18.643636 | BM22: =AK22 -> 990 | BN22: =+BK22*BM22/1000 -> 54415.35 | BO22: 1014.5 | BP22: 0 | BQ22: 0 | BR22: =AO22-BC22 -> 176 | BS22: =(AP22+AQ22+AR22+AS22+AT22+AU22)-(BD22+BE22+BF22+BG22+BH22+BI22) -> 110 | BT22: =BR22+BS22 -> 286 | BU22: =IFERROR(+BK22/AE22,0) -> 205.86142 | BV22: =IFERROR(+BK22/(AF22),0) -> 93.557447 | BW22: =IFERROR(+(AI22-AZ22)-BK22,0) -> 823 | BX22: =IFERROR(+BW22/BK22,0) -> 0.014973165 | BY22: =IFERROR(+(AL22-BA22)-BN22,0) -> 814.77 | BZ22: =IFERROR(+BY22/BN22,0) -> 0.014973165 | CA22: =IFERROR(+AW22-(BO22),0) -> 33 | CB22: =IFERROR(+CA22/BO22,1) -> 0.032528339 | CC22: 0 | CD22: 0 | CE22: Aprobacion, efecto telaraña color cyan, sucio en cyan y negro, se realiza estandar de colores | CF22: =IFERROR((BT22*1000)/BN22,"") -> 5.2558699 | CH22: 0 | CI22: 3500 | CJ22: =IF(BW22=0,"",CI22-BW22) -> 2677 | CK22: {=_xlfn.IFS(CJ22>0,"CUMPLE",CJ22<0,"NO CUMPLE",CJ22="","")} -> CUMPLE | CL22: 46094 | CM22: {=_xlfn.IFS(CL22-C22 > 0,"CUMPLE",CL22-A22 < 0,"NO CUMPLE")} -> NO CUMPLE | CN22: 55000 | CO22: =BK22-CN22 -> -35 | CP22: 950 | CQ22: FLEXAM | CR22: FLEX PET TRANSPARENTE
A23: 11-0122 | B23: NF | C23: 46120 | D23: =IFERROR(VLOOKUP($A23,Hoja3!$A$3:$F$6000,2,FALSE),"") -> TXAMMA040A001 | E23: 16614 | F23: =IFERROR(VLOOKUP($A23,Hoja3!$A$3:$F$6000,6,FALSE),"") -> LAMINACION | G23: 1 | H23: =IFERROR(VLOOKUP($A23,Hoja3!$A$3:$F$6000,5,FALSE),"") -> CX | I23: =IFERROR(VLOOKUP($A23,Hoja3!$A$3:$F$6000,3,FALSE),"") -> AMACORP, C.A. | J23: =IFERROR(VLOOKUP($A23,Hoja3!$A$3:$F$6000,4,FALSE),"") -> ETIQUETA LAMINADA IMPRESA MAYONESA AMACORP 175g | K23: 500 | L23: =20+20 -> 40 | M23: =30+15 -> 45 | N23: 0 | O23: 0 | P23: 0 | Q23: 0 | R23: 0 | S23: =15+10 -> 25 | T23: 0 | U23: 0 | V23: 0 | W23: 0 | X23: 15 | Y23: 0 | Z23: 55 | AA23: 50 | AB23: 0 | AC23: 0 | AD23: =SUM(L23:AC23) -> 230 | AE23: 70.2 | AF23: =SUM(AD23:AE23) -> 300.2 | AG23: =AF23/(60*24) -> 0.20847222 | AH23: =IFERROR(AE23/AF23,0) -> 0.2338441 | AI23: 18000 | AJ23: 18 | AK23: 1090 | AL23: =IF(AM23=0,0,(+AI23*AK23/1000)) -> 19620 | AM23: 372 | AN23: 5 | AO23: 108 | AP23: 0 | AQ23: 30 | AR23: 30 | AS23: 34 | AT23: 0 | AU23: 28 | AV23: =SUM(AO23:AU23) -> 230 | AW23: =+(AM23+(BR23*50/100))+(BS23*30/100)-BB23 -> 417.5 | AX23: 0 | AY23: 0 | AZ23: 0 | BA23: 0 | BB23: 0 | BC23: 35 | BD23: 0 | BE23: 24 | BF23: 24 | BG23: 23 | BH23: 0 | BI23: 21 | BJ23: =SUM(BC23:BI23) -> 127 | BK23: 7781 | BL23: =IFERROR(+BO23*1000/((BK23)*(BM23/1000)),0) -> 22.520159 | BM23: =AK23 -> 1090 | BN23: =+BK23*BM23/1000 -> 8481.29 | BO23: =297-106 -> 191 | BP23: 0 | BQ23: 0 | BR23: =AO23-BC23 -> 73 | BS23: =(AP23+AQ23+AR23+AS23+AT23+AU23)-(BD23+BE23+BF23+BG23+BH23+BI23) -> 30 | BT23: =BR23+BS23 -> 103 | BU23: =IFERROR(+BK23/AE23,0) -> 110.84046 | BV23: =IFERROR(+BK23/(AF23),0) -> 25.919387 | BW23: =IFERROR(+(AI23-AZ23)-BK23,0) -> 10219 | BX23: =IFERROR(+BW23/BK23,0) -> 1.3133273 | BY23: =IFERROR(+(AL23-BA23)-BN23,0) -> 11138.71 | BZ23: =IFERROR(+BY23/BN23,0) -> 1.3133273 | CA23: =IFERROR(+AW23-(BO23),0) -> 226.5 | CB23: =IFERROR(+CA23/BO23,1) -> 1.1858639 | CC23: 0 | CD23: 0 | CE23: Aprobacion, problemas de registros en negro y cyan generando 2300 m de desperdicio en el cuadre, bob 1 en observacion ya que el registrio del cyan sale movido un poco mas de lo que acepto el cliente , se realiza estandar de color, 106 kg fuera de registro tabla nutricional | CF23: =IFERROR((BT23*1000)/BN23,"") -> 12.144379 | CG23: APROBACION | CH23: 0 | CI23: 3500 | CJ23: =IF(BW23=0,"",CI23-BW23) -> -6719 | CK23: {=_xlfn.IFS(CJ23>0,"CUMPLE",CJ23<0,"NO CUMPLE",CJ23="","")} -> NO CUMPLE | CL23: 46115 | CM23: {=_xlfn.IFS(CL23-C23 > 0,"CUMPLE",CL23-C23 < 0,"NO CUMPLE")} -> NO CUMPLE | CN23: 13000 | CO23: =BK23-CN23 -> -5219 | CP23: 800 | CQ23: OPPFILM | CR23: BOPP SC TRANSPARENTE
A24: 11-0123 | B24: NF | C24: 46120 | D24: =IFERROR(VLOOKUP($A24,Hoja3!$A$3:$F$6000,2,FALSE),"") -> TXAMMA040B001 | E24: 16613 | F24: =IFERROR(VLOOKUP($A24,Hoja3!$A$3:$F$6000,6,FALSE),"") -> LAMINACION | G24: 1 | H24: =IFERROR(VLOOKUP($A24,Hoja3!$A$3:$F$6000,5,FALSE),"") -> CX | I24: =IFERROR(VLOOKUP($A24,Hoja3!$A$3:$F$6000,3,FALSE),"") -> AMACORP, C.A. | J24: =IFERROR(VLOOKUP($A24,Hoja3!$A$3:$F$6000,4,FALSE),"") -> ETIQUETA LAMINADA IMPRESA MAYONESA AMACORP 445g | K24: 600 | L24: =25+45+25 -> 95 | M24: 30 | N24: 0 | O24: 0 | P24: 50 | Q24: 0 | R24: 0 | S24: 0 | T24: 0 | U24: 0 | V24: 0 | W24: 0 | X24: 0 | Y24: 0 | Z24: 55 | AA24: 30 | AB24: 0 | AC24: 0 | AD24: =SUM(L24:AC24) -> 260 | AE24: 70.2 | AF24: =SUM(AD24:AE24) -> 330.2 | AG24: =AF24/(60*24) -> 0.22930556 | AH24: =IFERROR(AE24/AF24,0) -> 0.21259843 | AI24: 15600 | AJ24: 18 | AK24: 1090 | AL24: =IF(AM24=0,0,(+AI24*AK24/1000)) -> 17004 | AM24: 315 | AN24: 5 | AO24: 230 | AP24: 0 | AQ24: 10 | AR24: 13 | AS24: 13 | AT24: 0 | AU24: 11 | AV24: =SUM(AO24:AU24) -> 277 | AW24: =+(AM24+(BR24*50/100))+(BS24*30/100)-BB24 -> 361.8 | AX24: 0 | AY24: 0 | AZ24: 0 | BA24: 0 | BB24: 0 | BC24: 152 | BD24: 0 | BE24: 5 | BF24: 6 | BG24: 4 | BH24: 0 | BI24: 6 | BJ24: =SUM(BC24:BI24) -> 173 | BK24: 13457 | BL24: =IFERROR(+BO24*1000/((BK24)*(BM24/1000)),0) -> 20.841102 | BM24: =AK24 -> 1090 | BN24: =+BK24*BM24/1000 -> 14668.13 | BO24: =318-12.3 -> 305.7 | BP24: 0 | BQ24: 0 | BR24: =AO24-BC24 -> 78 | BS24: =(AP24+AQ24+AR24+AS24+AT24+AU24)-(BD24+BE24+BF24+BG24+BH24+BI24) -> 26 | BT24: =BR24+BS24 -> 104 | BU24: =IFERROR(+BK24/AE24,0) -> 191.69516 | BV24: =IFERROR(+BK24/(AF24),0) -> 40.754088 | BW24: =IFERROR(+(AI24-AZ24)-BK24,0) -> 2143 | BX24: =IFERROR(+BW24/BK24,0) -> 0.15924798 | BY24: =IFERROR(+(AL24-BA24)-BN24,0) -> 2335.87 | BZ24: =IFERROR(+BY24/BN24,0) -> 0.15924798 | CA24: =IFERROR(+AW24-(BO24),0) -> 56.1 | CB24: =IFERROR(+CA24/BO24,1) -> 0.18351325 | CC24: 0 | CD24: 0 | CE24: Aprobacion, se realiza estandar de color | CF24: =IFERROR((BT24*1000)/BN24,"") -> 7.0902017 | CG24: APROBACION | CH24: 0 | CI24: 3500 | CJ24: =IF(BW24=0,"",CI24-BW24) -> 1357 | CK24: {=_xlfn.IFS(CJ24>0,"CUMPLE",CJ24<0,"NO CUMPLE",CJ24="","")} -> CUMPLE | CL24: 46115 | CM24: {=_xlfn.IFS(CL24-C24 > 0,"CUMPLE",CL24-C24 < 0,"NO CUMPLE")} -> NO CUMPLE | CN24: 13500 | CO24: =BK24-CN24 -> -43 | CP24: 900 | CQ24: OPPFILM | CR24: BOPP SC TRANSPARENTE
A25: 000PR | B25: NF | C25: 46121 | D25: PRUEBA | E25: PR-3852 | F25: =IFERROR(VLOOKUP($A25,Hoja3!$A$3:$F$6000,6,FALSE),"") -> PRUEBA | G25: 0 | H25: =IFERROR(VLOOKUP($A25,Hoja3!$A$3:$F$6000,5,FALSE),"") -> CX | I25: FINA ARROZ C.A | J25: EMPAQUE IMPRESO ARROZ LOLA 800g | K25: 0 | L25: =25+20 -> 45 | M25: 0 | N25: 0 | O25: 0 | P25: 45 | Q25: 0 | R25: 0 | S25: 0 | T25: 0 | U25: 0 | V25: 45 | W25: 0 | X25: 40 | Y25: 0 | Z25: 210 | AA25: 0 | AB25: 0 | AC25: 0 | AD25: =SUM(L25:AC25) -> 385 | AE25: 15 | AF25: =SUM(AD25:AE25) -> 400 | AG25: =AF25/(60*24) -> 0.27777778 | AH25: =IFERROR(AE25/AF25,0) -> 0.0375 | AI25: 1800 | AJ25: 66 | AK25: 1020 | AL25: =IF(AM25=0,0,(+AI25*AK25/1000)) -> 1836 | AM25: 138 | AN25: 7 | AO25: 122 | AP25: 9 | AQ25: 10 | AR25: 7 | AS25: 9 | AT25: 0 | AU25: =6+139 -> 145 | AV25: =SUM(AO25:AU25) -> 302 | AW25: =+(AM25+(BR25*50/100))+(BS25*30/100)-BB25 -> 142.1 | AX25: 0 | AY25: 0 | AZ25: 0 | BA25: 0 | BB25: 0 | BC25: 118 | BD25: 8 | BE25: 9 | BF25: 6 | BG25: 8 | BH25: 0 | BI25: =5+137 -> 142 | BJ25: =SUM(BC25:BI25) -> 291 | BK25: 900 | BL25: =IFERROR(+BO25*1000/((BK25)*(BM25/1000)),0) -> 71.895425 | BM25: =AK25 -> 1020 | BN25: =+BK25*BM25/1000 -> 918 | BO25: 66 | BP25: 0 | BQ25: 0 | BR25: =AO25-BC25 -> 4 | BS25: =(AP25+AQ25+AR25+AS25+AT25+AU25)-(BD25+BE25+BF25+BG25+BH25+BI25) -> 7 | BT25: =BR25+BS25 -> 11 | BU25: =IFERROR(+BK25/AE25,0) -> 60 | BV25: =IFERROR(+BK25/(AF25),0) -> 2.25 | BW25: =IFERROR(+(AI25-AZ25)-BK25,0) -> 900 | BX25: =IFERROR(+BW25/BK25,0) -> 1 | BY25: =IFERROR(+(AL25-BA25)-BN25,0) -> 918 | BZ25: =IFERROR(+BY25/BN25,0) -> 1 | CA25: =IFERROR(+AW25-(BO25),0) -> 76.1 | CB25: =IFERROR(+CA25/BO25,1) -> 1.1530303 | CC25: 0 | CD25: 0 | CE25: Aprobacion, se evalua condiciones de materia prima | CF25: =IFERROR((BT25*1000)/BN25,"") -> 11.982571 | CG25: PRUEBA | CH25: 1 | CI25: 3500 | CJ25: =IF(BW25=0,"",CI25-BW25) -> 2600 | CK25: {=_xlfn.IFS(CJ25>0,"CUMPLE",CJ25<0,"NO CUMPLE",CJ25="","")} -> CUMPLE | CL25: 46132 | CM25: {=_xlfn.IFS(CL25-C25 > 0,"CUMPLE",CL25-C25 < 0,"NO CUMPLE")} -> CUMPLE | CN25: 700 | CO25: =BK25-CN25 -> 200 | CP25: 700 | CQ25: PLASTICOS.DE.EMPAQUE | CR25: FILM PE TRANSPARENTE
A26: 01-6076 | B26: NF | C26: 46121 | D26: =IFERROR(VLOOKUP($A26,Hoja3!$A$3:$F$6000,2,FALSE),"") -> TXAFAL057A001 | E26: 16617 | F26: =IFERROR(VLOOKUP($A26,Hoja3!$A$3:$F$6000,6,FALSE),"") -> CORTE | G26: 1 | H26: =IFERROR(VLOOKUP($A26,Hoja3!$A$3:$F$6000,5,FALSE),"") -> CX | I26: =IFERROR(VLOOKUP($A26,Hoja3!$A$3:$F$6000,3,FALSE),"") -> FINA ARROZ C.A | J26: =IFERROR(VLOOKUP($A26,Hoja3!$A$3:$F$6000,4,FALSE),"") -> EMPAQUE IMPRESO ARROZ LOLA 800g | K26: 500 | L26: 0 | M26: 0 | N26: =15+15+25 -> 55 | O26: 0 | P26: 0 | Q26: 0 | R26: 0 | S26: 0 | T26: 0 | U26: 0 | V26: 15 | W26: 0 | X26: 0 | Y26: 0 | Z26: 0 | AA26: 35 | AB26: 0 | AC26: 0 | AD26: =SUM(L26:AC26) -> 105 | AE26: 180 | AF26: =SUM(AD26:AE26) -> 285 | AG26: =AF26/(60*24) -> 0.19791667 | AH26: =IFERROR(AE26/AF26,0) -> 0.63157895 | AI26: 10900 | AJ26: 55 | AK26: 984 | AL26: =IF(AM26=0,0,(+AI26*AK26/1000)) -> 10725.6 | AM26: 590.5 | AN26: 7 | AO26: 165 | AP26: 12 | AQ26: 17 | AR26: 12 | AS26: 15 | AT26: 0 | AU26: =12+161 -> 173 | AV26: =SUM(AO26:AU26) -> 394 | AW26: =+(AM26+(BR26*50/100))+(BS26*30/100)-BB26 -> 613.9 | AX26: 0 | AY26: 0 | AZ26: 0 | BA26: 0 | BB26: 0 | BC26: 135 | BD26: 9 | BE26: 12 | BF26: 7 | BG26: 13 | BH26: 0 | BI26: =9+151 -> 160 | BJ26: =SUM(BC26:BI26) -> 336 | BK26: 9190 | BL26: =IFERROR(+BO26*1000/((BK26)*(BM26/1000)),0) -> 54.185798 | BM26: =AK26 -> 984 | BN26: =+BK26*BM26/1000 -> 9042.96 | BO26: 490 | BP26: 0 | BQ26: 0 | BR26: =AO26-BC26 -> 30 | BS26: =(AP26+AQ26+AR26+AS26+AT26+AU26)-(BD26+BE26+BF26+BG26+BH26+BI26) -> 28 | BT26: =BR26+BS26 -> 58 | BU26: =IFERROR(+BK26/AE26,0) -> 51.055556 | BV26: =IFERROR(+BK26/(AF26),0) -> 32.245614 | BW26: =IFERROR(+(AI26-AZ26)-BK26,0) -> 1710 | BX26: =IFERROR(+BW26/BK26,0) -> 0.18607182 | BY26: =IFERROR(+(AL26-BA26)-BN26,0) -> 1682.64 | BZ26: =IFERROR(+BY26/BN26,0) -> 0.18607182 | CA26: =IFERROR(+AW26-(BO26),0) -> 123.9 | CB26: =IFERROR(+CA26/BO26,1) -> 0.25285714 | CC26: 0 | CD26: 0 | CE26: Aprobacion, se realiza estandar de color, | CF26: =IFERROR((BT26*1000)/BN26,"") -> 6.4138291 | CG26: APROBACION | CH26: 1 | CI26: 3500 | CJ26: =IF(BW26=0,"",CI26-BW26) -> 1790 | CK26: {=_xlfn.IFS(CJ26>0,"CUMPLE",CJ26<0,"NO CUMPLE",CJ26="","")} -> CUMPLE | CL26: 46132 | CM26: {=_xlfn.IFS(CL26-C26 > 0,"CUMPLE",CL26-C26 < 0,"NO CUMPLE")} -> CUMPLE | CN26: 10000 | CO26: =BK26-CN26 -> -810 | CP26: 700 | CQ26: PLASTICOS.DEL.LITORAL | CR26: PE COEXT TRANSPARENTE
A27: 01-6061 | B27: NF | C27: 46122 | D27: =IFERROR(VLOOKUP($A27,Hoja3!$A$3:$F$6000,2,FALSE),"") -> TXCVNB044A001 | E27: 16601C1 | F27: =IFERROR(VLOOKUP($A27,Hoja3!$A$3:$F$6000,6,FALSE),"") -> LAMINACION | G27: 1 | H27: =IFERROR(VLOOKUP($A27,Hoja3!$A$3:$F$6000,5,FALSE),"") -> CX | I27: =IFERROR(VLOOKUP($A27,Hoja3!$A$3:$F$6000,3,FALSE),"") -> INDUSTRIAS NEVEX-VEN,C.A | J27: =IFERROR(VLOOKUP($A27,Hoja3!$A$3:$F$6000,4,FALSE),"") -> ETIQUETA LAMINADA IMPRESA CLORO NEVEX BEBE 1L | K27: 62.5 | L27: =(15+20+15)/4 -> 12.5 | M27: 0 | N27: 0 | O27: 0 | P27: 0 | Q27: 0 | R27: 0 | S27: 5 | T27: 0 | U27: 0 | V27: 0 | W27: 0 | X27: 0 | Y27: 0 | Z27: 36.25 | AA27: 12.5 | AB27: 0 | AC27: 0 | AD27: =SUM(L27:AC27) -> 66.25 | AE27: 11.25 | AF27: =SUM(AD27:AE27) -> 77.5 | AG27: =AF27/(60*24) -> 0.053819444 | AH27: =IFERROR(AE27/AF27,0) -> 0.14516129 | AI27: 2062.5 | AJ27: 18 | AK27: 1000 | AL27: =IF(AM27=0,0,(+BK27*AK27/1000)) -> 1875 | AM27: 37.5 | AN27: 5 | AO27: 0 | AP27: 17 | AQ27: 13 | AR27: 12 | AS27: 16 | AT27: 0 | AU27: 15 | AV27: =SUM(AO27:AU27) -> 73 | AW27: =+(AM27+(BR27*50/100))+(BS27*30/100)-BB27 -> 39 | AX27: 0 | AY27: 0 | AZ27: 0 | BA27: 0 | BB27: 0 | BC27: 0 | BD27: 16 | BE27: 12 | BF27: 11 | BG27: 15 | BH27: 0 | BI27: 14 | BJ27: =SUM(BC27:BI27) -> 68 | BK27: 1875 | BL27: =IFERROR(+BO27*1000/((#REF!)*(BM27/1000)),0) -> 0 | BM27: =AK27 -> 1000 | BN27: =+BK27*BM27/1000 -> 1875 | BO27: 33.75 | BP27: 0 | BQ27: 0 | BR27: =AO27-BC27 -> 0 | BS27: =(AP27+AQ27+AR27+AS27+AT27+AU27)-(BD27+BE27+BF27+BG27+BH27+BI27) -> 5 | BT27: =BR27+BS27 -> 5 | BU27: =IFERROR(+#REF!/AE27,0) -> 0 | BV27: =IFERROR(+#REF!/(AF27),0) -> 0 | BW27: =IFERROR(+(AI27-AZ27)-BK27,0) -> 187.5 | BX27: =IFERROR(+BW27/BK27,0) -> 0.1 | BY27: =IFERROR(+(AL27-BA27)-BN27,0) -> 0 | BZ27: =IFERROR(+BY27/BN27,0) -> 0 | CA27: =IFERROR(+AW27-(BO27),0) -> 5.25 | CB27: =IFERROR(+CA27/BO27,1) -> 0.15555556 | CC27: 0 | CD27: 0 | CE27: Aprobacion en combo, problemas con taponamiento de anilox, se realiza estandar claro y oscuro | CF27: =IFERROR((BT27*1000)/BN27,"") -> 2.6666667 | CG27: APROBACION | CH27: 1 | CI27: 3500 | CJ27: =IF(BW27=0,"",CI27-BW27) -> 3312.5 | CK27: {=_xlfn.IFS(CJ27>=0,"CUMPLE",CJ27<0,"NO CUMPLE",CJ27="","")} -> CUMPLE | CL27: 46135 | CM27: {=_xlfn.IFS(CL27-C27 > 0,"CUMPLE",CL27-C27 < 0,"NO CUMPLE")} -> CUMPLE | CN27: 1750 | CO27: =BK27-CN27 -> 125 | CP27: 0 | CQ27: OPPFILM | CR27: BOPP SC TRANSPARENTE
A28: 01-6062 | B28: NF | C28: 46122 | D28: =IFERROR(VLOOKUP($A28,Hoja3!$A$3:$F$6000,2,FALSE),"") -> TXCVNL044A001 | E28: 16601C1 | F28: =IFERROR(VLOOKUP($A28,Hoja3!$A$3:$F$6000,6,FALSE),"") -> LAMINACION | G28: 1 | H28: =IFERROR(VLOOKUP($A28,Hoja3!$A$3:$F$6000,5,FALSE),"") -> CX | I28: =IFERROR(VLOOKUP($A28,Hoja3!$A$3:$F$6000,3,FALSE),"") -> INDUSTRIAS NEVEX-VEN,C.A | J28: =IFERROR(VLOOKUP($A28,Hoja3!$A$3:$F$6000,4,FALSE),"") -> ETIQUETA LAMINADA IMPRESA CLORO NEVEX LAVANDA 1L | K28: 62.5 | L28: 12.5 | M28: 0 | N28: 0 | O28: 0 | P28: 0 | Q28: 0 | R28: 0 | S28: 5 | T28: 0 | U28: 0 | V28: 0 | W28: 0 | X28: 0 | Y28: 0 | Z28: 36.25 | AA28: 12.5 | AB28: 0 | AC28: 0 | AD28: =SUM(L28:AC28) -> 66.25 | AE28: 11.25 | AF28: =SUM(AD28:AE28) -> 77.5 | AG28: =AF28/(60*24) -> 0.053819444 | AH28: =IFERROR(AE28/AF28,0) -> 0.14516129 | AI28: 2062.5 | AJ28: 18 | AK28: 1000 | AL28: =IF(AM28=0,0,(+BK28*AK28/1000)) -> 1875 | AM28: 37.5 | AN28: 0 | AO28: 0 | AP28: 16 | AQ28: 12 | AR28: 11 | AS28: 15 | AT28: 0 | AU28: 14 | AV28: =SUM(AO28:AU28) -> 68 | AW28: =+(AM28+(BR28*50/100))+(BS28*30/100)-BB28 -> 39 | AX28: 0 | AY28: 0 | AZ28: 0 | BA28: 0 | BB28: 0 | BC28: 0 | BD28: 15 | BE28: 11 | BF28: 10 | BG28: 14 | BH28: 0 | BI28: 13 | BJ28: =SUM(BC28:BI28) -> 63 | BK28: 1875 | BL28: =IFERROR(+BO28*1000/((#REF!)*(BM28/1000)),0) -> 0 | BM28: =AK28 -> 1000 | BN28: =+BK28*BM28/1000 -> 1875 | BO28: 33.75 | BP28: 0 | BQ28: 0 | BR28: =AO28-BC28 -> 0 | BS28: =(AP28+AQ28+AR28+AS28+AT28+AU28)-(BD28+BE28+BF28+BG28+BH28+BI28) -> 5 | BT28: =BR28+BS28 -> 5 | BU28: =IFERROR(+#REF!/AE28,0) -> 0 | BV28: =IFERROR(+#REF!/(AF28),0) -> 0 | BW28: =IFERROR(+(AI28-AZ28)-BK28,0) -> 187.5 | BX28: =IFERROR(+BW28/BK28,0) -> 0.1 | BY28: =IFERROR(+(AL28-BA28)-BN28,0) -> 0 | BZ28: =IFERROR(+BY28/BN28,0) -> 0 | CA28: =IFERROR(+AW28-(BO28),0) -> 5.25 | CB28: =IFERROR(+CA28/BO28,1) -> 0.15555556 | CC28: 0 | CD28: 0 | CE28: Aprobacion en combo, problemas con taponamiento de anilox, se realiza estandar claro y oscuro | CF28: =IFERROR((BT28*1000)/BN28,"") -> 2.6666667 | CG28: REPETICION | CH28: 0 | CI28: 3500 | CJ28: =IF(BW28=0,"",CI28-BW28) -> 3312.5 | CK28: {=_xlfn.IFS(CJ28>=0,"CUMPLE",CJ28<0,"NO CUMPLE",CJ28="","")} -> CUMPLE | CL28: 46135 | CM28: {=_xlfn.IFS(CL28-C28 > 0,"CUMPLE",CL28-C28 < 0,"NO CUMPLE")} -> CUMPLE | CN28: 1750 | CO28: =BK28-CN28 -> 125 | CP28: 0 | CQ28: OPPFILM | CR28: BOPP SC TRANSPARENTE
A29: 01-6063 | B29: NF | C29: 46122 | D29: =IFERROR(VLOOKUP($A29,Hoja3!$A$3:$F$6000,2,FALSE),"") -> TXCVNM044A001 | E29: 16601C1 | F29: =IFERROR(VLOOKUP($A29,Hoja3!$A$3:$F$6000,6,FALSE),"") -> LAMINACION | G29: 1 | H29: =IFERROR(VLOOKUP($A29,Hoja3!$A$3:$F$6000,5,FALSE),"") -> CX | I29: =IFERROR(VLOOKUP($A29,Hoja3!$A$3:$F$6000,3,FALSE),"") -> INDUSTRIAS NEVEX-VEN,C.A | J29: =IFERROR(VLOOKUP($A29,Hoja3!$A$3:$F$6000,4,FALSE),"") -> ETIQUETA LAMINADA IMPRESA CLORO NEVEX LIMON 1L | K29: 125 | L29: 12.5 | M29: 0 | N29: 0 | O29: 0 | P29: 0 | Q29: 0 | R29: 0 | S29: 5 | T29: 0 | U29: 0 | V29: 0 | W29: 0 | X29: 0 | Y29: 0 | Z29: 36.25 | AA29: 12.5 | AB29: 0 | AC29: 0 | AD29: =SUM(L29:AC29) -> 66.25 | AE29: 11.25 | AF29: =SUM(AD29:AE29) -> 77.5 | AG29: =AF29/(60*24) -> 0.053819444 | AH29: =IFERROR(AE29/AF29,0) -> 0.14516129 | AI29: 4125 | AJ29: 18 | AK29: 1000 | AL29: =IF(AM29=0,0,(+BK29*AK29/1000)) -> 3750 | AM29: 75 | AN29: 0 | AO29: 0 | AP29: 15 | AQ29: 11 | AR29: 10 | AS29: 14 | AT29: 0 | AU29: 13 | AV29: =SUM(AO29:AU29) -> 63 | AW29: =+(AM29+(BR29*50/100))+(BS29*30/100)-BB29 -> 77.7 | AX29: 0 | AY29: 0 | AZ29: 0 | BA29: 0 | BB29: 0 | BC29: 0 | BD29: 12 | BE29: 10 | BF29: 8 | BG29: 12 | BH29: 0 | BI29: 12 | BJ29: =SUM(BC29:BI29) -> 54 | BK29: 3750 | BL29: =IFERROR(+BO29*1000/((#REF!)*(BM29/1000)),0) -> 0 | BM29: =AK29 -> 1000 | BN29: =+BK29*BM29/1000 -> 3750 | BO29: 67.5 | BP29: 0 | BQ29: 0 | BR29: =AO29-BC29 -> 0 | BS29: =(AP29+AQ29+AR29+AS29+AT29+AU29)-(BD29+BE29+BF29+BG29+BH29+BI29) -> 9 | BT29: =BR29+BS29 -> 9 | BU29: =IFERROR(+#REF!/AE29,0) -> 0 | BV29: =IFERROR(+#REF!/(AF29),0) -> 0 | BW29: =IFERROR(+(AI29-AZ29)-BK29,0) -> 375 | BX29: =IFERROR(+BW29/BK29,0) -> 0.1 | BY29: =IFERROR(+(AL29-BA29)-BN29,0) -> 0 | BZ29: =IFERROR(+BY29/BN29,0) -> 0 | CA29: =IFERROR(+AW29-(BO29),0) -> 10.2 | CB29: =IFERROR(+CA29/BO29,1) -> 0.15111111 | CC29: 0 | CD29: 0 | CE29: Aprobacion en combo, problemas con taponamiento de anilox, se realiza estandar claro y oscuro | CF29: =IFERROR((BT29*1000)/BN29,"") -> 2.4 | CG29: REPETICION | CH29: 0 | CI29: 3500 | CJ29: =IF(BW29=0,"",CI29-BW29) -> 3125 | CK29: {=_xlfn.IFS(CJ29>=0,"CUMPLE",CJ29<0,"NO CUMPLE",CJ29="","")} -> CUMPLE | CL29: 46135 | CM29: {=_xlfn.IFS(CL29-C29 > 0,"CUMPLE",CL29-C29 < 0,"NO CUMPLE")} -> CUMPLE | CN29: 3500 | CO29: =BK29-CN29 -> 250 | CP29: 0 | CQ29: OPPFILM | CR29: BOPP SC TRANSPARENTE
A30: 01-6064 | B30: NF | C30: 46122 | D30: =IFERROR(VLOOKUP($A30,Hoja3!$A$3:$F$6000,2,FALSE),"") -> TXCVNR044A001 | E30: 16601C1 | F30: =IFERROR(VLOOKUP($A30,Hoja3!$A$3:$F$6000,6,FALSE),"") -> LAMINACION | G30: 1 | H30: =IFERROR(VLOOKUP($A30,Hoja3!$A$3:$F$6000,5,FALSE),"") -> CX | I30: =IFERROR(VLOOKUP($A30,Hoja3!$A$3:$F$6000,3,FALSE),"") -> INDUSTRIAS NEVEX-VEN,C.A | J30: =IFERROR(VLOOKUP($A30,Hoja3!$A$3:$F$6000,4,FALSE),"") -> ETIQUETA LAMINADA IMPRESA CLORO NEVEX REGULAR 1L | K30: 250 | L30: 12.5 | M30: 0 | N30: 0 | O30: 0 | P30: 0 | Q30: 0 | R30: 0 | S30: 5 | T30: 0 | U30: 0 | V30: 0 | W30: 0 | X30: 0 | Y30: 0 | Z30: 36.25 | AA30: 12.5 | AB30: 0 | AC30: 0 | AD30: =SUM(L30:AC30) -> 66.25 | AE30: 11.25 | AF30: =SUM(AD30:AE30) -> 77.5 | AG30: =AF30/(60*24) -> 0.053819444 | AH30: =IFERROR(AE30/AF30,0) -> 0.14516129 | AI30: 8250 | AJ30: 18 | AK30: 1000 | AL30: =IF(AM30=0,0,(+BK30*AK30/1000)) -> 7500 | AM30: 150 | AN30: 0 | AO30: 0 | AP30: 12 | AQ30: 10 | AR30: 8 | AS30: 12 | AT30: 0 | AU30: 12 | AV30: =SUM(AO30:AU30) -> 54 | AW30: =+(AM30+(BR30*50/100))+(BS30*30/100)-BB30 -> 154.8 | AX30: 0 | AY30: 0 | AZ30: 0 | BA30: 0 | BB30: 0 | BC30: 0 | BD30: 7 | BE30: 8 | BF30: 4 | BG30: 9 | BH30: 0 | BI30: 10 | BJ30: =SUM(BC30:BI30) -> 38 | BK30: 7500 | BL30: =IFERROR(+BO30*1000/((#REF!)*(BM30/1000)),0) -> 0 | BM30: =AK30 -> 1000 | BN30: =+BK30*BM30/1000 -> 7500 | BO30: 135 | BP30: 0 | BQ30: 0 | BR30: =AO30-BC30 -> 0 | BS30: =(AP30+AQ30+AR30+AS30+AT30+AU30)-(BD30+BE30+BF30+BG30+BH30+BI30) -> 16 | BT30: =BR30+BS30 -> 16 | BU30: =IFERROR(+#REF!/AE30,0) -> 0 | BV30: =IFERROR(+#REF!/(AF30),0) -> 0 | BW30: =IFERROR(+(AI30-AZ30)-BK30,0) -> 750 | BX30: =IFERROR(+BW30/BK30,0) -> 0.1 | BY30: =IFERROR(+(AL30-BA30)-BN30,0) -> 0 | BZ30: =IFERROR(+BY30/BN30,0) -> 0 | CA30: =IFERROR(+AW30-(BO30),0) -> 19.8 | CB30: =IFERROR(+CA30/BO30,1) -> 0.14666667 | CC30: 0 | CD30: 0 | CE30: Aprobacion en combo, problemas con taponamiento de anilox, se realiza estandar claro y oscuro | CF30: =IFERROR((BT30*1000)/BN30,"") -> 2.1333333 | CG30: REPETICION | CH30: 0 | CI30: 3500 | CJ30: =IF(BW30=0,"",CI30-BW30) -> 2750 | CK30: {=_xlfn.IFS(CJ30>=0,"CUMPLE",CJ30<0,"NO CUMPLE",CJ30="","")} -> CUMPLE | CL30: 46135 | CM30: {=_xlfn.IFS(CL30-C30 > 0,"CUMPLE",CL30-C30 < 0,"NO CUMPLE")} -> CUMPLE | CN30: 7000 | CO30: =BK30-CN30 -> 500 | CP30: 0 | CQ30: OPPFILM | CR30: BOPP SC TRANSPARENTE
A31: 01-6079 | B31: NF | C31: 46122 | D31: =IFERROR(VLOOKUP($A31,Hoja3!$A$3:$F$6000,2,FALSE),"") -> TXPAHB059A002 | E31: 16624 | F31: =IFERROR(VLOOKUP($A31,Hoja3!$A$3:$F$6000,6,FALSE),"") -> LAMINACION | G31: 1 | H31: =IFERROR(VLOOKUP($A31,Hoja3!$A$3:$F$6000,5,FALSE),"") -> CX | I31: =IFERROR(VLOOKUP($A31,Hoja3!$A$3:$F$6000,3,FALSE),"") -> PRAVENCA,C.A | J31: =IFERROR(VLOOKUP($A31,Hoja3!$A$3:$F$6000,4,FALSE),"") -> LAMINACION IMP. HARINA PRECOCIDA MASIA 900g | K31: 10000 | L31: =40+40+20+25 -> 125 | M31: =40+85+35 -> 160 | N31: =20+15+25 -> 60 | O31: =20+10+20 -> 50 | P31: =40+20 -> 60 | Q31: 0 | R31: 0 | S31: =15+10+10+10+15+20+10+10+8+10+10 -> 128 | T31: 0 | U31: 0 | V31: =10+25+10+25+20+10+10+10+15+10 -> 145 | W31: 0 | X31: 0 | Y31: 0 | Z31: 0 | AA31: 0 | AB31: 0 | AC31: 0 | AD31: =SUM(L31:AC31) -> 728 | AE31: 972 | AF31: =SUM(AD31:AE31) -> 1700 | AG31: =AF31/(60*24) -> 1.1805556 | AH31: =IFERROR(AE31/AF31,0) -> 0.57176471 | AI31: =88499+103850 -> 192349 | AJ31: 27 | AK31: 980 | AL31: =IF(AM31=0,0,(+AI31*AK31/1000)) -> 188502.02 | AM31: =2371.6+2787.2 -> 5158.8 | AN31: 7 | AO31: 684 | AP31: 0 | AQ31: 34 | AR31: 59 | AS31: 44 | AT31: 0 | AU31: =533+50+45 -> 628 | AV31: =SUM(AO31:AU31) -> 1449 | AW31: =+(AM31+(BR31*50/100))+(BS31*30/100)-BB31 -> 5508.7 | AX31: 0 | AY31: 0 | AZ31: 0 | BA31: 0 | BB31: 0 | BC31: 178 | BD31: 0 | BE31: 26 | BF31: 29 | BG31: 27 | BH31: 0 | BI31: =299+34+27 -> 360 | BJ31: =SUM(BC31:BI31) -> 620 | BK31: 181862 | BL31: =IFERROR(+BO31*1000/((BK31)*(BM31/1000)),0) -> 28.900025 | BM31: =AK31 -> 980 | BN31: =+BK31*BM31/1000 -> 178224.76 | BO31: =(2317+2919.8)-86.1 -> 5150.7 | BP31: 0 | BQ31: 0 | BR31: =AO31-BC31 -> 506 | BS31: =(AP31+AQ31+AR31+AS31+AT31+AU31)-(BD31+BE31+BF31+BG31+BH31+BI31) -> 323 | BT31: =BR31+BS31 -> 829 | BU31: =IFERROR(+BK31/AE31,0) -> 187.10082 | BV31: =IFERROR(+BK31/(AF31),0) -> 106.97765 | BW31: =IFERROR(+(AI31-AZ31)-BK31,0) -> 10487 | BX31: =IFERROR(+BW31/BK31,0) -> 0.057664603 | BY31: =IFERROR(+(AL31-BA31)-BN31,0) -> 10277.26 | BZ31: =IFERROR(+BY31/BN31,0) -> 0.057664603 | CA31: =IFERROR(+AW31-(BO31),0) -> 358 | CB31: =IFERROR(+CA31/BO31,1) -> 0.069505116 | CC31: 0 | CD31: 0 | CE31: problemas con sucio color negro, falla de aire comprimido en desbobinador, se baja trabajo para montar aprobacion de nevex y luego se continua produccion | CF31: =IFERROR((BT31*1000)/BN31,"") -> 4.65143 | CG31: REPETICION | CH31: 1 | CI31: 3500 | CJ31: =IF(BW31=0,"",CI31-BW31) -> -6987 | CK31: {=_xlfn.IFS(CJ31>=0,"CUMPLE",CJ31<0,"NO CUMPLE",CJ31="","")} -> NO CUMPLE | CL31: 46142 | CM31: {=_xlfn.IFS(CL31-C31 > 0,"CUMPLE",CL31-C31 < 0,"NO CUMPLE")} -> CUMPLE | CN31: 187000 | CO31: =BK31-CN31 -> -5138 | CP31: 100 | CQ31: TECHNOFILM | CR31: BOPP CT ST TRANSPARENTE
A32: 01-6080 | B32: NF | C32: 46125 | D32: =IFERROR(VLOOKUP($A32,Hoja3!$A$3:$F$6000,2,FALSE),"") -> TXPAHB059A001 | E32: 16623 | F32: =IFERROR(VLOOKUP($A32,Hoja3!$A$3:$F$6000,6,FALSE),"") -> LAMINACION | G32: 1 | H32: =IFERROR(VLOOKUP($A32,Hoja3!$A$3:$F$6000,5,FALSE),"") -> CX | I32: =IFERROR(VLOOKUP($A32,Hoja3!$A$3:$F$6000,3,FALSE),"") -> PRAVENCA,C.A | J32: =IFERROR(VLOOKUP($A32,Hoja3!$A$3:$F$6000,4,FALSE),"") -> LAMINACION IMP. HARINA PRECOCIDA MASIA 900g | K32: 10000 | L32: =15+15 -> 30 | M32: =40+110 -> 150 | N32: =30+20+50+40+15+35+40+40 -> 270 | O32: 20 | P32: =40+35+40+135+35+50+60+60+40+20+50+20 -> 585 | Q32: 0 | R32: 0 | S32: =15+15+30+15+20+15+15+10+20+20+15+10+15+15+45+30+15 -> 320 | T32: 15 | U32: 40 | V32: =15+20+35+15 -> 85 | W32: 0 | X32: 0 | Y32: 0 | Z32: 0 | AA32: 0 | AB32: 0 | AC32: 0 | AD32: =SUM(L32:AC32) -> 1515 | AE32: 1035.6 | AF32: =SUM(AD32:AE32) -> 2550.6 | AG32: =AF32/(60*24) -> 1.77125 | AH32: =IFERROR(AE32/AF32,0) -> 0.40602211 | AI32: =31500+155720 -> 187220 | AJ32: 27 | AK32: 980 | AL32: =IF(AM32=0,0,(+AI32*AK32/1000)) -> 183475.6 | AM32: =4198.9+841 -> 5039.9 | AN32: 7 | AO32: 453 | AP32: 0 | AQ32: 26 | AR32: 50 | AS32: 30 | AT32: 0 | AU32: =281+45+46 -> 372 | AV32: =SUM(AO32:AU32) -> 931 | AW32: =+(AM32+(BR32*50/100))+(BS32*30/100)-BB32 -> 5338.1 | AX32: 0 | AY32: 0 | AZ32: 0 | BA32: 0 | BB32: 0 | BC32: 72 | BD32: 0 | BE32: 15 | BF32: 13 | BG32: 7 | BH32: 0 | BI32: =51+14+19 -> 84 | BJ32: =SUM(BC32:BI32) -> 191 | BK32: 182611 | BL32: =IFERROR(+BO32*1000/((BK32)*(BM32/1000)),0) -> 28.910009 | BM32: =AK32 -> 980 | BN32: =+BK32*BM32/1000 -> 178958.78 | BO32: =(4570.1+732)-128.4 -> 5173.7 | BP32: 0 | BQ32: 0 | BR32: =AO32-BC32 -> 381 | BS32: =(AP32+AQ32+AR32+AS32+AT32+AU32)-(BD32+BE32+BF32+BG32+BH32+BI32) -> 359 | BT32: =BR32+BS32 -> 740 | BU32: =IFERROR(+BK32/AE32,0) -> 176.33353 | BV32: =IFERROR(+BK32/(AF32),0) -> 71.595311 | BW32: =IFERROR(+(AI32-AZ32)-BK32,0) -> 4609 | BX32: =IFERROR(+BW32/BK32,0) -> 0.025239443 | BY32: =IFERROR(+(AL32-BA32)-BN32,0) -> 4516.82 | BZ32: =IFERROR(+BY32/BN32,0) -> 0.025239443 | CA32: =IFERROR(+AW32-(BO32),0) -> 164.4 | CB32: =IFERROR(+CA32/BO32,1) -> 0.031776098 | CC32: 0 | CD32: 0 | CE32: problemas con taponamiento color cyan y verde fondo, problemas de copiado sobre el mismo, se llama plancha del color amarillo la cual colisiono contra tambor central, problemas de sucio y falla de impresión en color negro | CF32: =IFERROR((BT32*1000)/BN32,"") -> 4.1350304 | CG32: REPETICION | CH32: 1 | CI32: 3500 | CJ32: =IF(BW32=0,"",CI32-BW32) -> -1109 | CK32: {=_xlfn.IFS(CJ32>=0,"CUMPLE",CJ32<0,"NO CUMPLE",CJ32="","")} -> NO CUMPLE | CL32: 46142 | CM32: {=_xlfn.IFS(CL32-C32 > 0,"CUMPLE",CL32-C32 < 0,"NO CUMPLE")} -> CUMPLE | CN32: 187000 | CO32: =BK32-CN32 -> -4389 | CP32: 1800 | CQ32: TECHNOFILM | CR32: BOPP CT ST TRANSPARENTE
A33: 01-6056 | B33: NF | C33: 46126 | D33: =IFERROR(VLOOKUP($A33,Hoja3!$A$3:$F$6000,2,FALSE),"") -> TXCPEM023A001 | E33: 16570-1 | F33: =IFERROR(VLOOKUP($A33,Hoja3!$A$3:$F$6000,6,FALSE),"") -> CORTE | G33: 1 | H33: =IFERROR(VLOOKUP($A33,Hoja3!$A$3:$F$6000,5,FALSE),"") -> CX | I33: =IFERROR(VLOOKUP($A33,Hoja3!$A$3:$F$6000,3,FALSE),"") -> CERVECERIA POLAR,C.A. | J33: =IFERROR(VLOOKUP($A33,Hoja3!$A$3:$F$6000,4,FALSE),"") -> ETIQUETA IMPRESA MALTIN POLAR 1,5 L | K33: 1100 | L33: =30+30+20 -> 80 | M33: 0 | N33: =55+20 -> 75 | O33: =20+20 -> 40 | P33: =130+15 -> 145 | Q33: 0 | R33: 0 | S33: =30+10+30 -> 70 | T33: 0 | U33: 0 | V33: =15+50 -> 65 | W33: 0 | X33: 40 | Y33: 0 | Z33: 0 | AA33: 0 | AB33: 0 | AC33: 0 | AD33: =SUM(L33:AC33) -> 515 | AE33: 245.4 | AF33: =SUM(AD33:AE33) -> 760.4 | AG33: =AF33/(60*24) -> 0.52805556 | AH33: =IFERROR(AE33/AF33,0) -> 0.32272488 | AI33: 61000 | AJ33: 21 | AK33: 930 | AL33: =IF(AM33=0,0,(+AI33*AK33/1000)) -> 56730 | AM33: 1274 | AN33: 6 | AO33: 0 | AP33: 29 | AQ33: 33 | AR33: 52 | AS33: 25 | AT33: 0 | AU33: =29+143 -> 172 | AV33: =SUM(AO33:AU33) -> 311 | AW33: =+(AM33+(BR33*50/100))+(BS33*30/100)-BB33 -> 1337.3 | AX33: 0 | AY33: 0 | AZ33: 0 | BA33: 0 | BB33: 0 | BC33: 0 | BD33: 16 | BE33: 4 | BF33: 9 | BG33: 7 | BH33: 0 | BI33: =7+57 -> 64 | BJ33: =SUM(BC33:BI33) -> 100 | BK33: 53599 | BL33: =IFERROR(+BO33*1000/((BK33)*(BM33/1000)),0) -> 22.940165 | BM33: =AK33 -> 930 | BN33: =+BK33*BM33/1000 -> 49847.07 | BO33: =1229-85.5 -> 1143.5 | BP33: 0 | BQ33: 0 | BR33: =AO33-BC33 -> 0 | BS33: =(AP33+AQ33+AR33+AS33+AT33+AU33)-(BD33+BE33+BF33+BG33+BH33+BI33) -> 211 | BT33: =BR33+BS33 -> 211 | BU33: =IFERROR(+BK33/AE33,0) -> 218.41483 | BV33: =IFERROR(+BK33/(AF33),0) -> 70.487901 | BW33: =IFERROR(+(AI33-AZ33)-BK33,0) -> 7401 | BX33: =IFERROR(+BW33/BK33,0) -> 0.13808093 | BY33: =IFERROR(+(AL33-BA33)-BN33,0) -> 6882.93 | BZ33: =IFERROR(+BY33/BN33,0) -> 0.13808093 | CA33: =IFERROR(+AW33-(BO33),0) -> 193.8 | CB33: =IFERROR(+CA33/BO33,1) -> 0.16947967 | CC33: 0 | CD33: 0 | CE33: se cambia anilox y se coloca 340/8184 ya que dicho color necesita mas incremento del tono, limpiexa color azul y negro | CF33: =IFERROR((BT33*1000)/BN33,"") -> 4.2329469 | CG33: REPETICION | CH33: 1 | CI33: 3500 | CJ33: =IF(BW33=0,"",CI33-BW33) -> -3901 | CK33: {=_xlfn.IFS(CJ33>0,"CUMPLE",CJ33<0,"NO CUMPLE",CJ33="","")} -> NO CUMPLE | CL33: 46112 | CM33: {=_xlfn.IFS(CL33-C33 > 0,"CUMPLE",CL33-C33 < 0,"NO CUMPLE")} -> NO CUMPLE | CN33: 57500 | CO33: =BK33-CN33 -> -3901 | CP33: 1300 | CQ33: TELEPLASTIC | CR33: BOPP POCT PERLADO
A34: 21-0553 | B34: NF | C34: 46127 | D34: =IFERROR(VLOOKUP($A34,Hoja3!$A$3:$F$6000,2,FALSE),"") -> TXNVCL096C004 | E34: 16607 | F34: =IFERROR(VLOOKUP($A34,Hoja3!$A$3:$F$6000,6,FALSE),"") -> LAMINACION | G34: 1 | H34: =IFERROR(VLOOKUP($A34,Hoja3!$A$3:$F$6000,5,FALSE),"") -> CX | I34: =IFERROR(VLOOKUP($A34,Hoja3!$A$3:$F$6000,3,FALSE),"") -> NESTLE VENEZUELA, S.A. | J34: =IFERROR(VLOOKUP($A34,Hoja3!$A$3:$F$6000,4,FALSE),"") -> LAMINACION IMPRESA CERELAC 400g | K34: 2755 | L34: =25+45+20 -> 90 | M34: =30+30 -> 60 | N34: =40+65 -> 105 | O34: 20 | P34: 0 | Q34: 0 | R34: 0 | S34: =15+20 -> 35 | T34: 0 | U34: 0 | V34: 10 | W34: 0 | X34: 15 | Y34: 0 | Z34: 0 | AA34: 0 | AB34: 0 | AC34: 0 | AD34: =SUM(L34:AC34) -> 335 | AE34: 199.8 | AF34: =SUM(AD34:AE34) -> 534.8 | AG34: =AF34/(60*24) -> 0.37138889 | AH34: =IFERROR(AE34/AF34,0) -> 0.37359761 | AI34: 39390 | AJ34: 18 | AK34: 790 | AL34: =IF(AM34=0,0,(+AI34*AK34/1000)) -> 31118.1 | AM34: 588.8 | AN34: 7 | AO34: 272 | AP34: 17 | AQ34: 19 | AR34: 28 | AS34: 15 | AT34: 0 | AU34: =26+15 -> 41 | AV34: =SUM(AO34:AU34) -> 392 | AW34: =+(AM34+(BR34*50/100))+(BS34*30/100)-BB34 -> 652.7 | AX34: 0 | AY34: 0 | AZ34: 0 | BA34: 0 | BB34: 0 | BC34: 170 | BD34: 13 | BE34: 15 | BF34: 12 | BG34: 13 | BH34: 0 | BI34: =16+8 -> 24 | BJ34: =SUM(BC34:BI34) -> 247 | BK34: 35578 | BL34: =IFERROR(+BO34*1000/((BK34)*(BM34/1000)),0) -> 19.650175 | BM34: =AK34 -> 790 | BN34: =+BK34*BM34/1000 -> 28106.62 | BO34: =564-11.7 -> 552.3 | BP34: 0 | BQ34: 0 | BR34: =AO34-BC34 -> 102 | BS34: =(AP34+AQ34+AR34+AS34+AT34+AU34)-(BD34+BE34+BF34+BG34+BH34+BI34) -> 43 | BT34: =BR34+BS34 -> 145 | BU34: =IFERROR(+BK34/AE34,0) -> 178.06807 | BV34: =IFERROR(+BK34/(AF34),0) -> 66.525804 | BW34: =IFERROR(+(AI34-AZ34)-BK34,0) -> 3812 | BX34: =IFERROR(+BW34/BK34,0) -> 0.10714486 | BY34: =IFERROR(+(AL34-BA34)-BN34,0) -> 3011.48 | BZ34: =IFERROR(+BY34/BN34,0) -> 0.10714486 | CA34: =IFERROR(+AW34-(BO34),0) -> 100.4 | CB34: =IFERROR(+CA34/BO34,1) -> 0.18178526 | CC34: 0 | CD34: 0 | CE34: falla de impresión en el color beige, se limpia plancha del magenta y se baja para que se active manga twinlock, se baja trabajo por falla en el color magenta | CF34: =IFERROR((BT34*1000)/BN34,"") -> 5.158927 | CG34: REPETICION | CH34: 1 | CI34: 3500 | CJ34: =IF(BW34=0,"",CI34-BW34) -> -312 | CK34: {=_xlfn.IFS(CJ34>0,"CUMPLE",CJ34<0,"NO CUMPLE",CJ34="","")} -> NO CUMPLE | CL34: 46198 | CM34: {=_xlfn.IFS(CL34-C34 > 0,"CUMPLE",CL34-C34 < 0,"NO CUMPLE")} -> CUMPLE | CN34: 41000 | CO34: =BK34-CN34 -> -5422 | CP34: 1600 | CQ34: TELEPLASTIC | CR34: BOPP OCTS TRANSPARENTE
A35: 000pr | B35: NF | C35: 46127 | D35: =IFERROR(VLOOKUP($A35,Hoja3!$A$3:$F$6000,2,FALSE),"") -> 000pr | E35: PR 3848/49 | F35: =IFERROR(VLOOKUP($A35,Hoja3!$A$3:$F$6000,6,FALSE),"") -> PRUEBA | G35: 0 | H35: =IFERROR(VLOOKUP($A35,Hoja3!$A$3:$F$6000,5,FALSE),"") -> CX | I35: =IFERROR(VLOOKUP($A35,Hoja3!$A$3:$F$6000,3,FALSE),"") -> PRUEBAS | J35: =IFERROR(VLOOKUP($A35,Hoja3!$A$3:$F$6000,4,FALSE),"") -> PRUEBAS VARIAS | K35: 0 | L35: =25+10 -> 35 | M35: 0 | N35: 0 | O35: 0 | P35: 0 | Q35: 0 | R35: 0 | S35: 15 | T35: 0 | U35: 0 | V35: 0 | W35: 15 | X35: 0 | Y35: 0 | Z35: 0 | AA35: 0 | AB35: 0 | AC35: 0 | AD35: =SUM(L35:AC35) -> 65 | AE35: 10.2 | AF35: =SUM(AD35:AE35) -> 75.2 | AG35: =AF35/(60*24) -> 0.052222222 | AH35: =IFERROR(AE35/AF35,0) -> 0.1356383 | AI35: 0 | AJ35: 0 | AK35: 0 | AL35: =IF(AM35=0,0,(+AI35*AK35/1000)) -> 0 | AM35: 0 | AN35: 0 | AO35: 0 | AP35: 0 | AQ35: 0 | AR35: 0 | AS35: 0 | AT35: 0 | AU35: 0 | AV35: =SUM(AO35:AU35) -> 0 | AW35: =+(AM35+(BR35*50/100))+(BS35*30/100)-BB35 -> 0 | AX35: 0 | AY35: 0 | AZ35: 0 | BA35: 0 | BB35: 0 | BC35: 0 | BD35: 0 | BE35: 0 | BF35: 0 | BG35: 0 | BH35: 0 | BI35: 0 | BJ35: =SUM(BC35:BI35) -> 0 | BK35: 0 | BL35: =IFERROR(+BO35*1000/((BK35)*(BM35/1000)),0) -> 0 | BM35: =AK35 -> 0 | BN35: =+BK35*BM35/1000 -> 0 | BO35: 0 | BP35: 0 | BQ35: 0 | BR35: =AO35-BC35 -> 0 | BS35: =(AP35+AQ35+AR35+AS35+AT35+AU35)-(BD35+BE35+BF35+BG35+BH35+BI35) -> 0 | BT35: =BR35+BS35 -> 0 | BU35: =IFERROR(+BK35/AE35,0) -> 0 | BV35: =IFERROR(+BK35/(AF35),0) -> 0 | BW35: =IFERROR(+(AI35-AZ35)-BK35,0) -> 0 | BX35: =IFERROR(+BW35/BK35,0) -> 0 | BY35: =IFERROR(+(AL35-BA35)-BN35,0) -> 0 | BZ35: =IFERROR(+BY35/BN35,0) -> 0 | CA35: =IFERROR(+AW35-(BO35),0) -> 0 | CB35: =IFERROR(+CA35/BO35,1) -> 1 | CC35: 0 | CD35: 0 | CE35: Se realiza prueb de crema de arroz poly 150g | CF35: 0 | CG35: PRUEBA | CH35: 0 | CI35: 0 | CJ35: 0 | CK35: 0 | CL35: 0 | CM35: {=_xlfn.IFS(CL35-C35 > 0,"CUMPLE",CL35-C35 < 0,"NO CUMPLE")} -> NO CUMPLE | CN35: 0 | CO35: =BK35-CN35 -> 0 | CP35: 0
A36: 01-6052 | B36: NF | C36: 46127 | D36: =IFERROR(VLOOKUP($A36,Hoja3!$A$3:$F$6000,2,FALSE),"") -> TXPCGK023C002 | E36: 16590 | F36: =IFERROR(VLOOKUP($A36,Hoja3!$A$3:$F$6000,6,FALSE),"") -> CORTE | G36: 0 | H36: =IFERROR(VLOOKUP($A36,Hoja3!$A$3:$F$6000,5,FALSE),"") -> CX | I36: =IFERROR(VLOOKUP($A36,Hoja3!$A$3:$F$6000,3,FALSE),"") -> PEPSI-COLA VENEZUELA, C.A. | J36: =IFERROR(VLOOKUP($A36,Hoja3!$A$3:$F$6000,4,FALSE),"") -> ETIQUETA IMPRESA GOLDEN KOLITA 2L | K36: 0 | L36: =50+50 -> 100 | M36: 0 | N36: 30 | O36: 15 | P36: 70 | Q36: 0 | R36: 0 | S36: 15 | T36: 0 | U36: 0 | V36: =30+25+150 -> 205 | W36: 0 | X36: 35 | Y36: 0 | Z36: 0 | AA36: 0 | AB36: 30 | AC36: 0 | AD36: =SUM(L36:AC36) -> 500 | AE36: 0 | AF36: =SUM(AD36:AE36) -> 500 | AG36: =AF36/(60*24) -> 0.34722222 | AH36: =IFERROR(AE36/AF36,0) -> 0 | AI36: 0 | AJ36: 0 | AK36: 0 | AL36: =IF(AM36=0,0,(+AI36*AK36/1000)) -> 0 | AM36: 0 | AN36: 0 | AO36: 0 | AP36: 0 | AQ36: 0 | AR36: 0 | AS36: 0 | AT36: 0 | AU36: 0 | AV36: =SUM(AO36:AU36) -> 0 | AW36: =+(AM36+(BR36*50/100))+(BS36*30/100)-BB36 -> 0 | AX36: 0 | AY36: 0 | AZ36: 0 | BA36: 0 | BB36: 0 | BC36: 0 | BD36: 0 | BE36: 0 | BF36: 0 | BG36: 0 | BH36: 0 | BI36: 0 | BJ36: =SUM(BC36:BI36) -> 0 | BK36: 0 | BL36: =IFERROR(+BO36*1000/((BK36)*(BM36/1000)),0) -> 0 | BM36: =AK36 -> 0 | BN36: =+BK36*BM36/1000 -> 0 | BO36: 0 | BP36: 0 | BQ36: 0 | BR36: =AO36-BC36 -> 0 | BS36: =(AP36+AQ36+AR36+AS36+AT36+AU36)-(BD36+BE36+BF36+BG36+BH36+BI36) -> 0 | BT36: =BR36+BS36 -> 0 | BU36: =IFERROR(+BK36/AE36,0) -> 0 | BV36: =IFERROR(+BK36/(AF36),0) -> 0 | BW36: =IFERROR(+(AI36-AZ36)-BK36,0) -> 0 | BX36: =IFERROR(+BW36/BK36,0) -> 0 | BY36: =IFERROR(+(AL36-BA36)-BN36,0) -> 0 | BZ36: =IFERROR(+BY36/BN36,0) -> 0 | CA36: =IFERROR(+AW36-(BO36),0) -> 0 | CB36: =IFERROR(+CA36/BO36,1) -> 1 | CC36: 0 | CD36: 0 | CF36: 0 | CG36: SUSPENDIDO | CH36: 0 | CI36: 0 | CJ36: 0 | CK36: 0 | CL36: 0 | CM36: 0 | CN36: 0 | CO36: =BK36-CN36 -> 0 | CP36: 0
A37: 000pr | B37: NF | C37: 46128 | D37: =IFERROR(VLOOKUP($A37,Hoja3!$A$3:$F$6000,2,FALSE),"") -> 000pr | E37: pr-3855 | F37: =IFERROR(VLOOKUP($A37,Hoja3!$A$3:$F$6000,6,FALSE),"") -> PRUEBA | G37: 0 | H37: =IFERROR(VLOOKUP($A37,Hoja3!$A$3:$F$6000,5,FALSE),"") -> CX | I37: =IFERROR(VLOOKUP($A37,Hoja3!$A$3:$F$6000,3,FALSE),"") -> PRUEBAS | J37: =IFERROR(VLOOKUP($A37,Hoja3!$A$3:$F$6000,4,FALSE),"") -> PRUEBAS VARIAS | K37: 0 | L37: =30+60 -> 90 | M37: 120 | N37: 0 | O37: 0 | P37: =60+280 -> 340 | Q37: 0 | R37: 0 | S37: 0 | T37: 0 | U37: 0 | V37: 0 | W37: 15 | X37: 0 | Y37: 0 | Z37: 0 | AA37: 0 | AB37: 0 | AC37: 0 | AD37: =SUM(L37:AC37) -> 565 | AE37: 10.2 | AF37: =SUM(AD37:AE37) -> 575.2 | AG37: =AF37/(60*24) -> 0.39944444 | AH37: =IFERROR(AE37/AF37,0) -> 0.017732962 | AI37: 0 | AJ37: 0 | AK37: 0 | AL37: =IF(AM37=0,0,(+AI37*AK37/1000)) -> 0 | AM37: 0 | AN37: 0 | AO37: 0 | AP37: 0 | AQ37: 0 | AR37: 0 | AS37: 0 | AT37: 0 | AU37: 0 | AV37: =SUM(AO37:AU37) -> 0 | AW37: =+(AM37+(BR37*50/100))+(BS37*30/100)-BB37 -> 0 | AX37: 0 | AY37: 0 | AZ37: 0 | BA37: 0 | BB37: 0 | BC37: 0 | BD37: 0 | BE37: 0 | BF37: 0 | BG37: 0 | BH37: 0 | BI37: 0 | BJ37: =SUM(BC37:BI37) -> 0 | BK37: 0 | BL37: =IFERROR(+BO37*1000/((BK37)*(BM37/1000)),0) -> 0 | BM37: =AK37 -> 0 | BN37: =+BK37*BM37/1000 -> 0 | BO37: 0 | BP37: 0 | BQ37: 0 | BR37: =AO37-BC37 -> 0 | BS37: =(AP37+AQ37+AR37+AS37+AT37+AU37)-(BD37+BE37+BF37+BG37+BH37+BI37) -> 0 | BT37: =BR37+BS37 -> 0 | BU37: =IFERROR(+BK37/AE37,0) -> 0 | BV37: =IFERROR(+BK37/(AF37),0) -> 0 | BW37: =IFERROR(+(AI37-AZ37)-BK37,0) -> 0 | BX37: =IFERROR(+BW37/BK37,0) -> 0 | BY37: =IFERROR(+(AL37-BA37)-BN37,0) -> 0 | BZ37: =IFERROR(+BY37/BN37,0) -> 0 | CA37: =IFERROR(+AW37-(BO37),0) -> 0 | CB37: =IFERROR(+CA37/BO37,1) -> 1 | CC37: 0 | CD37: 0 | CE37: se realiza prueba interna de brownie chocolate 175g | CF37: 0 | CG37: PRUEBA | CH37: 0 | CI37: 0 | CJ37: 0 | CK37: 0 | CL37: 0 | CM37: 0 | CN37: 0 | CO37: 0 | CP37: 0
A38: 01-6052 | B38: NF | C38: 46128 | D38: =IFERROR(VLOOKUP($A38,Hoja3!$A$3:$F$6000,2,FALSE),"") -> TXPCGK023C002 | E38: 16590 | F38: =IFERROR(VLOOKUP($A38,Hoja3!$A$3:$F$6000,6,FALSE),"") -> CORTE | G38: 1 | H38: =IFERROR(VLOOKUP($A38,Hoja3!$A$3:$F$6000,5,FALSE),"") -> CX | I38: =IFERROR(VLOOKUP($A38,Hoja3!$A$3:$F$6000,3,FALSE),"") -> PEPSI-COLA VENEZUELA, C.A. | J38: =IFERROR(VLOOKUP($A38,Hoja3!$A$3:$F$6000,4,FALSE),"") -> ETIQUETA IMPRESA GOLDEN KOLITA 2L | K38: 650 | L38: =25+40+15 -> 80 | M38: 0 | N38: =45+15 -> 60 | O38: 20 | P38: 0 | Q38: 0 | R38: 0 | S38: =10+15 -> 25 | T38: 0 | U38: 0 | V38: 0 | W38: 0 | X38: 0 | Y38: 0 | Z38: 0 | AA38: 0 | AB38: 0 | AC38: 0 | AD38: =SUM(L38:AC38) -> 185 | AE38: 154.8 | AF38: =SUM(AD38:AE38) -> 339.8 | AG38: =AF38/(60*24) -> 0.23597222 | AH38: =IFERROR(AE38/AF38,0) -> 0.4555621 | AI38: 30800 | AJ38: 21 | AK38: 1010 | AL38: =IF(AM38=0,0,(+AI38*AK38/1000)) -> 31108 | AM38: 675.1 | AN38: 6 | AO38: 0 | AP38: =25+17 -> 42 | AQ38: 0 | AR38: 0 | AS38: 0 | AT38: =18+30 -> 48 | AU38: =12+238 -> 250 | AV38: =SUM(AO38:AU38) -> 340 | AW38: =+(AM38+(BR38*50/100))+(BS38*30/100)-BB38 -> 698.8 | AX38: 0 | AY38: 0 | AZ38: 0 | BA38: 0 | BB38: 0 | BC38: 0 | BD38: =16+13 -> 29 | BE38: 0 | BF38: 0 | BG38: 0 | BH38: =15+20 -> 35 | BI38: =11+186 -> 197 | BJ38: =SUM(BC38:BI38) -> 261 | BK38: 28150 | BL38: =IFERROR(+BO38*1000/((BK38)*(BM38/1000)),0) -> 22.21128 | BM38: =AK38 -> 1010 | BN38: =+BK38*BM38/1000 -> 28431.5 | BO38: =665-33.5 -> 631.5 | BP38: 0 | BQ38: 0 | BR38: =AO38-BC38 -> 0 | BS38: =(AP38+AQ38+AR38+AS38+AT38+AU38)-(BD38+BE38+BF38+BG38+BH38+BI38) -> 79 | BT38: =BR38+BS38 -> 79 | BU38: =IFERROR(+BK38/AE38,0) -> 181.84755 | BV38: =IFERROR(+BK38/(AF38),0) -> 82.842849 | BW38: =IFERROR(+(AI38-AZ38)-BK38,0) -> 2650 | BX38: =IFERROR(+BW38/BK38,0) -> 0.094138544 | BY38: =IFERROR(+(AL38-BA38)-BN38,0) -> 2676.5 | BZ38: =IFERROR(+BY38/BN38,0) -> 0.094138544 | CA38: =IFERROR(+AW38-(BO38),0) -> 67.3 | CB38: =IFERROR(+CA38/BO38,1) -> 0.10657165 | CC38: 0 | CD38: 0 | CE38: se culmina produccion sin novedad | CF38: =IFERROR((BT38*1000)/BN38,"") -> 2.7786082 | CG38: REPETICION | CH38: 4 | CI38: 3500 | CJ38: =IF(BW38=0,"",CI38-BW38) -> 850 | CK38: {=_xlfn.IFS(CJ38>0,"CUMPLE",CJ38<0,"NO CUMPLE",CJ38="","")} -> CUMPLE | CL38: 46111 | CM38: {=_xlfn.IFS(CL38-C38 > 0,"CUMPLE",CL38-C38 < 0,"NO CUMPLE")} -> NO CUMPLE | CN38: 28000 | CO38: =BK38-CN38 -> 150 | CP38: 1300 | CQ38: TELEPLASTIC | CR38: BOPP POCT PERLADO
A39: 01-6034 | B39: NF | C39: 46128 | D39: =IFERROR(VLOOKUP($A39,Hoja3!$A$3:$F$6000,2,FALSE),"") -> TXPCGK023C002 | E39: 16572-1 | F39: =IFERROR(VLOOKUP($A39,Hoja3!$A$3:$F$6000,6,FALSE),"") -> CORTE | G39: 1 | H39: =IFERROR(VLOOKUP($A39,Hoja3!$A$3:$F$6000,5,FALSE),"") -> CX | I39: =IFERROR(VLOOKUP($A39,Hoja3!$A$3:$F$6000,3,FALSE),"") -> PEPSI-COLA VENEZUELA, C.A. | J39: =IFERROR(VLOOKUP($A39,Hoja3!$A$3:$F$6000,4,FALSE),"") -> ETIQUETA IMPRESA GOLDEN KOLITA 2L | K39: 550 | L39: 0 | M39: 0 | N39: 0 | O39: 10 | P39: 0 | Q39: 0 | R39: 0 | S39: =15+40 -> 55 | T39: 0 | U39: 0 | V39: 0 | W39: 0 | X39: 0 | Y39: 0 | Z39: 0 | AA39: 0 | AB39: 0 | AC39: 0 | AD39: =SUM(L39:AC39) -> 65 | AE39: 140.4 | AF39: =SUM(AD39:AE39) -> 205.4 | AG39: =AF39/(60*24) -> 0.14263889 | AH39: =IFERROR(AE39/AF39,0) -> 0.6835443 | AI39: 25300 | AJ39: 21 | AK39: 1010 | AL39: =IF(AM39=0,0,(+AI39*AK39/1000)) -> 25553 | AM39: 570.1 | AN39: 6 | AO39: 0 | AP39: =16+13 -> 29 | AQ39: 0 | AR39: 0 | AS39: 0 | AT39: =15+20 -> 35 | AU39: =11+186 -> 197 | AV39: =SUM(AO39:AU39) -> 261 | AW39: =+(AM39+(BR39*50/100))+(BS39*30/100)-BB39 -> 590.5 | AX39: 0 | AY39: 0 | AZ39: 0 | BA39: 0 | BB39: 0 | BC39: 0 | BD39: =9+9 -> 18 | BE39: 0 | BF39: 0 | BG39: 0 | BH39: =13+12 -> 25 | BI39: =10+140 -> 150 | BJ39: =SUM(BC39:BI39) -> 193 | BK39: 24040 | BL39: =IFERROR(+BO39*1000/((BK39)*(BM39/1000)),0) -> 23.224494 | BM39: =AK39 -> 1010 | BN39: =+BK39*BM39/1000 -> 24280.4 | BO39: =586-22.1 -> 563.9 | BP39: 0 | BQ39: 0 | BR39: =AO39-BC39 -> 0 | BS39: =(AP39+AQ39+AR39+AS39+AT39+AU39)-(BD39+BE39+BF39+BG39+BH39+BI39) -> 68 | BT39: =BR39+BS39 -> 68 | BU39: =IFERROR(+BK39/AE39,0) -> 171.22507 | BV39: =IFERROR(+BK39/(AF39),0) -> 117.03992 | BW39: =IFERROR(+(AI39-AZ39)-BK39,0) -> 1260 | BX39: =IFERROR(+BW39/BK39,0) -> 0.052412646 | BY39: =IFERROR(+(AL39-BA39)-BN39,0) -> 1272.6 | BZ39: =IFERROR(+BY39/BN39,0) -> 0.052412646 | CA39: =IFERROR(+AW39-(BO39),0) -> 26.6 | CB39: =IFERROR(+CA39/BO39,1) -> 0.047171484 | CC39: 0 | CD39: 0 | CE39: se culmina produccion sin novedad | CF39: =IFERROR((BT39*1000)/BN39,"") -> 2.8006128 | CG39: REPETICION | CH39: 0 | CI39: 3500 | CJ39: =IF(BW39=0,"",CI39-BW39) -> 2240 | CK39: {=_xlfn.IFS(CJ39>0,"CUMPLE",CJ39<0,"NO CUMPLE",CJ39="","")} -> CUMPLE | CL39: 46111 | CM39: {=_xlfn.IFS(CL39-C39 > 0,"CUMPLE",CL39-C39 < 0,"NO CUMPLE")} -> NO CUMPLE | CN39: 24500 | CO39: =BK39-CN39 -> -460 | CP39: 0 | CQ39: TELEPLASTIC | CR39: BOPP POCT PERLADO
A40: 01-6043 | B40: NF | C40: 46128 | D40: =IFERROR(VLOOKUP($A40,Hoja3!$A$3:$F$6000,2,FALSE),"") -> TXPCGK023B001 | E40: 16581 | F40: =IFERROR(VLOOKUP($A40,Hoja3!$A$3:$F$6000,6,FALSE),"") -> CORTE | G40: 1 | H40: =IFERROR(VLOOKUP($A40,Hoja3!$A$3:$F$6000,5,FALSE),"") -> CX | I40: =IFERROR(VLOOKUP($A40,Hoja3!$A$3:$F$6000,3,FALSE),"") -> PEPSI-COLA VENEZUELA, C.A. | J40: =IFERROR(VLOOKUP($A40,Hoja3!$A$3:$F$6000,4,FALSE),"") -> ETIQUETA IMPRESA GOLDEN KOLITA 1,5 L | K40: 165 | L40: =20+15 -> 35 | M40: 0 | N40: =25+15 -> 40 | O40: 15 | P40: =40+15 -> 55 | Q40: 0 | R40: 0 | S40: =10+15 -> 25 | T40: 0 | U40: 0 | V40: =15+5 -> 20 | W40: 0 | X40: 0 | Y40: 0 | Z40: 0 | AA40: 0 | AB40: 30 | AC40: 0 | AD40: =SUM(L40:AC40) -> 220 | AE40: 45 | AF40: =SUM(AD40:AE40) -> 265 | AG40: =AF40/(60*24) -> 0.18402778 | AH40: =IFERROR(AE40/AF40,0) -> 0.16981132 | AI40: 12000 | AJ40: 21 | AK40: 1010 | AL40: =IF(AM40=0,0,(+AI40*AK40/1000)) -> 12120 | AM40: 268 | AN40: 6 | AO40: 0 | AP40: =18+16 -> 34 | AQ40: 0 | AR40: 0 | AS40: 0 | AT40: =23+23 -> 46 | AU40: =13+140 -> 153 | AV40: =SUM(AO40:AU40) -> 233 | AW40: =+(AM40+(BR40*50/100))+(BS40*30/100)-BB40 -> 278.8 | AX40: 0 | AY40: 0 | AZ40: 0 | BA40: 0 | BB40: 0 | BC40: 0 | BD40: =15+14 -> 29 | BE40: 0 | BF40: 0 | BG40: 0 | BH40: =14+12 -> 26 | BI40: =12+130 -> 142 | BJ40: =SUM(BC40:BI40) -> 197 | BK40: 7450 | BL40: =IFERROR(+BO40*1000/((BK40)*(BM40/1000)),0) -> 22.061267 | BM40: =AK40 -> 1010 | BN40: =+BK40*BM40/1000 -> 7524.5 | BO40: 166 | BP40: 0 | BQ40: 0 | BR40: =AO40-BC40 -> 0 | BS40: =(AP40+AQ40+AR40+AS40+AT40+AU40)-(BD40+BE40+BF40+BG40+BH40+BI40) -> 36 | BT40: =BR40+BS40 -> 36 | BU40: =IFERROR(+BK40/AE40,0) -> 165.55556 | BV40: =IFERROR(+BK40/(AF40),0) -> 28.113208 | BW40: =IFERROR(+(AI40-AZ40)-BK40,0) -> 4550 | BX40: =IFERROR(+BW40/BK40,0) -> 0.61073826 | BY40: =IFERROR(+(AL40-BA40)-BN40,0) -> 4595.5 | BZ40: =IFERROR(+BY40/BN40,0) -> 0.61073826 | CA40: =IFERROR(+AW40-(BO40),0) -> 112.8 | CB40: =IFERROR(+CA40/BO40,1) -> 0.67951807 | CC40: 0 | CD40: 0 | CE40: problemas de registro estac 8 | CF40: =IFERROR((BT40*1000)/BN40,"") -> 4.7843711 | CG40: REPETICION | CH40: 4 | CI40: 3500 | CJ40: =IF(BW40=0,"",CI40-BW40) -> -1050 | CK40: {=_xlfn.IFS(CJ40>0,"CUMPLE",CJ40<0,"NO CUMPLE",CJ40="","")} -> NO CUMPLE | CL40: 46111 | CM40: {=_xlfn.IFS(CL40-C40 > 0,"CUMPLE",CL40-C40 < 0,"NO CUMPLE")} -> NO CUMPLE | CN40: 7500 | CO40: =BK40-CN40 -> -50 | CP40: 0 | CQ40: TELEPLASTIC | CR40: BOPP POCT PERLADO
A41: 01-6038 | B41: NF | C41: 46129 | D41: =IFERROR(VLOOKUP($A41,Hoja3!$A$3:$F$6000,2,FALSE),"") -> TXPCGM023C001 | E41: 16576 | F41: =IFERROR(VLOOKUP($A41,Hoja3!$A$3:$F$6000,6,FALSE),"") -> CORTE | G41: 1 | H41: =IFERROR(VLOOKUP($A41,Hoja3!$A$3:$F$6000,5,FALSE),"") -> CX | I41: =IFERROR(VLOOKUP($A41,Hoja3!$A$3:$F$6000,3,FALSE),"") -> PEPSI-COLA VENEZUELA, C.A. | J41: =IFERROR(VLOOKUP($A41,Hoja3!$A$3:$F$6000,4,FALSE),"") -> ETIQUETA IMPRESA GOLDEN MANZANA 2L | K41: 920 | L41: =25+25+20 -> 70 | M41: 30 | N41: =50+18+7+30+60+10+15+10 -> 200 | O41: 25 | P41: =40+30+30+60 -> 160 | Q41: 0 | R41: 0 | S41: =10+15+15+25+20 -> 85 | T41: 15 | U41: 0 | V41: =15+10+20+5+10+210 -> 270 | W41: 0 | X41: 30 | Y41: 0 | Z41: 0 | AA41: 0 | AB41: 0 | AC41: 0 | AD41: =SUM(L41:AC41) -> 885 | AE41: 246.6 | AF41: =SUM(AD41:AE41) -> 1131.6 | AG41: =AF41/(60*24) -> 0.78583333 | AH41: =IFERROR(AE41/AF41,0) -> 0.21792153 | AI41: 43163 | AJ41: 21 | AK41: 1010 | AL41: =IF(AM41=0,0,(+AI41*AK41/1000)) -> 43594.63 | AM41: =1015.5-100 -> 915.5 | AN41: 7 | AO41: 0 | AP41: =26+26 -> 52 | AQ41: 0 | AR41: 0 | AS41: 0 | AT41: 11 | AU41: =14+61+72+164 -> 311 | AV41: =SUM(AO41:AU41) -> 374 | AW41: =+(AM41+(BR41*50/100))+(BS41*30/100)-BB41 -> 964.1 | AX41: 0 | AY41: 0 | AZ41: 0 | BA41: 0 | BB41: 0 | BC41: 0 | BD41: =15+14 -> 29 | BE41: 0 | BF41: 0 | BG41: 0 | BH41: 10 | BI41: =12+34+38+89 -> 173 | BJ41: =SUM(BC41:BI41) -> 212 | BK41: 36410 | BL41: =IFERROR(+BO41*1000/((BK41)*(BM41/1000)),0) -> 22.010056 | BM41: =AK41 -> 1010 | BN41: =+BK41*BM41/1000 -> 36774.1 | BO41: =820.3-10.9 -> 809.4 | BP41: 0 | BQ41: 0 | BR41: =AO41-BC41 -> 0 | BS41: =(AP41+AQ41+AR41+AS41+AT41+AU41)-(BD41+BE41+BF41+BG41+BH41+BI41) -> 162 | BT41: =BR41+BS41 -> 162 | BU41: =IFERROR(+BK41/AE41,0) -> 147.64801 | BV41: =IFERROR(+BK41/(AF41),0) -> 32.17568 | BW41: =IFERROR(+(AI41-AZ41)-BK41,0) -> 6753 | BX41: =IFERROR(+BW41/BK41,0) -> 0.18547102 | BY41: =IFERROR(+(AL41-BA41)-BN41,0) -> 6820.53 | BZ41: =IFERROR(+BY41/BN41,0) -> 0.18547102 | CA41: =IFERROR(+AW41-(BO41),0) -> 154.7 | CB41: =IFERROR(+CA41/BO41,1) -> 0.19112923 | CC41: 0 | CD41: 0 | CE41: movimiento de registros en dos ocasiones, rayas en impresión se intercambian anilox, problemas de arrastre del color verde y azul, paradas por sucio del color negro, | CF41: =IFERROR((BT41*1000)/BN41,"") -> 4.4052744 | CG41: REPETICION | CH41: 5 | CI41: 3500 | CJ41: =IF(BW41=0,"",CI41-BW41) -> -3253 | CK41: {=_xlfn.IFS(CJ41>0,"CUMPLE",CJ41<0,"NO CUMPLE",CJ41="","")} -> NO CUMPLE | CL41: 46111 | CM41: {=_xlfn.IFS(CL41-C41 > 0,"CUMPLE",CL41-C41 < 0,"NO CUMPLE")} -> NO CUMPLE | CN41: 38500 | CO41: =BK41-CN41 -> -2090 | CP41: 0 | CQ41: TELEPLASTIC | CR41: BOPP POCT PERLADO
A42: 01-6049 | B42: NF | C42: 46129 | D42: =IFERROR(VLOOKUP($A42,Hoja3!$A$3:$F$6000,2,FALSE),"") -> TXPCGM023C001 | E42: 16587 | F42: =IFERROR(VLOOKUP($A42,Hoja3!$A$3:$F$6000,6,FALSE),"") -> CORTE | G42: 1 | H42: =IFERROR(VLOOKUP($A42,Hoja3!$A$3:$F$6000,5,FALSE),"") -> CX | I42: =IFERROR(VLOOKUP($A42,Hoja3!$A$3:$F$6000,3,FALSE),"") -> PEPSI-COLA VENEZUELA, C.A. | J42: =IFERROR(VLOOKUP($A42,Hoja3!$A$3:$F$6000,4,FALSE),"") -> ETIQUETA IMPRESA GOLDEN MANZANA 2L | K42: 450 | L42: 0 | M42: 0 | N42: 20 | O42: 0 | P42: 0 | Q42: 0 | R42: 0 | S42: 0 | T42: 0 | U42: 0 | V42: 0 | W42: 0 | X42: 0 | Y42: 0 | Z42: 0 | AA42: 0 | AB42: 0 | AC42: 0 | AD42: =SUM(L42:AC42) -> 20 | AE42: 90 | AF42: =SUM(AD42:AE42) -> 110 | AG42: =AF42/(60*24) -> 0.076388889 | AH42: =IFERROR(AE42/AF42,0) -> 0.81818182 | AI42: 19100 | AJ42: 21 | AK42: 1010 | AL42: =IF(AM42=0,0,(+AI42*AK42/1000)) -> 19291 | AM42: 410 | AN42: 7 | AO42: 0 | AP42: =15+14 -> 29 | AQ42: 0 | AR42: 0 | AS42: 0 | AT42: 10 | AU42: =12+34+38+89 -> 173 | AV42: =SUM(AO42:AU42) -> 212 | AW42: =+(AM42+(BR42*50/100))+(BS42*30/100)-BB42 -> 434.6 | AX42: 0 | AY42: 0 | AZ42: 0 | BA42: 0 | BB42: 0 | BC42: 0 | BD42: =9+8 -> 17 | BE42: 0 | BF42: 0 | BG42: 0 | BH42: 9 | BI42: =11+20+21+52 -> 104 | BJ42: =SUM(BC42:BI42) -> 130 | BK42: 19000 | BL42: =IFERROR(+BO42*1000/((BK42)*(BM42/1000)),0) -> 22.152163 | BM42: =AK42 -> 1010 | BN42: =+BK42*BM42/1000 -> 19190 | BO42: =450-24.9 -> 425.1 | BP42: 0 | BQ42: 0 | BR42: =AO42-BC42 -> 0 | BS42: =(AP42+AQ42+AR42+AS42+AT42+AU42)-(BD42+BE42+BF42+BG42+BH42+BI42) -> 82 | BT42: =BR42+BS42 -> 82 | BU42: =IFERROR(+BK42/AE42,0) -> 211.11111 | BV42: =IFERROR(+BK42/(AF42),0) -> 172.72727 | BW42: =IFERROR(+(AI42-AZ42)-BK42,0) -> 100 | BX42: =IFERROR(+BW42/BK42,0) -> 0.0052631579 | BY42: =IFERROR(+(AL42-BA42)-BN42,0) -> 101 | BZ42: =IFERROR(+BY42/BN42,0) -> 0.0052631579 | CA42: =IFERROR(+AW42-(BO42),0) -> 9.5 | CB42: =IFERROR(+CA42/BO42,1) -> 0.022347683 | CC42: 0 | CD42: 0 | CE42: se realiza produccion con notificacion de falla por problemas de registros de color verde rama y fondo | CF42: =IFERROR((BT42*1000)/BN42,"") -> 4.2730589 | CG42: REPETICION | CH42: 0 | CI42: 3500 | CJ42: =IF(BW42=0,"",CI42-BW42) -> 3400 | CK42: {=_xlfn.IFS(CJ42>0,"CUMPLE",CJ42<0,"NO CUMPLE",CJ42="","")} -> CUMPLE | CL42: 46111 | CM42: {=_xlfn.IFS(CL42-C42 > 0,"CUMPLE",CL42-C42 < 0,"NO CUMPLE")} -> NO CUMPLE | CN42: 19000 | CO42: =BK42-CN42 -> 0 | CP42: 0 | CQ42: TELEPLASTIC | CR42: BOPP POCT PERLADO
A43: 000lm | B43: NF | C43: 46129 | D43: =IFERROR(VLOOKUP($A43,Hoja3!$A$3:$F$6000,2,FALSE),"") -> 000LM | E43: 000lm | F43: =IFERROR(VLOOKUP($A43,Hoja3!$A$3:$F$6000,6,FALSE),"") -> LIMPIEZA | G43: 0 | H43: =IFERROR(VLOOKUP($A43,Hoja3!$A$3:$F$6000,5,FALSE),"") -> CX | I43: =IFERROR(VLOOKUP($A43,Hoja3!$A$3:$F$6000,3,FALSE),"") -> LIMPIEZA GENERAL DE MAQUINA | J43: =IFERROR(VLOOKUP($A43,Hoja3!$A$3:$F$6000,4,FALSE),"") -> LIMPIEZA GENERAL DE MAQUINA | K43: 0 | L43: 0 | M43: 0 | N43: 0 | O43: 0 | P43: 0 | Q43: 30 | R43: 0 | S43: 0 | T43: 0 | U43: 0 | V43: 0 | W43: 0 | X43: 0 | Y43: 0 | Z43: 0 | AA43: 0 | AB43: 0 | AC43: 0 | AD43: =SUM(L43:AC43) -> 30 | AE43: 0 | AF43: =SUM(AD43:AE43) -> 30 | AG43: =AF43/(60*24) -> 0.020833333 | AH43: =IFERROR(AE43/AF43,0) -> 0 | AI43: 0 | AJ43: 0 | AK43: 0 | AL43: 0 | AM43: 0 | AN43: 0 | AO43: 0 | AP43: 0 | AQ43: 0 | AR43: 0 | AS43: 0 | AT43: 0 | AU43: 0 | AV43: =SUM(AO43:AU43) -> 0 | AW43: 0 | AX43: 0 | AY43: 0 | AZ43: 0 | BA43: 0 | BB43: 0 | BC43: 0 | BD43: 0 | BE43: 0 | BF43: 0 | BG43: 0 | BH43: 0 | BI43: 0 | BJ43: 0 | BK43: 0 | BL43: 0 | BM43: =AK43 -> 0 | BN43: =+BK43*BM43/1000 -> 0 | BO43: 0 | BP43: 0 | BQ43: 0 | BR43: 0 | BS43: 0 | BT43: 0 | BU43: =IFERROR(+BK43/AE43,0) -> 0 | BV43: =IFERROR(+BK43/(AF43),0) -> 0 | BW43: =IFERROR(+(AI43-AZ43)-BK43,0) -> 0 | BX43: =IFERROR(+BW43/BK43,0) -> 0 | BY43: =IFERROR(+(AL43-BA43)-BN43,0) -> 0 | BZ43: =IFERROR(+BY43/BN43,0) -> 0 | CA43: =IFERROR(+AW43-(BO43),0) -> 0 | CB43: =IFERROR(+CA43/BO43,1) -> 1 | CC43: 0 | CD43: 0 | CE43: se realiza limpieza general de maquina | CF43: 0 | CG43: LIMPIEZA | CH43: 0 | CI43: 0 | CJ43: 0 | CK43: 0 | CL43: 0 | CM43: {=_xlfn.IFS(CL43-C43 > 0,"CUMPLE",CL43-C43 < 0,"NO CUMPLE")} -> NO CUMPLE | CN43: 0 | CO43: 0 | CP43: 0
A44: 01-6055 | B44: NF | C44: 46132 | D44: =IFERROR(VLOOKUP($A44,Hoja3!$A$3:$F$6000,2,FALSE),"") -> TXPCGM023C001 | E44: 16593 | F44: =IFERROR(VLOOKUP($A44,Hoja3!$A$3:$F$6000,6,FALSE),"") -> CORTE | G44: 1 | H44: =IFERROR(VLOOKUP($A44,Hoja3!$A$3:$F$6000,5,FALSE),"") -> CX | I44: =IFERROR(VLOOKUP($A44,Hoja3!$A$3:$F$6000,3,FALSE),"") -> PEPSI-COLA VENEZUELA, C.A. | J44: =IFERROR(VLOOKUP($A44,Hoja3!$A$3:$F$6000,4,FALSE),"") -> ETIQUETA IMPRESA GOLDEN MANZANA 2L | K44: 334 | L44: =15+15 -> 30 | M44: 0 | N44: =50+20 -> 70 | O44: 20 | P44: =30+20 -> 50 | Q44: 0 | R44: 0 | S44: 10 | T44: 0 | U44: 0 | V44: 20 | W44: 0 | X44: 0 | Y44: 0 | Z44: 0 | AA44: 0 | AB44: 0 | AC44: 0 | AD44: =SUM(L44:AC44) -> 200 | AE44: 64.8 | AF44: =SUM(AD44:AE44) -> 264.8 | AG44: =AF44/(60*24) -> 0.18388889 | AH44: =IFERROR(AE44/AF44,0) -> 0.24471299 | AI44: 19000 | AJ44: 21 | AK44: 1010 | AL44: =IF(AM44=0,0,(+AI44*AK44/1000)) -> 19190 | AM44: =303+100 -> 403 | AN44: 7 | AO44: 0 | AP44: =9+8 -> 17 | AQ44: 0 | AR44: 0 | AS44: 0 | AT44: 9 | AU44: =11+20+21+52 -> 104 | AV44: =SUM(AO44:AU44) -> 130 | AW44: =+(AM44+(BR44*50/100))+(BS44*30/100)-BB44 -> 421 | AX44: 0 | AY44: 0 | AZ44: 0 | BA44: 0 | BB44: 0 | BC44: 0 | BD44: =5+4 -> 9 | BE44: 0 | BF44: 0 | BG44: 0 | BH44: 8 | BI44: =10+10+8+25 -> 53 | BJ44: =SUM(BC44:BI44) -> 70 | BK44: 18192 | BL44: =IFERROR(+BO44*1000/((BK44)*(BM44/1000)),0) -> 22.667999 | BM44: =AK44 -> 1010 | BN44: =+BK44*BM44/1000 -> 18373.92 | BO44: =434-17.5 -> 416.5 | BP44: 0 | BQ44: 0 | BR44: =AO44-BC44 -> 0 | BS44: =(AP44+AQ44+AR44+AS44+AT44+AU44)-(BD44+BE44+BF44+BG44+BH44+BI44) -> 60 | BT44: =BR44+BS44 -> 60 | BU44: =IFERROR(+BK44/AE44,0) -> 280.74074 | BV44: =IFERROR(+BK44/(AF44),0) -> 68.700906 | BW44: =IFERROR(+(AI44-AZ44)-BK44,0) -> 808 | BX44: =IFERROR(+BW44/BK44,0) -> 0.044415128 | BY44: =IFERROR(+(AL44-BA44)-BN44,0) -> 816.08 | BZ44: =IFERROR(+BY44/BN44,0) -> 0.044415128 | CA44: =IFERROR(+AW44-(BO44),0) -> 4.5 | CB44: =IFERROR(+CA44/BO44,1) -> 0.010804322 | CC44: 0 | CD44: 0 | CE44: se cambia tinta del color negro por sucio en trama, se corre trabajo con notificacion de falla por defecto en plancha del color verde. | CF44: =IFERROR((BT44*1000)/BN44,"") -> 3.2654981 | CG44: REPETICION | CH44: 5 | CI44: 3500 | CJ44: =IF(BW44=0,"",CI44-BW44) -> 2692 | CK44: {=_xlfn.IFS(CJ44>0,"CUMPLE",CJ44<0,"NO CUMPLE",CJ44="","")} -> CUMPLE | CL44: 46111 | CM44: {=_xlfn.IFS(CL44-C44 > 0,"CUMPLE",CL44-C44 < 0,"NO CUMPLE")} -> NO CUMPLE | CN44: 14000 | CO44: =BK44-CN44 -> 4192 | CP44: 0 | CQ44: TELEPLASTIC | CR44: BOPP POCT PERLADO
A45: 01-6039 | B45: NF | C45: 46132 | D45: =IFERROR(VLOOKUP($A45,Hoja3!$A$3:$F$6000,2,FALSE),"") -> TXPCGU023B001 | E45: 16577 | F45: =IFERROR(VLOOKUP($A45,Hoja3!$A$3:$F$6000,6,FALSE),"") -> CORTE | G45: 1 | H45: =IFERROR(VLOOKUP($A45,Hoja3!$A$3:$F$6000,5,FALSE),"") -> CX | I45: =IFERROR(VLOOKUP($A45,Hoja3!$A$3:$F$6000,3,FALSE),"") -> PEPSI-COLA VENEZUELA, C.A. | J45: =IFERROR(VLOOKUP($A45,Hoja3!$A$3:$F$6000,4,FALSE),"") -> ETIQUETA IMPRESA GOLDEN UVA 1,5L | K45: 650 | L45: =15+25+25 -> 65 | M45: 0 | N45: =60+10+10+20 -> 100 | O45: 20 | P45: 0 | Q45: 0 | R45: 0 | S45: 10 | T45: 0 | U45: 0 | V45: 10 | W45: 0 | X45: 0 | Y45: 0 | AA45: 0 | AB45: 0 | AC45: 0 | AD45: =SUM(L45:AC45) -> 205 | AE45: 189 | AF45: =SUM(AD45:AE45) -> 394 | AG45: =AF45/(60*24) -> 0.27361111 | AH45: =IFERROR(AE45/AF45,0) -> 0.47969543 | AI45: 32965 | AJ45: 21 | AK45: 1010 | AL45: =IF(AM45=0,0,(+AI45*AK45/1000)) -> 33294.65 | AM45: 713 | AN45: 7 | AO45: 0 | AP45: =17+26 -> 43 | AQ45: 0 | AR45: 0 | AS45: 0 | AT45: 13 | AU45: =14+35+50+210 -> 309 | AV45: =SUM(AO45:AU45) -> 365 | AW45: =+(AM45+(BR45*50/100))+(BS45*30/100)-BB45 -> 747.5 | AX45: 0 | AY45: 0 | AZ45: 0 | BA45: 0 | BB45: 0 | BC45: 0 | BD45: =15+13 -> 28 | BE45: 0 | BF45: 0 | BG45: 0 | BH45: 11 | BI45: =11+18+22+160 -> 211 | BJ45: =SUM(BC45:BI45) -> 250 | BK45: 28500 | BL45: =IFERROR(+BO45*1000/((BK45)*(BM45/1000)),0) -> 22.209484 | BM45: =AK45 -> 1010 | BN45: =+BK45*BM45/1000 -> 28785 | BO45: =669-29.7 -> 639.3 | BP45: 0 | BQ45: 0 | BR45: =AO45-BC45 -> 0 | BS45: =(AP45+AQ45+AR45+AS45+AT45+AU45)-(BD45+BE45+BF45+BG45+BH45+BI45) -> 115 | BT45: =BR45+BS45 -> 115 | BU45: =IFERROR(+BK45/AE45,0) -> 150.79365 | BV45: =IFERROR(+BK45/(AF45),0) -> 72.335025 | BW45: =IFERROR(+(AI45-AZ45)-BK45,0) -> 4465 | BX45: =IFERROR(+BW45/BK45,0) -> 0.15666667 | BY45: =IFERROR(+(AL45-BA45)-BN45,0) -> 4509.65 | BZ45: =IFERROR(+BY45/BN45,0) -> 0.15666667 | CA45: =IFERROR(+AW45-(BO45),0) -> 108.2 | CB45: =IFERROR(+CA45/BO45,1) -> 0.16924761 | CC45: 0 | CD45: 0 | CE45: problemas con el color negro, se recalibra, se recalibra y limpia plancha | CF45: =IFERROR((BT45*1000)/BN45,"") -> 3.9951364 | CG45: REPETICION | CH45: 5 | CI45: 3500 | CJ45: =IF(BW45=0,"",CI45-BW45) -> -965 | CK45: {=_xlfn.IFS(CJ45>0,"CUMPLE",CJ45<0,"NO CUMPLE",CJ45="","")} -> NO CUMPLE | CL45: 46111 | CM45: {=_xlfn.IFS(CL45-C45 > 0,"CUMPLE",CL45-C45 < 0,"NO CUMPLE")} -> NO CUMPLE | CN45: 28500 | CO45: =BK45-CN45 -> 0 | CP45: 0 | CQ45: TELEPLASTIC | CR45: BOPP POCT PERLADO
A46: 01-6050 | B46: NF | C46: 46132 | D46: =IFERROR(VLOOKUP($A46,Hoja3!$A$3:$F$6000,2,FALSE),"") -> TXPCGU023B001 | E46: 16588 | F46: =IFERROR(VLOOKUP($A46,Hoja3!$A$3:$F$6000,6,FALSE),"") -> CORTE | G46: 1 | H46: =IFERROR(VLOOKUP($A46,Hoja3!$A$3:$F$6000,5,FALSE),"") -> CX | I46: =IFERROR(VLOOKUP($A46,Hoja3!$A$3:$F$6000,3,FALSE),"") -> PEPSI-COLA VENEZUELA, C.A. | J46: =IFERROR(VLOOKUP($A46,Hoja3!$A$3:$F$6000,4,FALSE),"") -> ETIQUETA IMPRESA GOLDEN UVA 1,5L | K46: 330 | L46: 0 | M46: 0 | N46: 0 | O46: 0 | P46: =30+40 -> 70 | Q46: 0 | R46: 0 | S46: 10 | T46: 0 | U46: 0 | V46: 0 | W46: 0 | X46: 0 | Y46: 0 | Z46: 0 | AA46: 0 | AB46: 0 | AC46: 0 | AD46: =SUM(L46:AC46) -> 80 | AE46: 70.2 | AF46: =SUM(AD46:AE46) -> 150.2 | AG46: =AF46/(60*24) -> 0.10430556 | AH46: =IFERROR(AE46/AF46,0) -> 0.46737683 | AI46: 14035 | AJ46: 21 | AK46: 1010 | AL46: =IF(AM46=0,0,(+AI46*AK46/1000)) -> 14175.35 | AM46: 310.4 | AN46: 7 | AO46: 0 | AP46: =15+13 -> 28 | AQ46: 0 | AR46: 0 | AS46: 0 | AT46: 11 | AU46: =11+18+22+160 -> 211 | AV46: =SUM(AO46:AU46) -> 250 | AW46: =+(AM46+(BR46*50/100))+(BS46*30/100)-BB46 -> 327.5 | AX46: 0 | AY46: 0 | AZ46: 0 | BA46: 0 | BB46: 0 | BC46: 0 | BD46: =14+7 -> 21 | BE46: 0 | BF46: 0 | BG46: 0 | BH46: 10 | BI46: =9+10+8+135 -> 162 | BJ46: =SUM(BC46:BI46) -> 193 | BK46: 14000 | BL46: =IFERROR(+BO46*1000/((BK46)*(BM46/1000)),0) -> 22.213579 | BM46: =AK46 -> 1010 | BN46: =+BK46*BM46/1000 -> 14140 | BO46: =334-19.9 -> 314.1 | BP46: 0 | BQ46: 0 | BR46: =AO46-BC46 -> 0 | BS46: =(AP46+AQ46+AR46+AS46+AT46+AU46)-(BD46+BE46+BF46+BG46+BH46+BI46) -> 57 | BT46: =BR46+BS46 -> 57 | BU46: =IFERROR(+BK46/AE46,0) -> 199.4302 | BV46: =IFERROR(+BK46/(AF46),0) -> 93.209055 | BW46: =IFERROR(+(AI46-AZ46)-BK46,0) -> 35 | BX46: =IFERROR(+BW46/BK46,0) -> 0.0025 | BY46: =IFERROR(+(AL46-BA46)-BN46,0) -> 35.35 | BZ46: =IFERROR(+BY46/BN46,0) -> 0.0025 | CA46: =IFERROR(+AW46-(BO46),0) -> 13.4 | CB46: =IFERROR(+CA46/BO46,1) -> 0.042661573 | CC46: 0 | CD46: 0 | CE46: se culmina produccion sin novedad | CF46: =IFERROR((BT46*1000)/BN46,"") -> 4.0311174 | CG46: REPETICION | CH46: 0 | CI46: 3500 | CJ46: =IF(BW46=0,"",CI46-BW46) -> 3465 | CK46: {=_xlfn.IFS(CJ46>0,"CUMPLE",CJ46<0,"NO CUMPLE",CJ46="","")} -> CUMPLE | CL46: 46111 | CM46: {=_xlfn.IFS(CL46-C46 > 0,"CUMPLE",CL46-C46 < 0,"NO CUMPLE")} -> NO CUMPLE | CN46: 14000 | CO46: =BK46-CN46 -> 0 | CP46: 0 | CQ46: TELEPLASTIC | CR46: BOPP POCT PERLADO
A47: 000pr | B47: NF | C47: 46132 | D47: =IFERROR(VLOOKUP($A47,Hoja3!$A$3:$F$6000,2,FALSE),"") -> 000pr | E47: 000pr | F47: =IFERROR(VLOOKUP($A47,Hoja3!$A$3:$F$6000,6,FALSE),"") -> PRUEBA | G47: 0 | H47: =IFERROR(VLOOKUP($A47,Hoja3!$A$3:$F$6000,5,FALSE),"") -> CX | I47: =IFERROR(VLOOKUP($A47,Hoja3!$A$3:$F$6000,3,FALSE),"") -> PRUEBAS | J47: =IFERROR(VLOOKUP($A47,Hoja3!$A$3:$F$6000,4,FALSE),"") -> PRUEBAS VARIAS | K47: 0 | L47: 20 | M47: 0 | N47: 0 | O47: 0 | P47: 0 | Q47: 0 | R47: 0 | S47: 0 | T47: 0 | U47: 0 | V47: 0 | W47: 25 | X47: 0 | Y47: 0 | Z47: 0 | AA47: 0 | AB47: 0 | AC47: 0 | AD47: =SUM(L47:AC47) -> 45 | AE47: 4.8 | AF47: =SUM(AD47:AE47) -> 49.8 | AG47: =AF47/(60*24) -> 0.034583333 | AH47: =IFERROR(AE47/AF47,0) -> 0.096385542 | AI47: 0 | AJ47: 0 | AK47: 0 | AL47: =IF(AM47=0,0,(+AI47*AK47/1000)) -> 0 | AM47: 0 | AN47: 0 | AO47: 0 | AP47: 0 | AQ47: 0 | AR47: 0 | AS47: 0 | AT47: 0 | AU47: 0 | AV47: =SUM(AO47:AU47) -> 0 | AW47: =+(AM47+(BR47*50/100))+(BS47*30/100)-BB47 -> 0 | AX47: 0 | AY47: 0 | AZ47: 0 | BA47: 0 | BB47: 0 | BC47: 0 | BD47: 0 | BE47: 0 | BF47: 0 | BG47: 0 | BH47: 0 | BI47: 0 | BJ47: =SUM(BC47:BI47) -> 0 | BK47: 0 | BL47: =IFERROR(+BO47*1000/((BK47)*(BM47/1000)),0) -> 0 | BM47: =AK47 -> 0 | BN47: =+BK47*BM47/1000 -> 0 | BO47: 0 | BP47: 0 | BQ47: 0 | BR47: =AO47-BC47 -> 0 | BS47: =(AP47+AQ47+AR47+AS47+AT47+AU47)-(BD47+BE47+BF47+BG47+BH47+BI47) -> 0 | BT47: =BR47+BS47 -> 0 | BU47: 0 | BV47: 0 | BW47: 0 | BX47: 0 | BY47: =IFERROR(+(AL47-BA47)-BN47,0) -> 0 | BZ47: =IFERROR(+BY47/BN47,0) -> 0 | CA47: =IFERROR(+AW47-(BO47),0) -> 0 | CB47: =IFERROR(+CA47/BO47,1) -> 1 | CC47: 0 | CD47: 0 | CE47: se realiza prueba de justy 400ml | CF47: =IFERROR((BT47*1000)/BN47,"") | CG47: PRUEBA | CH47: 0 | CI47: 0 | CJ47: =IF(BW47=0,"",CI47-BW47) | CK47: {=_xlfn.IFS(CJ47>0,"CUMPLE",CJ47<0,"NO CUMPLE",CJ47="","")} -> CUMPLE | CL47: 0 | CM47: {=_xlfn.IFS(CL47-C47 > 0,"CUMPLE",CL47-C47 < 0,"NO CUMPLE")} -> NO CUMPLE | CN47: 0 | CO47: =BK47-CN47 -> 0 | CP47: 0 | CQ47: TELEPLASTIC | CR47: BOPP POCT PERLADO
A48: 01-6046 | B48: NF | C48: 46132 | D48: =IFERROR(VLOOKUP($A48,Hoja3!$A$3:$F$6000,2,FALSE),"") -> TXPCSC023C002 | E48: 16584 | F48: =IFERROR(VLOOKUP($A48,Hoja3!$A$3:$F$6000,6,FALSE),"") -> CORTE | G48: 1 | H48: =IFERROR(VLOOKUP($A48,Hoja3!$A$3:$F$6000,5,FALSE),"") -> CX | I48: =IFERROR(VLOOKUP($A48,Hoja3!$A$3:$F$6000,3,FALSE),"") -> PEPSI-COLA VENEZUELA, C.A. | J48: =IFERROR(VLOOKUP($A48,Hoja3!$A$3:$F$6000,4,FALSE),"") -> ETIQUETA IMPRESA SEVEN UP CERO 1,5 L | K48: 1200 | L48: =25+35+15 -> 75 | M48: 135 | N48: =110+130 -> 240 | O48: =210+20 -> 230 | P48: =60+30+65+12 -> 167 | Q48: 0 | R48: 0 | S48: =20+10+15+15 -> 60 | T48: 10 | U48: 0 | V48: =20+15+20+10+40+60 -> 165 | W48: 0 | X48: 0 | Y48: 0 | Z48: 0 | AA48: 0 | AB48: 30 | AC48: 0 | AD48: =SUM(L48:AC48) -> 1112 | AE48: 308.4 | AF48: =SUM(AD48:AE48) -> 1420.4 | AG48: =AF48/(60*24) -> 0.98638889 | AH48: =IFERROR(AE48/AF48,0) -> 0.21712194 | AI48: 56700 | AJ48: 21 | AK48: 1010 | AL48: =IF(AM48=0,0,(+AI48*AK48/1000)) -> 57267 | AM48: 1312.9 | AN48: 6 | AO48: 0 | AP48: 0 | AQ48: 0 | AR48: 24 | AS48: 0 | AT48: 13 | AU48: =55+39+262+202 -> 558 | AV48: =SUM(AO48:AU48) -> 595 | AW48: =+(AM48+(BR48*50/100))+(BS48*30/100)-BB48 -> 1383.7 | AX48: 0 | AY48: 0 | AZ48: 0 | BA48: 0 | BB48: 0 | BC48: 0 | BD48: 0 | BE48: 0 | BF48: 16 | BG48: 0 | BH48: 10 | BI48: =35+26+147+125 -> 333 | BJ48: =SUM(BC48:BI48) -> 359 | BK48: 49504 | BL48: =IFERROR(+BO48*1000/((BK48)*(BM48/1000)),0) -> 23.250446 | BM48: =AK48 -> 1010 | BN48: =+BK48*BM48/1000 -> 49999.04 | BO48: =1222.1-59.6 -> 1162.5 | BP48: 0 | BQ48: 0 | BR48: =AO48-BC48 -> 0 | BS48: =(AP48+AQ48+AR48+AS48+AT48+AU48)-(BD48+BE48+BF48+BG48+BH48+BI48) -> 236 | BT48: =BR48+BS48 -> 236 | BU48: =IFERROR(+BK48/AE48,0) -> 160.51881 | BV48: =IFERROR(+BK48/(AF48),0) -> 34.852154 | BW48: =IFERROR(+(AI48-AZ48)-BK48,0) -> 7196 | BX48: =IFERROR(+BW48/BK48,0) -> 0.14536199 | BY48: =IFERROR(+(AL48-BA48)-BN48,0) -> 7267.96 | BZ48: =IFERROR(+BY48/BN48,0) -> 0.14536199 | CA48: =IFERROR(+AW48-(BO48),0) -> 221.2 | CB48: =IFERROR(+CA48/BO48,1) -> 0.19027957 | CC48: 0 | CD48: 0 | CE48: Registros compensados, copiado del verde fondo sobre el mismo, luego de varias muestras se logra tono pero persiste el copiado, se agrega retardante, se cambia tinta, se verifican exhaustores, racleta, adaptador, se cambia de estacion, se realiza prueba con varias velocidades | CF48: =IFERROR((BT48*1000)/BN48,"") -> 4.7200906 | CG48: REPETICION | CH48: 4 | CI48: 3500 | CJ48: =IF(BW48=0,"",CI48-BW48) -> -3696 | CK48: {=_xlfn.IFS(CJ48>0,"CUMPLE",CJ48<0,"NO CUMPLE",CJ48="","")} -> NO CUMPLE | CL48: 46111 | CM48: {=_xlfn.IFS(CL48-C48 > 0,"CUMPLE",CL48-C48 < 0,"NO CUMPLE")} -> NO CUMPLE | CN48: 52000 | CO48: =BK48-CN48 -> -2496 | CP48: 0 | CQ48: TELEPLASTIC | CR48: BOPP POCT PERLADO
A49: 01-6054 | B49: NF | C49: 46132 | D49: =IFERROR(VLOOKUP($A49,Hoja3!$A$3:$F$6000,2,FALSE),"") -> TXPCSC023C002 | E49: 16592 | F49: =IFERROR(VLOOKUP($A49,Hoja3!$A$3:$F$6000,6,FALSE),"") -> CORTE | G49: 1 | H49: =IFERROR(VLOOKUP($A49,Hoja3!$A$3:$F$6000,5,FALSE),"") -> CX | I49: =IFERROR(VLOOKUP($A49,Hoja3!$A$3:$F$6000,3,FALSE),"") -> PEPSI-COLA VENEZUELA, C.A. | J49: =IFERROR(VLOOKUP($A49,Hoja3!$A$3:$F$6000,4,FALSE),"") -> ETIQUETA IMPRESA SEVEN UP CERO 1,5 L | K49: 500 | L49: 0 | M49: 0 | N49: 0 | O49: 0 | P49: 0 | Q49: 0 | R49: 0 | S49: =15+10 -> 25 | T49: 0 | U49: 0 | V49: 0 | W49: 0 | X49: 0 | Y49: 0 | Z49: 0 | AA49: 0 | AB49: 30 | AC49: 0 | AD49: =SUM(L49:AC49) -> 55 | AE49: 155.4 | AF49: =SUM(AD49:AE49) -> 210.4 | AG49: =AF49/(60*24) -> 0.14611111 | AH49: =IFERROR(AE49/AF49,0) -> 0.73859316 | AI49: 23080 | AJ49: 21 | AK49: 1010 | AL49: =IF(AM49=0,0,(+AI49*AK49/1000)) -> 23310.8 | AM49: 561 | AN49: 6 | AO49: 0 | AP49: 0 | AQ49: 0 | AR49: 16 | AS49: 0 | AT49: 10 | AU49: =35+26+147+125 -> 333 | AV49: =SUM(AO49:AU49) -> 359 | AW49: =+(AM49+(BR49*50/100))+(BS49*30/100)-BB49 -> 591.3 | AX49: 0 | AY49: 0 | AZ49: 0 | BA49: 0 | BB49: 0 | BC49: 0 | BD49: 0 | BE49: 0 | BF49: 13 | BG49: 0 | BH49: 9 | BI49: =26+20+98+92 -> 236 | BJ49: =SUM(BC49:BI49) -> 258 | BK49: 21427 | BL49: =IFERROR(+BO49*1000/((BK49)*(BM49/1000)),0) -> 23.399736 | BM49: =AK49 -> 1010 | BN49: =+BK49*BM49/1000 -> 21641.27 | BO49: =515-8.6 -> 506.4 | BP49: 0 | BQ49: 0 | BR49: =AO49-BC49 -> 0 | BS49: =(AP49+AQ49+AR49+AS49+AT49+AU49)-(BD49+BE49+BF49+BG49+BH49+BI49) -> 101 | BT49: =BR49+BS49 -> 101 | BU49: =IFERROR(+BK49/AE49,0) -> 137.88288 | BV49: =IFERROR(+BK49/(AF49),0) -> 101.83935 | BW49: =IFERROR(+(AI49-AZ49)-BK49,0) -> 1653 | BX49: =IFERROR(+BW49/BK49,0) -> 0.077145657 | BY49: =IFERROR(+(AL49-BA49)-BN49,0) -> 1669.53 | BZ49: =IFERROR(+BY49/BN49,0) -> 0.077145657 | CA49: =IFERROR(+AW49-(BO49),0) -> 84.9 | CB49: =IFERROR(+CA49/BO49,1) -> 0.16765403 | CC49: 0 | CD49: 0 | CE49: se arranca produccion con leve repinte del color verde fondo | CF49: =IFERROR((BT49*1000)/BN49,"") -> 4.6670089 | CG49: REPETICION | CH49: 4 | CI49: 3500 | CJ49: =IF(BW49=0,"",CI49-BW49) -> 1847 | CK49: {=_xlfn.IFS(CJ49>0,"CUMPLE",CJ49<0,"NO CUMPLE",CJ49="","")} -> CUMPLE | CL49: 46111 | CM49: {=_xlfn.IFS(CL49-C49 > 0,"CUMPLE",CL49-C49 < 0,"NO CUMPLE")} -> NO CUMPLE | CN49: 22000 | CO49: =BK49-CN49 -> -573 | CP49: 0 | CQ49: TELEPLASTIC | CR49: BOPP POCT PERLADO
A50: 01-6033 | B50: NF | C50: 46133 | D50: =IFERROR(VLOOKUP($A50,Hoja3!$A$3:$F$6000,2,FALSE),"") -> TXPCSC023D001 | E50: 16571 | F50: =IFERROR(VLOOKUP($A50,Hoja3!$A$3:$F$6000,6,FALSE),"") -> CORTE | G50: 1 | H50: =IFERROR(VLOOKUP($A50,Hoja3!$A$3:$F$6000,5,FALSE),"") -> CX | I50: =IFERROR(VLOOKUP($A50,Hoja3!$A$3:$F$6000,3,FALSE),"") -> PEPSI-COLA VENEZUELA, C.A. | J50: =IFERROR(VLOOKUP($A50,Hoja3!$A$3:$F$6000,4,FALSE),"") -> ETIQUETA IMPRESA SEVEN UP CERO 1 L | K50: 2500 | L50: =20+20 -> 40 | M50: 0 | N50: 40 | O50: 20 | P50: =10+60+15 -> 85 | Q50: 0 | R50: 0 | S50: =10+10+10+10 -> 40 | T50: 10 | U50: 0 | V50: 20 | W50: 0 | X50: 20 | Y50: 0 | Z50: 0 | AA50: 0 | AB50: 30 | AC50: 0 | AD50: =SUM(L50:AC50) -> 305 | AE50: 665.4 | AF50: =SUM(AD50:AE50) -> 970.4 | AG50: =AF50/(60*24) -> 0.67388889 | AH50: =IFERROR(AE50/AF50,0) -> 0.68569662 | AI50: 111600 | AJ50: 21 | AK50: 1010 | AL50: =IF(AM50=0,0,(+AI50*AK50/1000)) -> 112716 | AM50: 2544.9 | AN50: 6 | AO50: 0 | AP50: 0 | AQ50: 0 | AR50: 22 | AS50: 0 | AT50: 24 | AU50: =42+36+316+228 -> 622 | AV50: =SUM(AO50:AU50) -> 668 | AW50: =+(AM50+(BR50*50/100))+(BS50*30/100)-BB50 -> 2663.4 | AX50: 0 | AY50: 0 | AZ50: 0 | BA50: 0 | BB50: 0 | BC50: 0 | BD50: 0 | BE50: 0 | BF50: 18 | BG50: 0 | BH50: 15 | BI50: =21+27+124+68 -> 240 | BJ50: =SUM(BC50:BI50) -> 273 | BK50: 104945 | BL50: =IFERROR(+BO50*1000/((BK50)*(BM50/1000)),0) -> 23.120078 | BM50: =AK50 -> 1010 | BN50: =+BK50*BM50/1000 -> 105994.45 | BO50: =2510.5-59.9 -> 2450.6 | BP50: 0 | BQ50: 0 | BR50: =AO50-BC50 -> 0 | BS50: =(AP50+AQ50+AR50+AS50+AT50+AU50)-(BD50+BE50+BF50+BG50+BH50+BI50) -> 395 | BT50: =BR50+BS50 -> 395 | BU50: =IFERROR(+BK50/AE50,0) -> 157.71716 | BV50: =IFERROR(+BK50/(AF50),0) -> 108.14613 | BW50: =IFERROR(+(AI50-AZ50)-BK50,0) -> 6655 | BX50: =IFERROR(+BW50/BK50,0) -> 0.063414169 | BY50: =IFERROR(+(AL50-BA50)-BN50,0) -> 6721.55 | BZ50: =IFERROR(+BY50/BN50,0) -> 0.063414169 | CA50: =IFERROR(+AW50-(BO50),0) -> 212.8 | CB50: =IFERROR(+CA50/BO50,1) -> 0.086835877 | CC50: 0 | CD50: 0 | CE50: Falla axial, genera poroblemas de registro, se bajan planchas de verde c.b y verde fondo para corregir regstros | CF50: =IFERROR((BT50*1000)/BN50,"") -> 3.7266102 | CG50: REPETICION | CH50: 4 | CI50: 3500 | CJ50: =IF(BW50=0,"",CI50-BW50) -> -3155 | CK50: {=_xlfn.IFS(CJ50>0,"CUMPLE",CJ50<0,"NO CUMPLE",CJ50="","")} -> NO CUMPLE | CL50: 46111 | CM50: {=_xlfn.IFS(CL50-C50 > 0,"CUMPLE",CL50-C50 < 0,"NO CUMPLE")} -> NO CUMPLE | CN50: 107500 | CO50: =BK50-CN50 -> -2555 | CP50: 1000 | CQ50: TELEPLASTIC | CR50: BOPP POCT PERLADO
A51: 01-6041 | B51: NF | C51: 46134 | D51: =IFERROR(VLOOKUP($A51,Hoja3!$A$3:$F$6000,2,FALSE),"") -> TXPCSC023D001 | E51: 16579 | F51: =IFERROR(VLOOKUP($A51,Hoja3!$A$3:$F$6000,6,FALSE),"") -> CORTE | G51: 1 | H51: =IFERROR(VLOOKUP($A51,Hoja3!$A$3:$F$6000,5,FALSE),"") -> CX | I51: =IFERROR(VLOOKUP($A51,Hoja3!$A$3:$F$6000,3,FALSE),"") -> PEPSI-COLA VENEZUELA, C.A. | J51: =IFERROR(VLOOKUP($A51,Hoja3!$A$3:$F$6000,4,FALSE),"") -> ETIQUETA IMPRESA SEVEN UP CERO 1 L | K51: 650 | L51: 0 | M51: 0 | N51: 0 | O51: 0 | P51: 0 | Q51: 0 | R51: 0 | S51: 0 | T51: 0 | U51: 0 | V51: 0 | W51: 0 | X51: 0 | Y51: 0 | Z51: 0 | AA51: 0 | AB51: 0 | AC51: 0 | AD51: =SUM(L51:AC51) -> 0 | AE51: 145.2 | AF51: =SUM(AD51:AE51) -> 145.2 | AG51: =AF51/(60*24) -> 0.10083333 | AH51: =IFERROR(AE51/AF51,0) -> 1 | AI51: 28950 | AJ51: 21 | AK51: 1010 | AL51: =IF(AM51=0,0,(+AI51*AK51/1000)) -> 29239.5 | AM51: 645.4 | AN51: 6 | AO51: 0 | AP51: 0 | AQ51: 0 | AR51: 18 | AS51: 0 | AT51: 15 | AU51: =21+27+124+68 -> 240 | AV51: =SUM(AO51:AU51) -> 273 | AW51: =+(AM51+(BR51*50/100))+(BS51*30/100)-BB51 -> 677.5 | AX51: 0 | AY51: 0 | AZ51: 0 | BA51: 0 | BB51: 0 | BC51: 0 | BD51: 0 | BE51: 0 | BF51: 17 | BG51: 0 | BH51: 13 | BI51: =15+24+72+25 -> 136 | BJ51: =SUM(BC51:BI51) -> 166 | BK51: 28650 | BL51: =IFERROR(+BO51*1000/((BK51)*(BM51/1000)),0) -> 22.739447 | BM51: =AK51 -> 1010 | BN51: =+BK51*BM51/1000 -> 28936.5 | BO51: 658 | BP51: 0 | BQ51: 0 | BR51: =AO51-BC51 -> 0 | BS51: =(AP51+AQ51+AR51+AS51+AT51+AU51)-(BD51+BE51+BF51+BG51+BH51+BI51) -> 107 | BT51: =BR51+BS51 -> 107 | BU51: =IFERROR(+BK51/AE51,0) -> 197.31405 | BV51: =IFERROR(+BK51/(AF51),0) -> 197.31405 | BW51: =IFERROR(+(AI51-AZ51)-BK51,0) -> 300 | BX51: =IFERROR(+BW51/BK51,0) -> 0.010471204 | BY51: =IFERROR(+(AL51-BA51)-BN51,0) -> 303 | BZ51: =IFERROR(+BY51/BN51,0) -> 0.010471204 | CA51: =IFERROR(+AW51-(BO51),0) -> 19.5 | CB51: =IFERROR(+CA51/BO51,1) -> 0.029635258 | CC51: 0 | CD51: 0 | CE51: se culmina produccion sin novedad | CF51: =IFERROR((BT51*1000)/BN51,"") -> 3.697752 | CG51: REPETICION | CH51: 4 | CI51: 3500 | CJ51: =IF(BW51=0,"",CI51-BW51) -> 3200 | CK51: {=_xlfn.IFS(CJ51>0,"CUMPLE",CJ51<0,"NO CUMPLE",CJ51="","")} -> CUMPLE | CL51: 46111 | CM51: {=_xlfn.IFS(CL51-C51 > 0,"CUMPLE",CL51-C51 < 0,"NO CUMPLE")} -> NO CUMPLE | CN51: 29000 | CO51: =BK51-CN51 -> -350 | CP51: 0 | CQ51: TELEPLASTIC | CR51: BOPP POCT PERLADO
A52: 01-6047 | B52: NF | C52: 46134 | D52: =IFERROR(VLOOKUP($A52,Hoja3!$A$3:$F$6000,2,FALSE),"") -> TXPCSC023A002 | E52: 16585 | F52: =IFERROR(VLOOKUP($A52,Hoja3!$A$3:$F$6000,6,FALSE),"") -> CORTE | G52: 1 | H52: =IFERROR(VLOOKUP($A52,Hoja3!$A$3:$F$6000,5,FALSE),"") -> CX | I52: =IFERROR(VLOOKUP($A52,Hoja3!$A$3:$F$6000,3,FALSE),"") -> PEPSI-COLA VENEZUELA, C.A. | J52: =IFERROR(VLOOKUP($A52,Hoja3!$A$3:$F$6000,4,FALSE),"") -> ETIQUETA IMPRESA SEVEN UP CERO 2 L | K52: 780 | L52: 25 | M52: 40 | N52: =20+25 -> 45 | O52: 20 | P52: 45 | Q52: 0 | R52: 0 | S52: =15+15+15 -> 45 | T52: 10 | U52: 0 | V52: 0 | W52: 0 | X52: 0 | Y52: 0 | Z52: 0 | AA52: 0 | AB52: 0 | AC52: 0 | AD52: =SUM(L52:AC52) -> 230 | AE52: 174 | AF52: =SUM(AD52:AE52) -> 404 | AG52: =AF52/(60*24) -> 0.28055556 | AH52: =IFERROR(AE52/AF52,0) -> 0.43069307 | AI52: 35980 | AJ52: 21 | AK52: 1010 | AL52: =IF(AM52=0,0,(+AI52*AK52/1000)) -> 36339.8 | AM52: 792.7 | AN52: 6 | AO52: 0 | AP52: 0 | AQ52: 0 | AR52: 17 | AS52: 0 | AT52: 13 | AU52: =22+23+135+178 -> 358 | AV52: =SUM(AO52:AU52) -> 388 | AW52: =+(AM52+(BR52*50/100))+(BS52*30/100)-BB52 -> 836.8 | AX52: 0 | AY52: 0 | AZ52: 0 | BA52: 0 | BB52: 0 | BC52: 0 | BD52: 0 | BE52: 0 | BF52: 11 | BG52: 0 | BH52: 7 | BI52: =13+15+70+125 -> 223 | BJ52: =SUM(BC52:BI52) -> 241 | BK52: 33054 | BL52: =IFERROR(+BO52*1000/((BK52)*(BM52/1000)),0) -> 23.130467 | BM52: =AK52 -> 1010 | BN52: =+BK52*BM52/1000 -> 33384.54 | BO52: =786-13.8 -> 772.2 | BP52: 0 | BQ52: 0 | BR52: =AO52-BC52 -> 0 | BS52: =(AP52+AQ52+AR52+AS52+AT52+AU52)-(BD52+BE52+BF52+BG52+BH52+BI52) -> 147 | BT52: =BR52+BS52 -> 147 | BU52: =IFERROR(+BK52/AE52,0) -> 189.96552 | BV52: =IFERROR(+BK52/(AF52),0) -> 81.816832 | BW52: =IFERROR(+(AI52-AZ52)-BK52,0) -> 2926 | BX52: =IFERROR(+BW52/BK52,0) -> 0.088521813 | BY52: =IFERROR(+(AL52-BA52)-BN52,0) -> 2955.26 | BZ52: =IFERROR(+BY52/BN52,0) -> 0.088521813 | CA52: =IFERROR(+AW52-(BO52),0) -> 64.6 | CB52: =IFERROR(+CA52/BO52,1) -> 0.083657084 | CC52: 0 | CD52: 0 | CE52: bomba presenta falla de frecuencia y deja de mandar tinta, se baja plancha por problemas de registro, | CF52: =IFERROR((BT52*1000)/BN52,"") -> 4.4032357 | CG52: REPETICION | CH52: 4 | CI52: 3500 | CJ52: =IF(BW52=0,"",CI52-BW52) -> 574 | CK52: {=_xlfn.IFS(CJ52>0,"CUMPLE",CJ52<0,"NO CUMPLE",CJ52="","")} -> CUMPLE | CL52: 46111 | CM52: {=_xlfn.IFS(CL52-C52 > 0,"CUMPLE",CL52-C52 < 0,"NO CUMPLE")} -> NO CUMPLE | CN52: 33000 | CO52: =BK52-CN52 -> 54 | CP52: 900 | CQ52: TELEPLASTIC | CR52: BOPP POCT PERLADO
A53: 01-6036 | B53: NF | C53: 46134 | D53: =IFERROR(VLOOKUP($A53,Hoja3!$A$3:$F$6000,2,FALSE),"") -> TXPCSC023A002 | E53: 16574-1 | F53: =IFERROR(VLOOKUP($A53,Hoja3!$A$3:$F$6000,6,FALSE),"") -> CORTE | G53: 1 | H53: =IFERROR(VLOOKUP($A53,Hoja3!$A$3:$F$6000,5,FALSE),"") -> CX | I53: =IFERROR(VLOOKUP($A53,Hoja3!$A$3:$F$6000,3,FALSE),"") -> PEPSI-COLA VENEZUELA, C.A. | J53: =IFERROR(VLOOKUP($A53,Hoja3!$A$3:$F$6000,4,FALSE),"") -> ETIQUETA IMPRESA SEVEN UP CERO 2 L | K53: 710 | L53: 0 | M53: 0 | N53: 0 | O53: 0 | P53: 0 | Q53: 0 | R53: 0 | S53: =15+15 -> 30 | T53: 0 | U53: 0 | V53: 0 | W53: 0 | X53: 0 | Y53: 0 | Z53: 0 | AA53: 0 | AB53: 0 | AC53: 0 | AD53: =SUM(L53:AC53) -> 30 | AE53: 165 | AF53: =SUM(AD53:AE53) -> 195 | AG53: =AF53/(60*24) -> 0.13541667 | AH53: =IFERROR(AE53/AF53,0) -> 0.84615385 | AI53: 33150 | AJ53: 21 | AK53: 1010 | AL53: =IF(AM53=0,0,(+AI53*AK53/1000)) -> 33481.5 | AM53: 689 | AN53: 6 | AO53: 0 | AP53: 0 | AQ53: 0 | AR53: 11 | AS53: 0 | AT53: 7 | AU53: =13+15+70+125 -> 223 | AV53: =SUM(AO53:AU53) -> 241 | AW53: =+(AM53+(BR53*50/100))+(BS53*30/100)-BB53 -> 730.7 | AX53: 0 | AY53: 0 | AZ53: 0 | BA53: 0 | BB53: 0 | BC53: 0 | BD53: 0 | BE53: 0 | BF53: 6 | BG53: 0 | BH53: 1 | BI53: =4+8+8+75 -> 95 | BJ53: =SUM(BC53:BI53) -> 102 | BK53: 29914 | BL53: =IFERROR(+BO53*1000/((BK53)*(BM53/1000)),0) -> 22.311484 | BM53: =AK53 -> 1010 | BN53: =+BK53*BM53/1000 -> 30213.14 | BO53: =714-39.9 -> 674.1 | BP53: 0 | BQ53: 0 | BR53: =AO53-BC53 -> 0 | BS53: =(AP53+AQ53+AR53+AS53+AT53+AU53)-(BD53+BE53+BF53+BG53+BH53+BI53) -> 139 | BT53: =BR53+BS53 -> 139 | BU53: =IFERROR(+BK53/AE53,0) -> 181.29697 | BV53: =IFERROR(+BK53/(AF53),0) -> 153.40513 | BW53: =IFERROR(+(AI53-AZ53)-BK53,0) -> 3236 | BX53: =IFERROR(+BW53/BK53,0) -> 0.10817677 | BY53: =IFERROR(+(AL53-BA53)-BN53,0) -> 3268.36 | BZ53: =IFERROR(+BY53/BN53,0) -> 0.10817677 | CA53: =IFERROR(+AW53-(BO53),0) -> 56.6 | CB53: =IFERROR(+CA53/BO53,1) -> 0.083963804 | CC53: 0 | CD53: 0 | CE53: se culmina produccion sin novedad | CF53: =IFERROR((BT53*1000)/BN53,"") -> 4.6006473 | CG53: REPETICION | CH53: 4 | CI53: 3500 | CJ53: =IF(BW53=0,"",CI53-BW53) -> 264 | CK53: {=_xlfn.IFS(CJ53>0,"CUMPLE",CJ53<0,"NO CUMPLE",CJ53="","")} -> CUMPLE | CL53: 46111 | CM53: {=_xlfn.IFS(CL53-C53 > 0,"CUMPLE",CL53-C53 < 0,"NO CUMPLE")} -> NO CUMPLE | CN53: 32000 | CO53: =BK53-CN53 -> -2086 | CP53: 0 | CQ53: TELEPLASTIC | CR53: BOPP POCT PERLADO
A54: 21-0570 | B54: NF | C54: 46135 | D54: =IFERROR(VLOOKUP($A54,Hoja3!$A$3:$F$6000,2,FALSE),"") -> TXSPBC050A003 | E54: 16594 | F54: =IFERROR(VLOOKUP($A54,Hoja3!$A$3:$F$6000,6,FALSE),"") -> LAMINACION | G54: 1 | H54: =IFERROR(VLOOKUP($A54,Hoja3!$A$3:$F$6000,5,FALSE),"") -> CX | I54: =IFERROR(VLOOKUP($A54,Hoja3!$A$3:$F$6000,3,FALSE),"") -> C.A. SUCESORA DE JOSE PUIG & CIA | J54: =IFERROR(VLOOKUP($A54,Hoja3!$A$3:$F$6000,4,FALSE),"") -> LAMINACION IMPRESA BROWNIES CHOCOLATE 175g | K54: 1900 | L54: =20+30+50 -> 100 | M54: =60+30 -> 90 | N54: =30+50+40 -> 120 | O54: 20 | P54: =90+20+40+20+50 -> 220 | Q54: 0 | R54: 0 | S54: =15+15+30+15+30 -> 105 | T54: =20+15 -> 35 | U54: 0 | V54: =15+20+60 -> 95 | W54: 0 | X54: 0 | Y54: 0 | Z54: =360+120 -> 480 | AA54: 60 | AB54: 0 | AC54: 0 | AD54: =SUM(L54:AC54) -> 1325 | AE54: 240 | AF54: =SUM(AD54:AE54) -> 1565 | AG54: =AF54/(60*24) -> 1.0868056 | AH54: =IFERROR(AE54/AF54,0) -> 0.15335463 | AI54: 49078 | AJ54: 27 | AK54: 1000 | AL54: =IF(AM54=0,0,(+AI54*AK54/1000)) -> 49078 | AM54: 1347.6 | AN54: 7 | AO54: 294 | AP54: 0 | AQ54: 26 | AR54: 14 | AS54: 0 | AT54: 17 | AU54: =19+53+40 -> 112 | AV54: =SUM(AO54:AU54) -> 463 | AW54: =+(AM54+(BR54*50/100))+(BS54*30/100)-BB54 -> 1453.2 | AX54: 0 | AY54: 0 | AZ54: 0 | BA54: 0 | BB54: 0 | BC54: 144 | BD54: 0 | BE54: 11 | BF54: 10 | BG54: 0 | BH54: 15 | BI54: =16+7+8 -> 31 | BJ54: =SUM(BC54:BI54) -> 211 | BK54: 39950 | BL54: =IFERROR(+BO54*1000/((BK54)*(BM54/1000)),0) -> 29.499374 | BM54: =AK54 -> 1000 | BN54: =+BK54*BM54/1000 -> 39950 | BO54: 1178.5 | BP54: 0 | BQ54: 0 | BR54: =AO54-BC54 -> 150 | BS54: =(AP54+AQ54+AR54+AS54+AT54+AU54)-(BD54+BE54+BF54+BG54+BH54+BI54) -> 102 | BT54: =BR54+BS54 -> 252 | BU54: =IFERROR(+BK54/AE54,0) -> 166.45833 | BV54: =IFERROR(+BK54/(AF54),0) -> 25.527157 | BW54: =IFERROR(+(AI54-AZ54)-BK54,0) -> 9128 | BX54: =IFERROR(+BW54/BK54,0) -> 0.22848561 | BY54: =IFERROR(+(AL54-BA54)-BN54,0) -> 9128 | BZ54: =IFERROR(+BY54/BN54,0) -> 0.22848561 | CA54: =IFERROR(+AW54-(BO54),0) -> 274.7 | CB54: =IFERROR(+CA54/BO54,1) -> 0.23309291 | CC54: 0 | CD54: 0 | CE54: Aprobacion, estandar de colores arroja 22 kg de desp, problemas con registros marron beige blanco y negro, se realiza parada en bob 4 por variacion de tono marron y beige, falla de flujo color marron, rayas en impresión color magenta, | CF54: =IFERROR((BT54*1000)/BN54,"") -> 6.3078849 | CG54: APROBACION | CH54: 3 | CI54: 3500 | CJ54: =IF(BW54=0,"",CI54-BW54) -> -5628 | CK54: {=_xlfn.IFS(CJ54>0,"CUMPLE",CJ54<0,"NO CUMPLE",CJ54="","")} -> NO CUMPLE | CL54: 46125 | CM54: {=_xlfn.IFS(CL54-C54 > 0,"CUMPLE",CL54-C54 < 0,"NO CUMPLE")} -> NO CUMPLE | CN54: 39500 | CO54: =BK54-CN54 -> 450 | CP54: 0 | CQ54: OPPFILM | CR54: BOPP SC TRANSPARENTE
A55: 01-6035 | B55: NF | C55: 46136 | D55: =IFERROR(VLOOKUP($A55,Hoja3!$A$3:$F$6000,2,FALSE),"") -> TXPCPF023C003 | E55: 16573 | F55: =IFERROR(VLOOKUP($A55,Hoja3!$A$3:$F$6000,6,FALSE),"") -> CORTE | G55: 1 | H55: =IFERROR(VLOOKUP($A55,Hoja3!$A$3:$F$6000,5,FALSE),"") -> CX | I55: =IFERROR(VLOOKUP($A55,Hoja3!$A$3:$F$6000,3,FALSE),"") -> PEPSI-COLA VENEZUELA, C.A. | J55: =IFERROR(VLOOKUP($A55,Hoja3!$A$3:$F$6000,4,FALSE),"") -> ETIQUETA IMPRESA PEPSI FREE 2 L | K55: 1600 | L55: =30+50+55 -> 135 | M55: =60+95+20 -> 175 | N55: =95+65+20+30+30+45+20 -> 305 | O55: 15 | P55: 100 | Q55: 0 | R55: 0 | S55: =10+10+10 -> 30 | T55: 0 | U55: 0 | V55: =15+10+15+25+15 -> 80 | W55: 0 | X55: =30 -> 30 | Y55: 0 | Z55: 0 | AA55: 0 | AB55: 0 | AC55: 0 | AD55: =SUM(L55:AC55) -> 870 | AE55: 365.4 | AF55: =SUM(AD55:AE55) -> 1235.4 | AG55: =AF55/(60*24) -> 0.85791667 | AH55: =IFERROR(AE55/AF55,0) -> 0.29577465 | AI55: 75350 | AJ55: 21 | AK55: 1010 | AL55: =IF(AM55=0,0,(+AI55*AK55/1000)) -> 76103.5 | AM55: 1684 | AN55: 6 | AO55: 0 | AP55: =143+25+241 -> 409 | AQ55: 0 | AR55: 0 | AS55: 0 | AT55: 24 | AU55: =16+170 -> 186 | AV55: =SUM(AO55:AU55) -> 619 | AW55: =+(AM55+(BR55*50/100))+(BS55*30/100)-BB55 -> 1758.4 | AX55: 0 | AY55: 0 | AZ55: 0 | BA55: 0 | BB55: 0 | BC55: 0 | BD55: =96+18+126 -> 240 | BE55: 0 | BF55: 0 | BG55: 0 | BH55: 18 | BI55: =11+102 -> 113 | BJ55: =SUM(BC55:BI55) -> 371 | BK55: 67772 | BL55: =IFERROR(+BO55*1000/((BK55)*(BM55/1000)),0) -> 22.780225 | BM55: =AK55 -> 1010 | BN55: =+BK55*BM55/1000 -> 68449.72 | BO55: =1623-63.7 -> 1559.3 | BP55: 0 | BQ55: 0 | BR55: =AO55-BC55 -> 0 | BS55: =(AP55+AQ55+AR55+AS55+AT55+AU55)-(BD55+BE55+BF55+BG55+BH55+BI55) -> 248 | BT55: =BR55+BS55 -> 248 | BU55: =IFERROR(+BK55/AE55,0) -> 185.47345 | BV55: =IFERROR(+BK55/(AF55),0) -> 54.858345 | BW55: =IFERROR(+(AI55-AZ55)-BK55,0) -> 7578 | BX55: =IFERROR(+BW55/BK55,0) -> 0.11181609 | BY55: =IFERROR(+(AL55-BA55)-BN55,0) -> 7653.78 | BZ55: =IFERROR(+BY55/BN55,0) -> 0.11181609 | CA55: =IFERROR(+AW55-(BO55),0) -> 199.1 | CB55: =IFERROR(+CA55/BO55,1) -> 0.1276855 | CC55: 0 | CD55: 0 | CE55: se baja plancha para ser grabada de nuevo por porosidad del azul logo, se utiliza tinmta pvk ya que la cromia genera repinte en fondo color azul | CF55: =IFERROR((BT55*1000)/BN55,"") -> 3.6230974 | CG55: REPETICION | CH55: 4 | CI55: 3500 | CJ55: =IF(BW55=0,"",CI55-BW55) -> -4078 | CK55: {=_xlfn.IFS(CJ55>0,"CUMPLE",CJ55<0,"NO CUMPLE",CJ55="","")} -> NO CUMPLE | CL55: 46111 | CM55: {=_xlfn.IFS(CL55-C55 > 0,"CUMPLE",CL55-C55 < 0,"NO CUMPLE")} -> NO CUMPLE | CN55: 70500 | CO55: =BK55-CN55 -> -2728 | CP55: 1000 | CQ55: TELEPLASTIC | CR55: BOPP POCT PERLADO
A56: 01-6044 | B56: NF | C56: 46136 | D56: =IFERROR(VLOOKUP($A56,Hoja3!$A$3:$F$6000,2,FALSE),"") -> TXPCPF023C003 | E56: 16582 | F56: =IFERROR(VLOOKUP($A56,Hoja3!$A$3:$F$6000,6,FALSE),"") -> CORTE | G56: 1 | H56: =IFERROR(VLOOKUP($A56,Hoja3!$A$3:$F$6000,5,FALSE),"") -> CX | I56: =IFERROR(VLOOKUP($A56,Hoja3!$A$3:$F$6000,3,FALSE),"") -> PEPSI-COLA VENEZUELA, C.A. | J56: =IFERROR(VLOOKUP($A56,Hoja3!$A$3:$F$6000,4,FALSE),"") -> ETIQUETA IMPRESA PEPSI FREE 2 L | K56: 0 | L56: 0 | M56: 0 | N56: 0 | O56: 0 | P56: 0 | Q56: 0 | R56: 0 | S56: 20 | T56: 0 | U56: 0 | V56: 0 | W56: 0 | X56: 0 | Y56: 0 | Z56: 0 | AA56: 0 | AB56: 0 | AC56: 0 | AD56: =SUM(L56:AC56) -> 20 | AE56: 75 | AF56: =SUM(AD56:AE56) -> 95 | AG56: =AF56/(60*24) -> 0.065972222 | AH56: =IFERROR(AE56/AF56,0) -> 0.78947368 | AI56: 14020 | AJ56: 21 | AK56: 1010 | AL56: =IF(AM56=0,0,(+AI56*AK56/1000)) -> 14160.2 | AM56: 303.6 | AN56: 6 | AP56: =96+18+126 -> 240 | AQ56: 0 | AR56: 0 | AS56: 0 | AT56: 18 | AU56: =11+102 -> 113 | AV56: =SUM(AO56:AU56) -> 371 | AW56: =+(AM56+(BR56*50/100))+(BS56*30/100)-BB56 -> 319.2 | AX56: 0 | AY56: 0 | AZ56: 0 | BA56: 0 | BB56: 0 | BC56: 0 | BD56: =86+16+103 -> 205 | BE56: 0 | BF56: 0 | BG56: 0 | BH56: 16 | BI56: =10+88 -> 98 | BJ56: =SUM(BC56:BI56) -> 319 | BK56: 13558 | BL56: =IFERROR(+BO56*1000/((BK56)*(BM56/1000)),0) -> 22.981572 | BM56: =AK56 -> 1010 | BN56: =+BK56*BM56/1000 -> 13693.58 | BO56: =325-10.3 -> 314.7 | BP56: 0 | BQ56: 0 | BR56: =AO56-BC56 -> 0 | BS56: =(AP56+AQ56+AR56+AS56+AT56+AU56)-(BD56+BE56+BF56+BG56+BH56+BI56) -> 52 | BT56: =BR56+BS56 -> 52 | BU56: =IFERROR(+BK56/AE56,0) -> 180.77333 | BV56: =IFERROR(+BK56/(AF56),0) -> 142.71579 | BW56: =IFERROR(+(AI56-AZ56)-BK56,0) -> 462 | BX56: =IFERROR(+BW56/BK56,0) -> 0.034075822 | BY56: =IFERROR(+(AL56-BA56)-BN56,0) -> 466.62 | BZ56: =IFERROR(+BY56/BN56,0) -> 0.034075822 | CA56: =IFERROR(+AW56-(BO56),0) -> 4.5 | CB56: =IFERROR(+CA56/BO56,1) -> 0.014299333 | CC56: 0 | CD56: 0 | CE56: se limpia plancha color negro por sucio en codigo de barra | CF56: =IFERROR((BT56*1000)/BN56,"") -> 3.7973999 | CG56: REPETICION | CH56: 0 | CI56: 3500 | CJ56: =IF(BW56=0,"",CI56-BW56) -> 3038 | CK56: {=_xlfn.IFS(CJ56>0,"CUMPLE",CJ56<0,"NO CUMPLE",CJ56="","")} -> CUMPLE | CL56: 46111 | CM56: {=_xlfn.IFS(CL56-C56 > 0,"CUMPLE",CL56-C56 < 0,"NO CUMPLE")} -> NO CUMPLE | CN56: 14000 | CO56: =BK56-CN56 -> -442 | CP56: 0 | CQ56: TELEPLASTIC | CR56: BOPP POCT PERLADO
A57: 000lm | B57: NF | C57: 46136 | D57: =IFERROR(VLOOKUP($A57,Hoja3!$A$3:$F$6000,2,FALSE),"") -> 000LM | E57: 000lm | F57: =IFERROR(VLOOKUP($A57,Hoja3!$A$3:$F$6000,6,FALSE),"") -> LIMPIEZA | G57: 0 | H57: =IFERROR(VLOOKUP($A57,Hoja3!$A$3:$F$6000,5,FALSE),"") -> CX | I57: =IFERROR(VLOOKUP($A57,Hoja3!$A$3:$F$6000,3,FALSE),"") -> LIMPIEZA GENERAL DE MAQUINA | J57: =IFERROR(VLOOKUP($A57,Hoja3!$A$3:$F$6000,4,FALSE),"") -> LIMPIEZA GENERAL DE MAQUINA | K57: 0 | L57: 0 | M57: 0 | N57: 0 | O57: 0 | P57: 0 | Q57: 234.6 | R57: 0 | S57: 0 | T57: 0 | U57: 0 | V57: 0 | W57: 0 | X57: 0 | Y57: 0 | Z57: 0 | AA57: 0 | AB57: 0 | AC57: 0 | AD57: =SUM(L57:AC57) -> 234.6 | AE57: 0 | AF57: =SUM(AD57:AE57) -> 234.6 | AG57: =AF57/(60*24) -> 0.16291667 | AH57: =IFERROR(AE57/AF57,0) -> 0 | AI57: 0 | AJ57: 0 | AK57: 0 | AL57: =IF(AM57=0,0,(+AI57*AK57/1000)) -> 0 | AM57: 0 | AN57: 0 | AO57: 0 | AP57: 0 | AQ57: 0 | AR57: 0 | AS57: 0 | AT57: 0 | AU57: 0 | AV57: =SUM(AO57:AU57) -> 0 | AW57: 0 | AX57: 0 | AY57: 0 | AZ57: 0 | BA57: 0 | BB57: 0 | BC57: 0 | BD57: 0 | BE57: 0 | BF57: 0 | BG57: 0 | BH57: 0 | BI57: 0 | BJ57: =SUM(BC57:BI57) -> 0 | BK57: 0 | BL57: 0 | BM57: =AK57 -> 0 | BN57: =+BK57*BM57/1000 -> 0 | BO57: 0 | BP57: 0 | BQ57: 0 | BR57: 0 | BS57: 0 | BT57: 0 | BU57: =IFERROR(+BK57/AE57,0) -> 0 | BV57: =IFERROR(+BK57/(AF57),0) -> 0 | BW57: =IFERROR(+(AI57-AZ57)-BK57,0) -> 0 | BX57: =IFERROR(+BW57/BK57,0) -> 0 | BY57: =IFERROR(+(AL57-BA57)-BN57,0) -> 0 | BZ57: =IFERROR(+BY57/BN57,0) -> 0 | CA57: =IFERROR(+AW57-(BO57),0) -> 0 | CB57: =IFERROR(+CA57/BO57,1) -> 1 | CC57: 0 | CD57: 0 | CE57: limpieza general de maquina | CF57: =IFERROR((BT57*1000)/BN57,"") | CG57: LIMPIEZA | CH57: 0 | CI57: 0 | CJ57: =IF(BW57=0,"",CI57-BW57) | CK57: {=_xlfn.IFS(CJ57>0,"CUMPLE",CJ57<0,"NO CUMPLE",CJ57="","")} -> CUMPLE | CL57: 0 | CM57: {=_xlfn.IFS(CL57-C57 > 0,"CUMPLE",CL57-C57 < 0,"NO CUMPLE")} -> NO CUMPLE | CN57: 0 | CO57: =BK57-CN57 -> 0 | CP57: 0
A58: 01-6082 | B58: NF | C58: 46139 | D58: =IFERROR(VLOOKUP($A58,Hoja3!$A$3:$F$6000,2,FALSE),"") -> TXIJDC023B001 | E58: 16629 | F58: =IFERROR(VLOOKUP($A58,Hoja3!$A$3:$F$6000,6,FALSE),"") -> CORTE | G58: 1 | H58: =IFERROR(VLOOKUP($A58,Hoja3!$A$3:$F$6000,5,FALSE),"") -> CX | I58: =IFERROR(VLOOKUP($A58,Hoja3!$A$3:$F$6000,3,FALSE),"") -> INDUSTRIAS VENEZOLANA DE BEBIDAS JAU C.A | J58: =IFERROR(VLOOKUP($A58,Hoja3!$A$3:$F$6000,4,FALSE),"") -> ETIQUETA IMPRESA DRINK COLA 400 ml | K58: 340 | L58: =20+15 -> 35 | M58: 0 | N58: 95 | O58: 20 | P58: 0 | Q58: 0 | R58: 0 | S58: 0 | T58: 0 | U58: 0 | V58: 0 | W58: 0 | X58: 0 | Y58: 0 | Z58: 90 | AA58: 30 | AB58: 0 | AC58: 0 | AD58: =SUM(L58:AC58) -> 270 | AE58: 84.6 | AF58: =SUM(AD58:AE58) -> 354.6 | AG58: =AF58/(60*24) -> 0.24625 | AH58: =IFERROR(AE58/AF58,0) -> 0.23857868 | AI58: 19010 | AJ58: 22 | AK58: 930 | AL58: =IF(AM58=0,0,(+AI58*AK58/1000)) -> 17679.3 | AM58: 388.3 | AN58: 4 | AO58: 0 | AP58: 0 | AQ58: 0 | AR58: 0 | AS58: 0 | AT58: =35+36 -> 71 | AU58: =11+210 -> 221 | AV58: =SUM(AO58:AU58) -> 292 | AW58: =+(AM58+(BR58*50/100))+(BS58*30/100)-BB58 -> 415.9 | AX58: 0 | AY58: 0 | AZ58: 0 | BA58: 0 | BB58: 0 | BC58: 0 | BD58: 0 | BE58: 0 | BF58: 0 | BG58: 0 | BH58: =9+12 -> 21 | BI58: =7+172 -> 179 | BJ58: =SUM(BC58:BI58) -> 200 | BK58: 15442 | BL58: =IFERROR(+BO58*1000/((BK58)*(BM58/1000)),0) -> 23.250373 | BM58: =AK58 -> 930 | BN58: =+BK58*BM58/1000 -> 14361.06 | BO58: =346-12.1 -> 333.9 | BP58: 0 | BQ58: 0 | BR58: =AO58-BC58 -> 0 | BS58: =(AP58+AQ58+AR58+AS58+AT58+AU58)-(BD58+BE58+BF58+BG58+BH58+BI58) -> 92 | BT58: =BR58+BS58 -> 92 | BU58: =IFERROR(+BK58/AE58,0) -> 182.52955 | BV58: =IFERROR(+BK58/(AF58),0) -> 43.547659 | BW58: =IFERROR(+(AI58-AZ58)-BK58,0) -> 3568 | BX58: =IFERROR(+BW58/BK58,0) -> 0.23105815 | BY58: =IFERROR(+(AL58-BA58)-BN58,0) -> 3318.24 | BZ58: =IFERROR(+BY58/BN58,0) -> 0.23105815 | CA58: =IFERROR(+AW58-(BO58),0) -> 82 | CB58: =IFERROR(+CA58/BO58,1) -> 0.24558251 | CC58: 0 | CE58: Aprobacin interna, se realiza estandar de color | CF58: =IFERROR((BT58*1000)/BN58,"") -> 6.4062124 | CG58: APROBACION | CH58: 2 | CI58: 3500 | CJ58: =IF(BW58=0,"",CI58-BW58) -> -68 | CK58: {=_xlfn.IFS(CJ58>0,"CUMPLE",CJ58<0,"NO CUMPLE",CJ58="","")} -> NO CUMPLE | CL58: 46142 | CM58: {=_xlfn.IFS(CL58-C58 > 0,"CUMPLE",CL58-C58 < 0,"NO CUMPLE")} -> CUMPLE | CN58: 16000 | CO58: =BK58-CN58 -> -558 | CP58: 520 | CQ58: TELEPLASTIC | CR58: BOPP POCT PERLADO
A59: 01-6045 | B59: NF | C59: 46139 | D59: =IFERROR(VLOOKUP($A59,Hoja3!$A$3:$F$6000,2,FALSE),"") -> TXPCPF023B003 | E59: 16583 | F59: =IFERROR(VLOOKUP($A59,Hoja3!$A$3:$F$6000,6,FALSE),"") -> CORTE | G59: 1 | H59: =IFERROR(VLOOKUP($A59,Hoja3!$A$3:$F$6000,5,FALSE),"") -> CX | I59: =IFERROR(VLOOKUP($A59,Hoja3!$A$3:$F$6000,3,FALSE),"") -> PEPSI-COLA VENEZUELA, C.A. | J59: =IFERROR(VLOOKUP($A59,Hoja3!$A$3:$F$6000,4,FALSE),"") -> ETIQUETA IMPRESA PEPSI FREE 1,5 L | K59: 1320 | L59: =20+35+15 -> 70 | M59: 0 | N59: 25 | O59: 20 | P59: =85+65+45+120+85 -> 400 | Q59: 0 | R59: 0 | S59: =10+20+15+15+25+15 -> 100 | T59: 10 | U59: 0 | V59: =10+5 -> 15 | W59: 0 | X59: 0 | Y59: 0 | Z59: 0 | AA59: 0 | AB59: 0 | AC59: 0 | AD59: =SUM(L59:AC59) -> 640 | AE59: 300 | AF59: =SUM(AD59:AE59) -> 940 | AG59: =AF59/(60*24) -> 0.65277778 | AH59: =IFERROR(AE59/AF59,0) -> 0.31914894 | AI59: 66440 | AJ59: 21 | AK59: 1010 | AL59: =IF(AM59=0,0,(+AI59*AK59/1000)) -> 67104.4 | AM59: 1487.7 | AN59: 6 | AO59: 0 | AP59: =158+32+264 -> 454 | AQ59: 0 | AR59: 0 | AS59: 0 | AT59: 28 | AU59: =27+308 -> 335 | AV59: =SUM(AO59:AU59) -> 817 | AW59: =+(AM59+(BR59*50/100))+(BS59*30/100)-BB59 -> 1562.1 | AX59: 0 | AY59: 0 | AZ59: 0 | BA59: 0 | BB59: 0 | BC59: 0 | BD59: =120+24+186 -> 330 | BE59: 0 | BF59: 0 | BG59: 0 | BH59: 23 | BI59: =17+199 -> 216 | BJ59: =SUM(BC59:BI59) -> 569 | BK59: 53542 | BL59: =IFERROR(+BO59*1000/((BK59)*(BM59/1000)),0) -> 23.029945 | BM59: =AK59 -> 1010 | BN59: =+BK59*BM59/1000 -> 54077.42 | BO59: =1445-199.6 -> 1245.4 | BP59: 0 | BQ59: 0 | BR59: =AO59-BC59 -> 0 | BS59: =(AP59+AQ59+AR59+AS59+AT59+AU59)-(BD59+BE59+BF59+BG59+BH59+BI59) -> 248 | BT59: =BR59+BS59 -> 248 | BU59: =IFERROR(+BK59/AE59,0) -> 178.47333 | BV59: =IFERROR(+BK59/(AF59),0) -> 56.959574 | BW59: =IFERROR(+(AI59-AZ59)-BK59,0) -> 12898 | BX59: =IFERROR(+BW59/BK59,0) -> 0.240895 | BY59: =IFERROR(+(AL59-BA59)-BN59,0) -> 13026.98 | BZ59: =IFERROR(+BY59/BN59,0) -> 0.240895 | CA59: =IFERROR(+AW59-(BO59),0) -> 316.7 | CB59: =IFERROR(+CA59/BO59,1) -> 0.25429581 | CC59: 0 | CD59: 0 | CE59: falla de flujo azul fondo, paradas por limpieza azul y negro | CF59: =IFERROR((BT59*1000)/BN59,"") -> 4.5860176 | CG59: REPETICION | CH59: 4 | CI59: 3500 | CJ59: =IF(BW59=0,"",CI59-BW59) -> -9398 | CK59: {=_xlfn.IFS(CJ59>0,"CUMPLE",CJ59<0,"NO CUMPLE",CJ59="","")} -> NO CUMPLE | CL59: 46111 | CM59: {=_xlfn.IFS(CL59-C59 > 0,"CUMPLE",CL59-C59 < 0,"NO CUMPLE")} -> NO CUMPLE | CN59: 61500 | CO59: =BK59-CN59 -> -7958 | CP59: 1348 | CQ59: TELEPLASTIC | CR59: BOPP POCT PERLADO
A60: 01-6053 | B60: NF | C60: 46139 | D60: =IFERROR(VLOOKUP($A60,Hoja3!$A$3:$F$6000,2,FALSE),"") -> TXPCPF023B003 | E60: 16591 | F60: =IFERROR(VLOOKUP($A60,Hoja3!$A$3:$F$6000,6,FALSE),"") -> CORTE | G60: 1 | H60: =IFERROR(VLOOKUP($A60,Hoja3!$A$3:$F$6000,5,FALSE),"") -> CX | I60: =IFERROR(VLOOKUP($A60,Hoja3!$A$3:$F$6000,3,FALSE),"") -> PEPSI-COLA VENEZUELA, C.A. | J60: =IFERROR(VLOOKUP($A60,Hoja3!$A$3:$F$6000,4,FALSE),"") -> ETIQUETA IMPRESA PEPSI FREE 1,5 L | K60: 360 | L60: 0 | M60: 0 | N60: 0 | O60: 0 | P60: 0 | Q60: 0 | R60: 0 | S60: =20+20 -> 40 | T60: 0 | U60: 0 | V60: 0 | W60: 0 | X60: 0 | Y60: 0 | Z60: 0 | AA60: 0 | AB60: 0 | AC60: 0 | AD60: =SUM(L60:AC60) -> 40 | AE60: 90 | AF60: =SUM(AD60:AE60) -> 130 | AG60: =AF60/(60*24) -> 0.090277778 | AH60: =IFERROR(AE60/AF60,0) -> 0.69230769 | AI60: 17016 | AJ60: 21 | AK60: 1010 | AL60: =IF(AM60=0,0,(+AI60*AK60/1000)) -> 17186.16 | AM60: 359.8 | AN60: 6 | AO60: 0 | AP60: =120+24+186 -> 330 | AQ60: 0 | AR60: 0 | AS60: 0 | AT60: 23 | AU60: =17+199 -> 216 | AV60: =SUM(AO60:AU60) -> 569 | AW60: =+(AM60+(BR60*50/100))+(BS60*30/100)-BB60 -> 379.6 | AX60: 0 | AY60: 0 | AZ60: 0 | BA60: 0 | BB60: 0 | BC60: 0 | BD60: =110+22+165 -> 297 | BE60: 0 | BF60: 0 | BG60: 0 | BH60: 21 | BI60: =15+170 -> 185 | BJ60: =SUM(BC60:BI60) -> 503 | BK60: 16000 | BL60: =IFERROR(+BO60*1000/((BK60)*(BM60/1000)),0) -> 22.153465 | BM60: =AK60 -> 1010 | BN60: =+BK60*BM60/1000 -> 16160 | BO60: 358 | BP60: 0 | BQ60: 0 | BR60: =AO60-BC60 -> 0 | BS60: =(AP60+AQ60+AR60+AS60+AT60+AU60)-(BD60+BE60+BF60+BG60+BH60+BI60) -> 66 | BT60: =BR60+BS60 -> 66 | BU60: =IFERROR(+BK60/AE60,0) -> 177.77778 | BV60: =IFERROR(+BK60/(AF60),0) -> 123.07692 | BW60: =IFERROR(+(AI60-AZ60)-BK60,0) -> 1016 | BX60: =IFERROR(+BW60/BK60,0) -> 0.0635 | BY60: =IFERROR(+(AL60-BA60)-BN60,0) -> 1026.16 | BZ60: =IFERROR(+BY60/BN60,0) -> 0.0635 | CA60: =IFERROR(+AW60-(BO60),0) -> 21.6 | CB60: =IFERROR(+CA60/BO60,1) -> 0.060335196 | CC60: 0 | CD60: 0 | CE60: se culmina sin novedad | CF60: =IFERROR((BT60*1000)/BN60,"") -> 4.0841584 | CG60: REPETICION | CH60: 0 | CI60: 3500 | CJ60: =IF(BW60=0,"",CI60-BW60) -> 2484 | CK60: {=_xlfn.IFS(CJ60>0,"CUMPLE",CJ60<0,"NO CUMPLE",CJ60="","")} -> CUMPLE | CL60: 46111 | CM60: {=_xlfn.IFS(CL60-C60 > 0,"CUMPLE",CL60-C60 < 0,"NO CUMPLE")} -> NO CUMPLE | CN60: 16000 | CO60: =BK60-CN60 -> 0 | CP60: 0 | CQ60: TELEPLASTIC | CR60: BOPP POCT PERLADO
A61: 01-6037 | B61: NF | C61: 46140 | D61: =IFERROR(VLOOKUP($A61,Hoja3!$A$3:$F$6000,2,FALSE),"") -> TXPCEP023B003 | E61: 16575 | F61: =IFERROR(VLOOKUP($A61,Hoja3!$A$3:$F$6000,6,FALSE),"") -> CORTE | G61: 1 | H61: =IFERROR(VLOOKUP($A61,Hoja3!$A$3:$F$6000,5,FALSE),"") -> CX | I61: =IFERROR(VLOOKUP($A61,Hoja3!$A$3:$F$6000,3,FALSE),"") -> PEPSI-COLA VENEZUELA, C.A. | J61: =IFERROR(VLOOKUP($A61,Hoja3!$A$3:$F$6000,4,FALSE),"") -> ETIQUETA IMPRESA PEPSI FREE 1 L | K61: 3900 | L61: =15+20 -> 35 | M61: 0 | N61: =25+15 -> 40 | O61: 20 | P61: =25+20+10+20 -> 75 | Q61: 0 | R61: 0 | S61: =15+10+10+20+15+15+15+15 -> 115 | T61: 0 | U61: 0 | V61: 5 | W61: 0 | X61: =35+32+50 -> 117 | Y61: 0 | Z61: 0 | AA61: 0 | AB61: 0 | AC61: 0 | AD61: =SUM(L61:AC61) -> 407 | AE61: 918 | AF61: =SUM(AD61:AE61) -> 1325 | AG61: =AF61/(60*24) -> 0.92013889 | AH61: =IFERROR(AE61/AF61,0) -> 0.69283019 | AI61: 172650 | AJ61: 21 | AK61: 1010 | AL61: =IF(AM61=0,0,(+AI61*AK61/1000)) -> 174376.5 | AM61: 3845 | AN61: 6 | AO61: 0 | AP61: =308+22+377 -> 707 | AQ61: 0 | AR61: 0 | AS61: 0 | AT61: 21 | AU61: =28+255 -> 283 | AV61: =SUM(AO61:AU61) -> 1011 | AW61: =+(AM61+(BR61*50/100))+(BS61*30/100)-BB61 -> 4015.4 | AX61: 0 | AY61: 0 | AZ61: 0 | BA61: 0 | BB61: 0 | BC61: 0 | BD61: =173+14+130 -> 317 | BE61: 0 | BF61: 0 | BG61: 0 | BH61: 13 | BI61: =14+99 -> 113 | BJ61: =SUM(BC61:BI61) -> 443 | BK61: 167379 | BL61: =IFERROR(+BO61*1000/((BK61)*(BM61/1000)),0) -> 22.70001 | BM61: =AK61 -> 1010 | BN61: =+BK61*BM61/1000 -> 169052.79 | BO61: =3925.7-88.2 -> 3837.5 | BP61: 0 | BQ61: 0 | BR61: =AO61-BC61 -> 0 | BS61: =(AP61+AQ61+AR61+AS61+AT61+AU61)-(BD61+BE61+BF61+BG61+BH61+BI61) -> 568 | BT61: =BR61+BS61 -> 568 | BU61: =IFERROR(+BK61/AE61,0) -> 182.33007 | BV61: =IFERROR(+BK61/(AF61),0) -> 126.32377 | BW61: =IFERROR(+(AI61-AZ61)-BK61,0) -> 5271 | BX61: =IFERROR(+BW61/BK61,0) -> 0.031491406 | BY61: =IFERROR(+(AL61-BA61)-BN61,0) -> 5323.71 | BZ61: =IFERROR(+BY61/BN61,0) -> 0.031491406 | CA61: =IFERROR(+AW61-(BO61),0) -> 177.9 | CB61: =IFERROR(+CA61/BO61,1) -> 0.046358306 | CC61: 0 | CD61: 0 | CE61: se culmina sin novedad | CF61: =IFERROR((BT61*1000)/BN61,"") -> 3.3598972 | CG61: REPETICION | CH61: 4 | CI61: 3500 | CJ61: =IF(BW61=0,"",CI61-BW61) -> -1771 | CK61: {=_xlfn.IFS(CJ61>0,"CUMPLE",CJ61<0,"NO CUMPLE",CJ61="","")} -> NO CUMPLE | CL61: 46111 | CM61: {=_xlfn.IFS(CL61-C61 > 0,"CUMPLE",CL61-C61 < 0,"NO CUMPLE")} -> NO CUMPLE | CN61: 171000 | CO61: =BK61-CN61 -> -3621 | CP61: 895 | CQ61: OPPFILM | CR61: BOPP PC PERLADO
A62: 01-6048 | B62: NF | C62: 46141 | D62: =IFERROR(VLOOKUP($A62,Hoja3!$A$3:$F$6000,2,FALSE),"") -> TXPCEP023B003 | E62: 16586 | F62: =IFERROR(VLOOKUP($A62,Hoja3!$A$3:$F$6000,6,FALSE),"") -> CORTE | G62: 1 | H62: =IFERROR(VLOOKUP($A62,Hoja3!$A$3:$F$6000,5,FALSE),"") -> CX | I62: =IFERROR(VLOOKUP($A62,Hoja3!$A$3:$F$6000,3,FALSE),"") -> PEPSI-COLA VENEZUELA, C.A. | J62: =IFERROR(VLOOKUP($A62,Hoja3!$A$3:$F$6000,4,FALSE),"") -> ETIQUETA IMPRESA PEPSI FREE 1 L | K62: 1200 | L62: 0 | M62: 0 | N62: 0 | O62: 0 | P62: 0 | Q62: 0 | R62: 0 | S62: =25+10+15+10 -> 60 | T62: 0 | U62: 0 | V62: 0 | W62: 0 | X62: 0 | Y62: 0 | Z62: 0 | AA62: 0 | AB62: 0 | AC62: 0 | AD62: =SUM(L62:AC62) -> 60 | AE62: 315 | AF62: =SUM(AD62:AE62) -> 375 | AG62: =AF62/(60*24) -> 0.26041667 | AH62: =IFERROR(AE62/AF62,0) -> 0.84 | AI62: 54350 | AJ62: 21 | AK62: 1010 | AL62: =IF(AM62=0,0,(+AI62*AK62/1000)) -> 54893.5 | AM62: 1233 | AN62: 6 | AO62: 0 | AP62: =173+14+130 -> 317 | AQ62: 0 | AR62: 0 | AS62: 0 | AT62: 13 | AU62: =14+99 -> 113 | AV62: =SUM(AO62:AU62) -> 443 | AW62: =+(AM62+(BR62*50/100))+(BS62*30/100)-BB62 -> 1286.7 | AX62: 0 | AY62: 0 | AZ62: 0 | BA62: 0 | BB62: 0 | BC62: 0 | BD62: =130+12+52 -> 194 | BE62: 0 | BF62: 0 | BG62: 0 | BH62: 10 | BI62: =10+50 -> 60 | BJ62: =SUM(BC62:BI62) -> 264 | BK62: 52922 | BL62: =IFERROR(+BO62*1000/((BK62)*(BM62/1000)),0) -> 23.00041 | BM62: =AK62 -> 1010 | BN62: =+BK62*BM62/1000 -> 53451.22 | BO62: =1262.3-32.9 -> 1229.4 | BP62: 0 | BQ62: 0 | BR62: =AO62-BC62 -> 0 | BS62: =(AP62+AQ62+AR62+AS62+AT62+AU62)-(BD62+BE62+BF62+BG62+BH62+BI62) -> 179 | BT62: =BR62+BS62 -> 179 | BU62: =IFERROR(+BK62/AE62,0) -> 168.00635 | BV62: =IFERROR(+BK62/(AF62),0) -> 141.12533 | BW62: =IFERROR(+(AI62-AZ62)-BK62,0) -> 1428 | BX62: =IFERROR(+BW62/BK62,0) -> 0.026983107 | BY62: =IFERROR(+(AL62-BA62)-BN62,0) -> 1442.28 | BZ62: =IFERROR(+BY62/BN62,0) -> 0.026983107 | CA62: =IFERROR(+AW62-(BO62),0) -> 57.3 | CB62: =IFERROR(+CA62/BO62,1) -> 0.046608102 | CC62: 0 | CD62: 0 | CE62: paradas por limpieza color azul y negro | CF62: =IFERROR((BT62*1000)/BN62,"") -> 3.3488478 | CG62: REPETICION | CH62: 0 | CI62: 3500 | CJ62: =IF(BW62=0,"",CI62-BW62) -> 2072 | CK62: {=_xlfn.IFS(CJ62>0,"CUMPLE",CJ62<0,"NO CUMPLE",CJ62="","")} -> CUMPLE | CL62: 46111 | CM62: {=_xlfn.IFS(CL62-C62 > 0,"CUMPLE",CL62-C62 < 0,"NO CUMPLE")} -> NO CUMPLE | CN62: 54000 | CO62: =BK62-CN62 -> -1078 | CP62: 0 | CQ62: OPPFILM | CR62: BOPP PC PERLADO
A63: 01-5932 | B63: NF | C63: 46141 | D63: =IFERROR(VLOOKUP($A63,Hoja3!$A$3:$F$6000,2,FALSE),"") -> TMPRSC094A001 | E63: 16479-1 | F63: =IFERROR(VLOOKUP($A63,Hoja3!$A$3:$F$6000,6,FALSE),"") -> LAMINACION | G63: 1 | H63: =IFERROR(VLOOKUP($A63,Hoja3!$A$3:$F$6000,5,FALSE),"") -> MCL | I63: =IFERROR(VLOOKUP($A63,Hoja3!$A$3:$F$6000,3,FALSE),"") -> COMPAÑÍA ANONIMA PRODUCTOS RONAVA | J63: =IFERROR(VLOOKUP($A63,Hoja3!$A$3:$F$6000,4,FALSE),"") -> LAMINACION IMPRESA SACHET COLAYTE 69,57(120*160) | K63: 850 | L63: =25+30+20 -> 75 | M63: 0 | N63: 60 | O63: 20 | P63: 0 | Q63: 0 | R63: 0 | S63: 20 | T63: 0 | U63: 0 | V63: =25+20+230 -> 275 | W63: 0 | X63: =30+30 -> 60 | Y63: 0 | Z63: 0 | AA63: 0 | AB63: 0 | AC63: 0 | AD63: =SUM(L63:AC63) -> 510 | AE63: 64.8 | AF63: =SUM(AD63:AE63) -> 574.8 | AG63: =AF63/(60*24) -> 0.39916667 | AH63: =IFERROR(AE63/AF63,0) -> 0.11273486 | AI63: 11600 | AJ63: 22 | AK63: 780 | AL63: =IF(AM63=0,0,(+AI63*AK63/1000)) -> 9048 | AM63: 207 | AN63: 4 | AO63: 144 | AP63: 0 | AQ63: 0 | AR63: 18 | AS63: 17 | AT63: 0 | AU63: 15 | AV63: =SUM(AO63:AU63) -> 194 | AW63: =+(AM63+(BR63*50/100))+(BS63*30/100)-BB63 -> 233.5 | AX63: 0 | AY63: 0 | AZ63: 0 | BA63: 0 | BB63: 0 | BC63: 100 | BD63: 0 | BE63: 0 | BF63: 11 | BG63: 12 | BH63: 0 | BI63: 12 | BJ63: =SUM(BC63:BI63) -> 135 | BK63: 11500 | BL63: =IFERROR(+BO63*1000/((BK63)*(BM63/1000)),0) -> 24.080268 | BM63: =AK63 -> 780 | BN63: =+BK63*BM63/1000 -> 8970 | BO63: 216 | BP63: 0 | BQ63: 0 | BR63: =AO63-BC63 -> 44 | BS63: =(AP63+AQ63+AR63+AS63+AT63+AU63)-(BD63+BE63+BF63+BG63+BH63+BI63) -> 15 | BT63: =BR63+BS63 -> 59 | BU63: =IFERROR(+BK63/AE63,0) -> 177.46914 | BV63: =IFERROR(+BK63/(AF63),0) -> 20.006959 | BW63: =IFERROR(+(AI63-AZ63)-BK63,0) -> 100 | BX63: =IFERROR(+BW63/BK63,0) -> 0.0086956522 | BY63: =IFERROR(+(AL63-BA63)-BN63,0) -> 78 | BZ63: =IFERROR(+BY63/BN63,0) -> 0.0086956522 | CA63: =IFERROR(+AW63-(BO63),0) -> 17.5 | CB63: =IFERROR(+CA63/BO63,1) -> 0.081018519 | CC63: 0 | CD63: 0 | CE63: se realizan varios ajustes en el cyan y amarillo, | CF63: =IFERROR((BT63*1000)/BN63,"") -> 6.5774805 | CG63: REPETICION | CH63: 0 | CI63: 3500 | CJ63: =IF(BW63=0,"",CI63-BW63) -> 3400 | CK63: {=_xlfn.IFS(CJ63>0,"CUMPLE",CJ63<0,"NO CUMPLE",CJ63="","")} -> CUMPLE | CL63: 46104 | CM63: {=_xlfn.IFS(CL63-C63 > 0,"CUMPLE",CL63-C63 < 0,"NO CUMPLE")} -> NO CUMPLE | CN63: 11500 | CO63: =BK63-CN63 -> 0 | CP63: 0 | CQ63: TELEPLASTIC | CR63: BOPP OCTS TRANSPARENTE
A64: 01-5933 | B64: NF | C64: 46141 | D64: =IFERROR(VLOOKUP($A64,Hoja3!$A$3:$F$6000,2,FALSE),"") -> TMPRSM094A001 | E64: 16480-1 | F64: =IFERROR(VLOOKUP($A64,Hoja3!$A$3:$F$6000,6,FALSE),"") -> LAMINACION | G64: 1 | H64: =IFERROR(VLOOKUP($A64,Hoja3!$A$3:$F$6000,5,FALSE),"") -> MCL | I64: =IFERROR(VLOOKUP($A64,Hoja3!$A$3:$F$6000,3,FALSE),"") -> COMPAÑÍA ANONIMA PRODUCTOS RONAVA | J64: =IFERROR(VLOOKUP($A64,Hoja3!$A$3:$F$6000,4,FALSE),"") -> LAMINACION IMPRESA SACHET MILAX 8,5g (120*100) | K64: 800 | L64: =25+15 -> 40 | M64: 0 | N64: 10 | O64: 15 | P64: 0 | Q64: 0 | R64: 0 | S64: =20+10+15 -> 45 | T64: 0 | U64: 0 | V64: =5+15 -> 20 | W64: 0 | X64: =30+20 -> 50 | Y64: 0 | Z64: 0 | AA64: 0 | AB64: 0 | AC64: 0 | AD64: =SUM(L64:AC64) -> 180 | AE64: 45 | AF64: =SUM(AD64:AE64) -> 225 | AG64: =AF64/(60*24) -> 0.15625 | AH64: =IFERROR(AE64/AF64,0) -> 0.2 | AI64: 13200 | AJ64: 22 | AK64: 780 | AL64: =IF(AM64=0,0,(+AI64*AK64/1000)) -> 10296 | AM64: 244.5 | AN64: 4 | AO64: 100 | AP64: 0 | AQ64: 0 | AR64: 11 | AS64: 12 | AT64: 0 | AU64: 12 | AV64: =SUM(AO64:AU64) -> 135 | AW64: =+(AM64+(BR64*50/100))+(BS64*30/100)-BB64 -> 261.9 | AX64: 0 | AY64: 0 | AZ64: 0 | BA64: 0 | BB64: 0 | BC64: 70 | BD64: 0 | BE64: 0 | BF64: 8 | BG64: 8 | BH64: 0 | BI64: 11 | BJ64: =SUM(BC64:BI64) -> 97 | BK64: 11121 | BL64: =IFERROR(+BO64*1000/((BK64)*(BM64/1000)),0) -> 23.517531 | BM64: =AK64 -> 780 | BN64: =+BK64*BM64/1000 -> 8674.38 | BO64: 204 | BP64: 0 | BQ64: 0 | BR64: =AO64-BC64 -> 30 | BS64: =(AP64+AQ64+AR64+AS64+AT64+AU64)-(BD64+BE64+BF64+BG64+BH64+BI64) -> 8 | BT64: =BR64+BS64 -> 38 | BU64: =IFERROR(+BK64/AE64,0) -> 247.13333 | BV64: =IFERROR(+BK64/(AF64),0) -> 49.426667 | BW64: =IFERROR(+(AI64-AZ64)-BK64,0) -> 2079 | BX64: =IFERROR(+BW64/BK64,0) -> 0.18694362 | BY64: =IFERROR(+(AL64-BA64)-BN64,0) -> 1621.62 | BZ64: =IFERROR(+BY64/BN64,0) -> 0.18694362 | CA64: =IFERROR(+AW64-(BO64),0) -> 57.9 | CB64: =IFERROR(+CA64/BO64,1) -> 0.28382353 | CC64: 0 | CD64: 0 | CE64: se culmina sin novedad | CF64: =IFERROR((BT64*1000)/BN64,"") -> 4.3807165 | CG64: REPETICION | CH64: 0 | CI64: 3500 | CJ64: =IF(BW64=0,"",CI64-BW64) -> 1421 | CK64: {=_xlfn.IFS(CJ64>0,"CUMPLE",CJ64<0,"NO CUMPLE",CJ64="","")} -> CUMPLE | CL64: 46104 | CM64: {=_xlfn.IFS(CL64-C64 > 0,"CUMPLE",CL64-C64 < 0,"NO CUMPLE")} -> NO CUMPLE | CN64: 12000 | CO64: =BK64-CN64 -> -879 | CP64: 850 | CQ64: TELEPLASTIC | CR64: BOPP OCTS TRANSPARENTE
A65: 11-0128 | B65: NF | C65: 46141 | D65: =IFERROR(VLOOKUP($A65,Hoja3!$A$3:$F$6000,2,FALSE),"") -> TXECAC028A001 | E65: 16632 | F65: =IFERROR(VLOOKUP($A65,Hoja3!$A$3:$F$6000,6,FALSE),"") -> CORTE | G65: 1 | H65: =IFERROR(VLOOKUP($A65,Hoja3!$A$3:$F$6000,5,FALSE),"") -> CX | I65: =IFERROR(VLOOKUP($A65,Hoja3!$A$3:$F$6000,3,FALSE),"") -> EMBOTELLADORA CRISTAL;C.A. | J65: =IFERROR(VLOOKUP($A65,Hoja3!$A$3:$F$6000,4,FALSE),"") -> ETIQUETA IMPRESA AGUA MINERAL CRYSTAL 330 cm³ | K65: 560 | L65: =20+30+15 -> 65 | M65: 0 | N65: =20+15 -> 35 | O65: 20 | P65: 0 | Q65: 0 | R65: 0 | S65: =10+10 -> 20 | T65: 20 | U65: 0 | V65: =15+10+5+5+5 -> 40 | W65: 0 | X65: =10 -> 10 | Y65: 0 | Z65: 0 | AA65: 0 | AB65: 0 | AC65: 0 | AD65: =SUM(L65:AC65) -> 210 | AE65: 120 | AF65: =SUM(AD65:AE65) -> 330 | AG65: =AF65/(60*24) -> 0.22916667 | AH65: =IFERROR(AE65/AF65,0) -> 0.36363636 | AI65: 23000 | AJ65: 27 | AK65: 980 | AL65: =IF(AM65=0,0,(+AI65*AK65/1000)) -> 22540 | AM65: 603 | AN65: 4 | AO65: 63 | AP65: 50 | AQ65: 0 | AR65: 0 | AS65: 17 | AT65: 0 | AU65: 12 | AV65: =SUM(AO65:AU65) -> 142 | AW65: =+(AM65+(BR65*50/100))+(BS65*30/100)-BB65 -> 630.3 | AX65: 0 | AY65: 0 | AZ65: 0 | BA65: 0 | BB65: 0 | BC65: 30 | BD65: 28 | BE65: 0 | BF65: 0 | BG65: 8 | BH65: 0 | BI65: 7 | BJ65: =SUM(BC65:BI65) -> 73 | BK65: 20528 | BL65: =IFERROR(+BO65*1000/((BK65)*(BM65/1000)),0) -> 28.035376 | BM65: =AK65 -> 980 | BN65: =+BK65*BM65/1000 -> 20117.44 | BO65: 564 | BP65: 0 | BQ65: 0 | BR65: =AO65-BC65 -> 33 | BS65: =(AP65+AQ65+AR65+AS65+AT65+AU65)-(BD65+BE65+BF65+BG65+BH65+BI65) -> 36 | BT65: =BR65+BS65 -> 69 | BU65: =IFERROR(+BK65/AE65,0) -> 171.06667 | BV65: =IFERROR(+BK65/(AF65),0) -> 62.206061 | BW65: =IFERROR(+(AI65-AZ65)-BK65,0) -> 2472 | BX65: =IFERROR(+BW65/BK65,0) -> 0.12042089 | BY65: =IFERROR(+(AL65-BA65)-BN65,0) -> 2422.56 | BZ65: =IFERROR(+BY65/BN65,0) -> 0.12042089 | CA65: =IFERROR(+AW65-(BO65),0) -> 66.3 | CB65: =IFERROR(+CA65/BO65,1) -> 0.11755319 | CC65: 0 | CD65: 0 | CE65: problemas de registro color blanco se cam bia adaptador, se cambia anilox del azul por rayas | CF65: =IFERROR((BT65*1000)/BN65,"") -> 3.4298599 | CG65: REPETICION | CH65: 1 | CI65: 3500 | CJ65: =IF(BW65=0,"",CI65-BW65) -> 1028 | CK65: {=_xlfn.IFS(CJ65>0,"CUMPLE",CJ65<0,"NO CUMPLE",CJ65="","")} -> CUMPLE | CL65: 46156 | CM65: {=_xlfn.IFS(CL65-C65 > 0,"CUMPLE",CL65-C65 < 0,"NO CUMPLE")} -> CUMPLE | CN65: 20500 | CO65: =BK65-CN65 -> 28 | CP65: 1300 | CQ65: TECHNOFILM | CR65: BOPP CT ST TRANSPARENTE
A66: 11-0127 | B66: NF | C66: 46142 | D66: =IFERROR(VLOOKUP($A66,Hoja3!$A$3:$F$6000,2,FALSE),"") -> TXECEC028D001 | E66: 16631 | F66: =IFERROR(VLOOKUP($A66,Hoja3!$A$3:$F$6000,6,FALSE),"") -> CORTE | G66: 1 | H66: =IFERROR(VLOOKUP($A66,Hoja3!$A$3:$F$6000,5,FALSE),"") -> CX | I66: =IFERROR(VLOOKUP($A66,Hoja3!$A$3:$F$6000,3,FALSE),"") -> EMBOTELLADORA CRISTAL;C.A. | J66: =IFERROR(VLOOKUP($A66,Hoja3!$A$3:$F$6000,4,FALSE),"") -> ETIQUETA IMPRESA AGUA CRYSTAL 600 cm³ | K66: 350 | L66: =15+15 -> 30 | M66: 0 | N66: 195 | O66: 15 | P66: 0 | Q66: 0 | R66: 0 | S66: 0 | T66: 0 | U66: 0 | V66: 10 | W66: 0 | X66: 0 | Y66: 0 | Z66: 0 | AA66: 0 | AB66: 0 | AC66: 0 | AD66: =SUM(L66:AC66) -> 250 | AE66: 109.8 | AF66: =SUM(AD66:AE66) -> 359.8 | AG66: =AF66/(60*24) -> 0.24986111 | AH66: =IFERROR(AE66/AF66,0) -> 0.30516954 | AI66: 10944 | AJ66: 27 | AK66: 1150 | AL66: =IF(AM66=0,0,(+AI66*AK66/1000)) -> 12585.6 | AM66: 350 | AN66: 4 | AO66: 110 | AP66: 28 | AQ66: 0 | AR66: 0 | AS66: 11 | AT66: 0 | AU66: 17 | AV66: =SUM(AO66:AU66) -> 166 | AW66: =+(AM66+(BR66*50/100))+(BS66*30/100)-BB66 -> 364.3 | AX66: 0 | AY66: 0 | AZ66: 0 | BA66: 0 | BB66: 0 | BC66: 94 | BD66: 13 | BE66: 0 | BF66: 0 | BG66: 7 | BH66: 0 | BI66: 15 | BJ66: =SUM(BC66:BI66) -> 129 | BK66: 10500 | BL66: =IFERROR(+BO66*1000/((BK66)*(BM66/1000)),0) -> 29.184265 | BM66: =AK66 -> 1150 | BN66: =+BK66*BM66/1000 -> 12075 | BO66: 352.4 | BP66: 0 | BQ66: 0 | BR66: =AO66-BC66 -> 16 | BS66: =(AP66+AQ66+AR66+AS66+AT66+AU66)-(BD66+BE66+BF66+BG66+BH66+BI66) -> 21 | BT66: =BR66+BS66 -> 37 | BU66: =IFERROR(+BK66/AE66,0) -> 95.628415 | BV66: =IFERROR(+BK66/(AF66),0) -> 29.182879 | BW66: =IFERROR(+(AI66-AZ66)-BK66,0) -> 444 | BX66: =IFERROR(+BW66/BK66,0) -> 0.042285714 | BY66: =IFERROR(+(AL66-BA66)-BN66,0) -> 510.6 | BZ66: =IFERROR(+BY66/BN66,0) -> 0.042285714 | CA66: =IFERROR(+AW66-(BO66),0) -> 11.9 | CB66: =IFERROR(+CA66/BO66,1) -> 0.033768445 | CC66: 0 | CD66: 0 | CE66: se arranca trabajo con notificacion de falla por problemas de copiado color azul cod de barra, | CF66: =IFERROR((BT66*1000)/BN66,"") -> 3.0641822 | CG66: REPETICION | CH66: 1 | CI66: 3500 | CJ66: =IF(BW66=0,"",CI66-BW66) -> 3056 | CK66: {=_xlfn.IFS(CJ66>0,"CUMPLE",CJ66<0,"NO CUMPLE",CJ66="","")} -> CUMPLE | CL66: 46156 | CM66: {=_xlfn.IFS(CL66-C66 > 0,"CUMPLE",CL66-C66 < 0,"NO CUMPLE")} -> CUMPLE | CN66: 10500 | CO66: =BK66-CN66 -> 0 | CP66: 2000 | CQ66: OPPFILM | CR66: BOPP SC TRANSPARENTE
A67: 11-0126 | B67: NF | C67: 46142 | D67: =IFERROR(VLOOKUP($A67,Hoja3!$A$3:$F$6000,2,FALSE),"") -> TXECEC028D001 | E67: 16630 | F67: =IFERROR(VLOOKUP($A67,Hoja3!$A$3:$F$6000,6,FALSE),"") -> CORTE | G67: 1 | H67: =IFERROR(VLOOKUP($A67,Hoja3!$A$3:$F$6000,5,FALSE),"") -> CX | I67: =IFERROR(VLOOKUP($A67,Hoja3!$A$3:$F$6000,3,FALSE),"") -> EMBOTELLADORA CRISTAL;C.A. | J67: =IFERROR(VLOOKUP($A67,Hoja3!$A$3:$F$6000,4,FALSE),"") -> ETIQUETA IMPRESA AGUA CRYSTAL 600 cm³ | K67: 250 | L67: 0 | M67: 0 | N67: 0 | O67: 0 | P67: 15 | Q67: 0 | R67: 0 | S67: =10+10 -> 20 | T67: 0 | U67: 0 | V67: 45 | W67: 0 | X67: 30 | Y67: 0 | Z67: 0 | AA67: 0 | AB67: 0 | AC67: 0 | AD67: =SUM(L67:AC67) -> 110 | AE67: 55.2 | AF67: =SUM(AD67:AE67) -> 165.2 | AG67: =AF67/(60*24) -> 0.11472222 | AH67: =IFERROR(AE67/AF67,0) -> 0.33414044 | AI67: 7700 | AJ67: 27 | AK67: 1110 | AL67: =IF(AM67=0,0,(+AI67*AK67/1000)) -> 8547 | AM67: 225 | AN67: 4 | AO67: 94 | AP67: 13 | AQ67: 0 | AR67: 0 | AS67: 7 | AT67: 0 | AU67: 15 | AV67: =SUM(AO67:AU67) -> 129 | AW67: =+(AM67+(BR67*50/100))+(BS67*30/100)-BB67 -> 235.8 | AX67: 0 | AY67: 0 | AZ67: 0 | BA67: 0 | BB67: 0 | BC67: 82 | BD67: 2 | BE67: 0 | BF67: 0 | BG67: 4 | BH67: 0 | BI67: 13 | BJ67: =SUM(BC67:BI67) -> 101 | BK67: 7600 | BL67: =IFERROR(+BO67*1000/((BK67)*(BM67/1000)),0) -> 27.738265 | BM67: =AK67 -> 1110 | BN67: =+BK67*BM67/1000 -> 8436 | BO67: 234 | BP67: 0 | BQ67: 0 | BR67: =AO67-BC67 -> 12 | BS67: =(AP67+AQ67+AR67+AS67+AT67+AU67)-(BD67+BE67+BF67+BG67+BH67+BI67) -> 16 | BT67: =BR67+BS67 -> 28 | BU67: =IFERROR(+BK67/AE67,0) -> 137.68116 | BV67: =IFERROR(+BK67/(AF67),0) -> 46.004843 | BW67: =IFERROR(+(AI67-AZ67)-BK67,0) -> 100 | BX67: =IFERROR(+BW67/BK67,0) -> 0.013157895 | BY67: =IFERROR(+(AL67-BA67)-BN67,0) -> 111 | BZ67: =IFERROR(+BY67/BN67,0) -> 0.013157895 | CA67: =IFERROR(+AW67-(BO67),0) -> 1.8 | CB67: =IFERROR(+CA67/BO67,1) -> 0.0076923077 | CC67: 0 | CD67: 0 | CE67: se culmina sin novedad | CF67: =IFERROR((BT67*1000)/BN67,"") -> 3.3191086 | CG67: REPETICION | CH67: 1 | CI67: 3500 | CJ67: =IF(BW67=0,"",CI67-BW67) -> 3400 | CK67: {=_xlfn.IFS(CJ67>0,"CUMPLE",CJ67<0,"NO CUMPLE",CJ67="","")} -> CUMPLE | CL67: 46156 | CM67: {=_xlfn.IFS(CL67-C67 > 0,"CUMPLE",CL67-C67 < 0,"NO CUMPLE")} -> CUMPLE | CN67: 7000 | CO67: =BK67-CN67 -> 600 | CP67: 0 | CQ67: TELEPLASTIC | CR67: BOPP OCTS TRANSPARENTE
A68: 01-5940 | B68: NF | C68: 46142 | D68: =IFERROR(VLOOKUP($A68,Hoja3!$A$3:$F$6000,2,FALSE),"") -> TMCPAM080A001 | E68: 16483-1 | F68: =IFERROR(VLOOKUP($A68,Hoja3!$A$3:$F$6000,6,FALSE),"") -> LAMINACION | G68: 1 | H68: =IFERROR(VLOOKUP($A68,Hoja3!$A$3:$F$6000,5,FALSE),"") -> MCL | I68: =IFERROR(VLOOKUP($A68,Hoja3!$A$3:$F$6000,3,FALSE),"") -> CENTRAL EL PALMAR S.A. | J68: =IFERROR(VLOOKUP($A68,Hoja3!$A$3:$F$6000,4,FALSE),"") -> LAMINACION IMPRESA AZUCAR MORENA 1 Kg | K68: 700 | L68: =25+40+20 -> 85 | M68: 0 | N68: 30 | O68: 20 | P68: 0 | Q68: 0 | R68: 0 | S68: =10+20+10+15 -> 55 | T68: 0 | U68: 0 | V68: =28+85 -> 113 | W68: 0 | X68: 0 | Y68: 0 | Z68: 0 | AA68: 0 | AB68: 0 | AC68: 0 | AD68: =SUM(L68:AC68) -> 303 | AE68: 166.8 | AF68: =SUM(AD68:AE68) -> 469.8 | AG68: =AF68/(60*24) -> 0.32625 | AH68: =IFERROR(AE68/AF68,0) -> 0.3550447 | AI68: 40807 | AJ68: 22 | AK68: 790 | AL68: =IF(AM68=0,0,(+AI68*AK68/1000)) -> 32237.53 | AM68: 728 | AN68: 3 | AO68: 200 | AP68: 0 | AQ68: 0 | AR68: 0 | AS68: 0 | AT68: 0 | AU68: =43+45 -> 88 | AV68: =SUM(AO68:AU68) -> 288 | AW68: =+(AM68+(BR68*50/100))+(BS68*30/100)-BB68 -> 798.4 | AX68: 0 | AY68: 0 | AZ68: 0 | BA68: 0 | BB68: 0 | BC68: 85 | BD68: 0 | BE68: 0 | BF68: 0 | BG68: 0 | BH68: 0 | BI68: =27+18 -> 45 | BJ68: =SUM(BC68:BI68) -> 130 | BK68: 38500 | BL68: =IFERROR(+BO68*1000/((BK68)*(BM68/1000)),0) -> 24.889035 | BM68: =AK68 -> 790 | BN68: =+BK68*BM68/1000 -> 30415 | BO68: 757 | BP68: 0 | BQ68: 0 | BR68: =AO68-BC68 -> 115 | BS68: =(AP68+AQ68+AR68+AS68+AT68+AU68)-(BD68+BE68+BF68+BG68+BH68+BI68) -> 43 | BT68: =BR68+BS68 -> 158 | BU68: =IFERROR(+BK68/AE68,0) -> 230.81535 | BV68: =IFERROR(+BK68/(AF68),0) -> 81.949766 | BW68: =IFERROR(+(AI68-AZ68)-BK68,0) -> 2307 | BX68: =IFERROR(+BW68/BK68,0) -> 0.059922078 | BY68: =IFERROR(+(AL68-BA68)-BN68,0) -> 1822.53 | BZ68: =IFERROR(+BY68/BN68,0) -> 0.059922078 | CA68: =IFERROR(+AW68-(BO68),0) -> 41.4 | CB68: =IFERROR(+CA68/BO68,1) -> 0.054689564 | CC68: 0 | CD68: 0 | CE68: se culmina sin novedad | CF68: =IFERROR((BT68*1000)/BN68,"") -> 5.1948052 | CG68: REPETICION | CH68: 2 | CI68: 3500 | CJ68: =IF(BW68=0,"",CI68-BW68) -> 1193 | CK68: {=_xlfn.IFS(CJ68>0,"CUMPLE",CJ68<0,"NO CUMPLE",CJ68="","")} -> CUMPLE | CL68: 46075 | CM68: {=_xlfn.IFS(CL68-C68 > 0,"CUMPLE",CL68-C68 < 0,"NO CUMPLE")} -> NO CUMPLE | CN68: 38500 | CO68: =BK68-CN68 -> 0 | CP68: 0 | CQ68: TELEPLASTIC | CR68: BOPP OCTS TRANSPARENTE
A69: 000lm | B69: NF | C69: 46142 | D69: =IFERROR(VLOOKUP($A69,Hoja3!$A$3:$F$6000,2,FALSE),"") -> 000LM | E69: 000lm | F69: =IFERROR(VLOOKUP($A69,Hoja3!$A$3:$F$6000,6,FALSE),"") -> LIMPIEZA | G69: 0 | H69: =IFERROR(VLOOKUP($A69,Hoja3!$A$3:$F$6000,5,FALSE),"") -> CX | I69: =IFERROR(VLOOKUP($A69,Hoja3!$A$3:$F$6000,3,FALSE),"") -> LIMPIEZA GENERAL DE MAQUINA | J69: =IFERROR(VLOOKUP($A69,Hoja3!$A$3:$F$6000,4,FALSE),"") -> LIMPIEZA GENERAL DE MAQUINA | K69: 0 | L69: 0 | M69: 0 | N69: 0 | O69: 0 | P69: 0 | Q69: 489.6 | R69: 0 | S69: 0 | T69: 0 | U69: 0 | V69: 0 | W69: 0 | X69: 0 | Y69: 0 | Z69: 0 | AA69: 0 | AB69: 0 | AC69: 0 | AD69: =SUM(L69:AC69) -> 489.6 | AE69: 0 | AF69: =SUM(AD69:AE69) -> 489.6 | AG69: =AF69/(60*24) -> 0.34 | AH69: =IFERROR(AE69/AF69,0) -> 0 | AI69: 0 | AJ69: 0 | AK69: 0 | AL69: =IF(AM69=0,0,(+AI69*AK69/1000)) -> 0 | AM69: 0 | AN69: 0 | AO69: 0 | AP69: 0 | AQ69: 0 | AR69: 0 | AS69: 0 | AT69: 0 | AU69: 0 | AV69: =SUM(AO69:AU69) -> 0 | AW69: =+(AM69+(BR69*50/100))+(BS69*30/100)-BB69 -> 0 | AX69: 0 | AY69: 0 | AZ69: 0 | BA69: 0 | BB69: 0 | BC69: 0 | BD69: 0 | BE69: 0 | BF69: 0 | BG69: 0 | BH69: 0 | BI69: 0 | BJ69: 0 | BK69: 0 | BL69: 0 | BM69: 0 | BN69: 0 | BO69: 0 | BP69: 0 | BQ69: 0 | BR69: 0 | BS69: 0 | BT69: 0 | BU69: 0 | BV69: 0 | BW69: 0 | BX69: 0 | BY69: 0 | BZ69: 0 | CA69: 0 | CB69: 0 | CC69: 0 | CD69: 0 | CE69: se reliza limpieza general de maquina | CF69: 0 | CG69: LIMPIEZA | CH69: 0 | CI69: 0 | CJ69: 0 | CK69: 0 | CL69: 0 | CM69: 0 | CN69: 0 | CO69: =BK69-CN69 -> 0 | CP69: 0
A70: 000F | B70: NF | C70: 46142 | D70: =IFERROR(VLOOKUP($A70,Hoja3!$A$3:$F$6000,2,FALSE),"") -> 000F | E70: 000F | F70: =IFERROR(VLOOKUP($A70,Hoja3!$A$3:$F$6000,6,FALSE),"") -> TODAS | G70: 0 | H70: =IFERROR(VLOOKUP($A70,Hoja3!$A$3:$F$6000,5,FALSE),"") -> MCL | I70: =IFERROR(VLOOKUP($A70,Hoja3!$A$3:$F$6000,3,FALSE),"") -> FALTA DE PEDIDOS / INSUMOS | J70: =IFERROR(VLOOKUP($A70,Hoja3!$A$3:$F$6000,4,FALSE),"") -> FALTA DE PEDIDOS / INSUMOS | K70: 0 | L70: 0 | M70: 0 | N70: 0 | O70: 0 | P70: 0 | Q70: 0 | R70: 0 | S70: 0 | T70: 0 | U70: 0 | V70: 0 | W70: 0 | X70: 0 | Y70: 0 | Z70: 0 | AA70: 0 | AB70: 0 | AC70: 619 | AD70: =SUM(L70:AC70) -> 619 | AE70: 0 | AF70: =SUM(AD70:AE70) -> 619 | AG70: =AF70/(60*24) -> 0.42986111 | AH70: =IFERROR(AE70/AF70,0) -> 0 | AW70: =+(AM70+(BR70*50/100))+(BS70*30/100)-BB70 -> 0 | BJ70: 0
I71: =IFERROR(VLOOKUP($A71,Hoja3!$A$3:$F$6000,3,FALSE),"") | J71: =IFERROR(VLOOKUP($A71,Hoja3!$A$3:$F$6000,4,FALSE),"") | CK71: {=_xlfn.IFS(CJ71>0,"CUMPLE",CJ71<0,"NO CUMPLE",CJ71="","")}
A72: NF= NOVOFLEX FINAL | E72: Numeros de trabajos= | G72: =SUM(G14:G70) -> 45 | I72: =IFERROR(VLOOKUP($A72,Hoja3!$A$3:$F$6000,3,FALSE),"") | J72: =IFERROR(VLOOKUP($A72,Hoja3!$A$3:$F$6000,4,FALSE),"") | K72: =SUM(K14:K70) -> 70604 | L72: =SUM(L14:L70) -> 2425 | M72: =SUM(M14:M70) -> 1120 | N72: =SUM(N14:N70) -> 2657 | O72: =SUM(O14:O70) -> 765 | P72: =SUM(P14:P70) -> 3222 | Q72: =SUM(Q14:Q70) -> 1419.4 | R72: =SUM(R14:R70) -> 0 | ... AG72: =SUM(AG14:AG70) -> 20.000278 | AH72: =IFERROR(AE72/AF73,0) -> 0.3432244 | AI72: =SUM(AI14:AI70) -> 1869772.5 | AL72: =SUM(AL14:AL70) -> 1838326 | AM72: =SUM(AM14:AM70) -> 49373.2 | AN72: =SUM(AN14:AN70) -> 260 | AW72: =+(AM72+(BR72*50/100))+(BS72*30/100)-BB72 -> 51994.4 | AX72: =SUM(AX14:AX70) -> 0 | AY72: =SUM(AY14:AY70) -> 0 | AZ72: =SUM(AZ14:AZ70) -> 0 | BA72: =SUM(BA14:BA70) -> 0 | BB72: =SUM(BB14:BB70) -> 0 | BJ72: =SUM(BJ14:BJ70) -> 10129 | BK72: =SUM(BK14:BK70) -> 1721876 | BN72: =SUM(BN14:BN70) -> 1693069.7 | BO72: =SUM(BO14:BO70) -> 47616.6 | BP72: =SUM(BP14:BP70) -> 0 | BQ72: =SUM(BQ14:BQ70) -> 0 | BR72: =SUM(BR14:BR70) -> 2201 | BS72: =SUM(BS14:BS70) -> 5069 | BT72: =SUM(BT14:BT70) -> 7270 | BU72: =IFERROR(+BK72/AE72,0) -> 174.19079 | BV72: =BK72/(AF72-(AC72+Q72+W72)) -> 64.472835 | BW72: =IFERROR(AI72-AZ72,0)-BK72 -> 147896.5 | BX72: =IFERROR(+BW72/BK72,0) -> 0.085892654 | BY72: =IFERROR(AL72-BA72,0)-BN72 -> 145256.32 | BZ72: =IFERROR(+BY72/BN72,0) -> 0.085794654 | CA72: =IFERROR(+AW72-(BO72),0) -> 4377.8 | CB72: =IFERROR(+CA72/BO72,0) -> 0.091938526 | CC72: =SUM(CC14:CC70) -> 0 | CD72: =SUM(CD14:CD70) -> 0 | CF72: =IFERROR((BT72*1000)/BN72,"") -> 4.2939757 | CK72: {=_xlfn.IFS(CJ72>0,"CUMPLE",CJ72<0,"NO CUMPLE",CJ72="","")} | CN72: =SUM(CN14:CN70) -> 1770200 | CO72: =BK72-CN72 -> -48324
A73: NP= NOVOFLEX PROCESO | I73: =IFERROR(VLOOKUP($A73,Hoja3!$A$3:$F$6000,3,FALSE),"") | J73: =IFERROR(VLOOKUP($A73,Hoja3!$A$3:$F$6000,4,FALSE),"") | K73: % EFICIENCIA | L73: =IFERROR(L72/AF73,0) -> 0.084200219 | M73: =IFERROR(M72/AF73,0) -> 0.038888349 | N73: =(N72/AF73) -> 0.092255663 | O73: =(O72/AF73) -> 0.026562131 | P73: =(P72/AF73) -> 0.11187345 | Q73: =(Q72/AF73) -> 0.049284038 | R73: =(R72/AF73) -> 0 | S73: =(S72/AF73) -> 0.068505993 | T73: =(T72/AF73) -> 0.0062499132 | U73: =(U72/AF73) -> 0.0024305218 | V73: =(V72/AF73) -> 0.064686602 | W73: =(W72/AF73) -> 0.0019096957 | X73: =(X72/AF73) -> 0.018819183 | Y73: =(Y72/AF73) -> 0 | Z73: =(Z72/AF73) -> 0.053124262 | AA73: =(AA72/AF73) -> 0.011284565 | AB73: =(AB72/AF72) -> 0.005208261 | AC73: =(AC72/AF72) -> 0.021492757 | AD73: =(AD72/AF73) -> 0.6567756 | AE73: =(AE72/AF73) -> 0.3432244 | AF73: =AF72 -> 28800.4 | AG73: =AF73/60/24 -> 20.000278 | AH73: <= Tiempo dedicado | CK73: {=_xlfn.IFS(CJ73>0,"CUMPLE",CJ73<0,"NO CUMPLE",CJ73="","")}
A74: Nota: | I74: =IFERROR(VLOOKUP($A74,Hoja3!$A$3:$F$6000,3,FALSE),"") | J74: =IFERROR(VLOOKUP($A74,Hoja3!$A$3:$F$6000,4,FALSE),"") | K74: Horas | L74: =(L72/60) -> 40.416667 | M74: =(M72/60) -> 18.666667 | N74: =(N72/60) -> 44.283333 | O74: =(O72/60) -> 12.75 | P74: =(P72/60) -> 53.7 | Q74: =(Q72/60) -> 23.656667 | R74: =(R72/60) -> 0 | S74: =(S72/60) -> 32.883333 | ... AF74: =(AF72/60) -> 480.00667 | AG74: =AH74/60/24 -> -0.00027777778 | AH74: =D7-(AF72) -> -0.4 | BJ74: Meta | BK74: 4200000 | BZ74: Meta Desperdicio | CB74: 0.08 | CF74: TRABAJOS QUE NO CUMPLEN CON EL ESTANDAR EN METROS | CJ74: =COUNTIF(CK14:CK70,"NO CUMPLE") -> 16
A75: EL PROMEDIO DE METROS EN TERMINOS DE EFICIENCIA POR TURNO EN FUNCION AL TIEMPO DISPONIBLE ES DE | J75: =IFERROR(BK72/(C7*3),0) -> 28697.933 | K75: Dias | L75: =(L74/24) -> 1.6840278 | M75: =(M74/24) -> 0.77777778 | N75: =(N74/24) -> 1.8451389 | O75: =(O74/24) -> 0.53125 | P75: =(P74/24) -> 2.2375 | Q75: =(Q74/24) -> 0.98569444 | R75: =(R74/24) -> 0 | S75: =(S74/24) -> 1.3701389 | ... AF75: =(AF74/24) -> 20.000278 | AG75: DIAS POR TRABAJAR | CF75: TRABAJOS CUMPLEN CON EL ESTANDAR EN METROS | CJ75: =COUNTIF(CK14:CK70,"CUMPLE") -> 33
A76: EL PROMEDIO DE METROS EN TERMINOS DE EFICIENCIA POR TURNO EN FUNCION AL TIEMPO DE TRABAJO ES DE | J76: =IFERROR(BK72/(ROUND(AE75,0)*3),0) -> 81994.095
A77: =IFERROR(L74/G72,0) -> 0.89814815 | AF77: min | AG77: Hrs | AH77: Dias | CF77: TRABAJOS QUE NO CUMPLEN CON LA FECHA DE ENTREGA | CJ77: =COUNTIF(CM14:CM70,"NO CUMPLE") -> 36
AC78: Tiempo Total de Limpieza general de maquina | AF78: =Q72 -> 1419.4 | AG78: =Q74 -> 23.656667 | AH78: =Q75 -> 0.98569444 | CF78: TRABAJOS CUMPLEN CON LA FECHA DE ENTREGA | CJ78: =COUNTIF(CM14:CM70,"CUMPLE") -> 15
D79: PROMEDIO DE TIEMPO DE PREPARACION POR TRABAJO => | I79: =IFERROR(L72/G72,0) -> 53.888889 | P79: suspendidos | CK79: {=_xlfn.IFS(CJ79>0,"CUMPLE",CJ79<0,"NO CUMPLE",CJ79="","")}
K80: Numero de aprobaciones en el mes => | O80: =COUNTIFS(CG20:CG70,"APROBACION") -> 8 | P80: =COUNTIFS(Z14:Z70,">0",CG14:CG70,"suspendido") -> 0 | Q80: Trabajos suspendidos en el mes => | W80: =P80+P81 -> 1 | AC80: Tiempo Total de Parada por Produccion | AF80: =(L72+M72+N72+S72+V72+T72+U72) -> 10288 | AG80: =(L74+M74+N74+S74+V74+T74+U74) -> 171.46667 | AH80: =(L75+M75+N75+S75+V75+T75+U75) -> 7.1444444 | CK80: {=_xlfn.IFS(CJ80>0,"CUMPLE",CJ80<0,"NO CUMPLE",CJ80="","")}
K81: Trabajos Repetidos en el mes => | O81: =COUNTIFS(CG14:CG70,"REPETICION")+COUNTIFS(CG14:CG70,"PROCESO") -> 37 | P81: =COUNTIFS(Z14:Z70,"=0",CG14:CG70,"suspendido") -> 1 | CK81: {=_xlfn.IFS(CJ81>0,"CUMPLE",CJ81<0,"NO CUMPLE",CJ81="","")}
AC82: Tiempo Total de Parada por Proceso de Apoyo | AF82: =(O72+P72+R72+W72+X72+Y72+Z72+AA72+AB72) -> 6589 | AG82: =(O74+P74+R74+W74+X74+Y74+Z74+AB74+AA74) -> 109.81667 | AH82: =(O75+P75+R75+W75+X75+Y75+Z75+AB75+AA75) -> 4.5756944 | CK82: {=_xlfn.IFS(CJ82>0,"CUMPLE",CJ82<0,"NO CUMPLE",CJ82="","")}
AC83: Tiempo Total de Parada por Falta de Pedido | AF83: =AC72 -> 619 | AG83: =AC74 -> 10.316667 | AH83: =AC75 -> 0.42986111 | CK83: {=_xlfn.IFS(CJ83>0,"CUMPLE",CJ83<0,"NO CUMPLE",CJ83="","")}
K84: Estandar de Color | O84: Min | AC84: Horas TRABAJADAS | AF84: =AE72 -> 9885 | AG84: =AE74 -> 164.75 | AH84: =AE75 -> 6.8645833 | CK84: {=_xlfn.IFS(CJ84>0,"CUMPLE",CJ84<0,"NO CUMPLE",CJ84="","")}
K85: *Cantidad de trabajos con estandar | O85: =COUNTIF(AA14:AA70,">0") -> 12 | AD85: TOTAL | AF85: =SUM(AF78:AF84) -> 28800.4 | AG85: =SUM(AG78:AG84) -> 480.00667 | AH85: =SUM(AH78:AH84) -> 20.000278
K86: * Tiempo total invertido para Estandar | O86: =SUM(AA14:AA70) -> 325
L88: meta de mes | O88: =((O85*60)/AF85) -> 0.024999653
L89: % del mes | O89: =(O86/AF85) -> 0.011284565

Sheet Hoja3
A1: 1 | B1: 2 | C1: 3 | D1: 4 | E1: 5 | F1: 6
A2: Pedido | B2: codigo | C2: Cliente | D2: Producto | E2: Cliente interno | F2: Destino
A3: =IF('[1]Hoja de pedidos'!$D5>0,'[1]Hoja de pedidos'!C5,"") -> 01-1582 | B3: =IF('[1]Hoja de pedidos'!$D5>0,'[1]Hoja de pedidos'!D5,"") -> 00110603540 | C3: =IF('[1]Hoja de pedidos'!$D5>0,'[1]Hoja de pedidos'!E5,"") -> ALUM-WARE PRODUCTOS DE ALUMINIO C.A. | D3: =IF('[1]Hoja de pedidos'!$D5>0,'[1]Hoja de pedidos'!F5,"") -> POLYPOUCH IMPRESO ANTIGRASO ALUM-WARE | E3: =IF('[1]Hoja de pedidos'!$D5>0,'[1]Hoja de pedidos'!G5,"") -> MCL | F3: =IF('[1]Hoja de pedidos'!$D5>0,'[1]Hoja de pedidos'!H5,"") -> LAMINACION
A4: =IF('[1]Hoja de pedidos'!$D6>0,'[1]Hoja de pedidos'!C6,"") -> 01-1610 | B4: =IF('[1]Hoja de pedidos'!$D6>0,'[1]Hoja de pedidos'!D6,"") -> 00110452168 | C4: =IF('[1]Hoja de pedidos'!$D6>0,'[1]Hoja de pedidos'!E6,"") -> CENTRAL EL PALMAR S.A. | D4: =IF('[1]Hoja de pedidos'!$D6>0,'[1]Hoja de pedidos'!F6,"") -> POLYPOUCH IMPRESO MONTALBAN - MONTALBAN 4 g | E4: =IF('[1]Hoja de pedidos'!$D6>0,'[1]Hoja de pedidos'!G6,"") -> MCL | F4: =IF('[1]Hoja de pedidos'!$D6>0,'[1]Hoja de pedidos'!H6,"") -> LAMINACION
A5: =IF('[1]Hoja de pedidos'!$D7>0,'[1]Hoja de pedidos'!C7,"") -> 01-1598 | B5: =IF('[1]Hoja de pedidos'!$D7>0,'[1]Hoja de pedidos'!D7,"") -> 00010610000 | C5: =IF('[1]Hoja de pedidos'!$D7>0,'[1]Hoja de pedidos'!E7,"") -> DEXX MEDICAL INDUSTRIES C.A. | D5: =IF('[1]Hoja de pedidos'!$D7>0,'[1]Hoja de pedidos'!F7,"") -> BOLSAS GASAS ESTIRILIZABLES DORSO SIN IMPRESIÓN | E5: =IF('[1]Hoja de pedidos'!$D7>0,'[1]Hoja de pedidos'!G7,"") -> MCL | F5: =IF('[1]Hoja de pedidos'!$D7>0,'[1]Hoja de pedidos'!H7,"") -> CORTE
A6: =IF('[1]Hoja de pedidos'!$D8>0,'[1]Hoja de pedidos'!C8,"") -> 32-005754 | B6: =IF('[1]Hoja de pedidos'!$D8>0,'[1]Hoja de pedidos'!D8,"") -> 01410423215 | C6: =IF('[1]Hoja de pedidos'!$D8>0,'[1]Hoja de pedidos'!E8,"") -> SERVIQUIM, C.A. | D6: =IF('[1]Hoja de pedidos'!$D8>0,'[1]Hoja de pedidos'!F8,"") -> ETIQUETAS LAMINADAS IMPRESA BLANCLORO REGULAR 1 L | E6: =IF('[1]Hoja de pedidos'!$D8>0,'[1]Hoja de pedidos'!G8,"") -> CX | F6: =IF('[1]Hoja de pedidos'!$D8>0,'[1]Hoja de pedidos'!H8,"") -> LAMINACION
A7: =IF('[1]Hoja de pedidos'!$D9>0,'[1]Hoja de pedidos'!C9,"") -> 01-1617 | B7: =IF('[1]Hoja de pedidos'!$D9>0,'[1]Hoja de pedidos'!D9,"") -> 00141190000 | C7: =IF('[1]Hoja de pedidos'!$D9>0,'[1]Hoja de pedidos'!E9,"") -> ETIQUETAS SOL SIL C.A | D7: =IF('[1]Hoja de pedidos'!$D9>0,'[1]Hoja de pedidos'!F9,"") -> ALUMINIO LAMINADO SIN IMPRESIÓN | E7: =IF('[1]Hoja de pedidos'!$D9>0,'[1]Hoja de pedidos'!G9,"") -> MCL | F7: =IF('[1]Hoja de pedidos'!$D9>0,'[1]Hoja de pedidos'!H9,"") -> LAMINACION
A8: =IF('[1]Hoja de pedidos'!$D10>0,'[1]Hoja de pedidos'!C10,"") -> 01-1609 | B8: =IF('[1]Hoja de pedidos'!$D10>0,'[1]Hoja de pedidos'!D10,"") -> 00141190000 | C8: =IF('[1]Hoja de pedidos'!$D10>0,'[1]Hoja de pedidos'!E10,"") -> ALIMENTOS POLAR COMERCIAL;C.A. | D8: =IF('[1]Hoja de pedidos'!$D10>0,'[1]Hoja de pedidos'!F10,"") -> ALUMINIO LAMINADO SIN IMPRESIÓN | E8: =IF('[1]Hoja de pedidos'!$D10>0,'[1]Hoja de pedidos'!G10,"") -> MCL | F8: =IF('[1]Hoja de pedidos'!$D10>0,'[1]Hoja de pedidos'!H10,"") -> LAMINACION
A9: =IF('[1]Hoja de pedidos'!$D11>0,'[1]Hoja de pedidos'!C11,"") -> 01-1619 | B9: =IF('[1]Hoja de pedidos'!$D11>0,'[1]Hoja de pedidos'!D11,"") -> 01410413727 | C9: =IF('[1]Hoja de pedidos'!$D11>0,'[1]Hoja de pedidos'!E11,"") -> PEPSICO ALIMENTOS, S.C.A. | D9: =IF('[1]Hoja de pedidos'!$D11>0,'[1]Hoja de pedidos'!F11,"") -> LAMINACIÓN IMPRESA RUFFLES QUESO 36 g. | E9: =IF('[1]Hoja de pedidos'!$D11>0,'[1]Hoja de pedidos'!G11,"") -> CX | F9: =IF('[1]Hoja de pedidos'!$D11>0,'[1]Hoja de pedidos'!H11,"") -> LAMINACION
A10: =IF('[1]Hoja de pedidos'!$D12>0,'[1]Hoja de pedidos'!C12,"") -> 01-1618 | B10: =IF('[1]Hoja de pedidos'!$D12>0,'[1]Hoja de pedidos'!D12,"") -> 01410413728 | C10: =IF('[1]Hoja de pedidos'!$D12>0,'[1]Hoja de pedidos'!E12,"") -> PEPSICO ALIMENTOS, S.C.A. | D10: =IF('[1]Hoja de pedidos'!$D12>0,'[1]Hoja de pedidos'!F12,"") -> LAMINACIÓN IMPRESA RUFFLESS QUESO 125 g | E10: =IF('[1]Hoja de pedidos'!$D12>0,'[1]Hoja de pedidos'!G12,"") -> CX | F10: =IF('[1]Hoja de pedidos'!$D12>0,'[1]Hoja de pedidos'!H12,"") -> LAMINACION
A11: =IF('[1]Hoja de pedidos'!$D13>0,'[1]Hoja de pedidos'!C13,"") -> 01-1625 | B11: =IF('[1]Hoja de pedidos'!$D13>0,'[1]Hoja de pedidos'!D13,"") -> 01410483669 | C11: =IF('[1]Hoja de pedidos'!$D13>0,'[1]Hoja de pedidos'!E13,"") -> C.A. SUCESORA DE JOSE PUIG & CIA | D11: =IF('[1]Hoja de pedidos'!$D13>0,'[1]Hoja de pedidos'!F13,"") -> LAMINACION IMPRESA REX 200 g | E11: =IF('[1]Hoja de pedidos'!$D13>0,'[1]Hoja de pedidos'!G13,"") -> CX | F11: =IF('[1]Hoja de pedidos'!$D13>0,'[1]Hoja de pedidos'!H13,"") -> LAMINACION
A12: =IF('[1]Hoja de pedidos'!$D14>0,'[1]Hoja de pedidos'!C14,"") -> 01-1629 | B12: =IF('[1]Hoja de pedidos'!$D14>0,'[1]Hoja de pedidos'!D14,"") -> 01410413673 | C12: =IF('[1]Hoja de pedidos'!$D14>0,'[1]Hoja de pedidos'!E14,"") -> PEPSICO ALIMENTOS, S.C.A. | D12: =IF('[1]Hoja de pedidos'!$D14>0,'[1]Hoja de pedidos'!F14,"") -> LAMINACION IMPRESA PAPAS JACKS SAL 100g | E12: =IF('[1]Hoja de pedidos'!$D14>0,'[1]Hoja de pedidos'!G14,"") -> CX | F12: =IF('[1]Hoja de pedidos'!$D14>0,'[1]Hoja de pedidos'!H14,"") -> LAMINACION
A13: =IF('[1]Hoja de pedidos'!$D15>0,'[1]Hoja de pedidos'!C15,"") -> 01-1628 | B13: =IF('[1]Hoja de pedidos'!$D15>0,'[1]Hoja de pedidos'!D15,"") -> 01410413674 | C13: =IF('[1]Hoja de pedidos'!$D15>0,'[1]Hoja de pedidos'!E15,"") -> PEPSICO ALIMENTOS, S.C.A. | D13: =IF('[1]Hoja de pedidos'!$D15>0,'[1]Hoja de pedidos'!F15,"") -> LAMINACION IMPRESA PAPAS JACKS QUESO 100g | E13: =IF('[1]Hoja de pedidos'!$D15>0,'[1]Hoja de pedidos'!G15,"") -> CX | F13: =IF('[1]Hoja de pedidos'!$D15>0,'[1]Hoja de pedidos'!H15,"") -> LAMINACION
A14: =IF('[1]Hoja de pedidos'!$D16>0,'[1]Hoja de pedidos'!C16,"") -> 01-1611 | B14: =IF('[1]Hoja de pedidos'!$D16>0,'[1]Hoja de pedidos'!D16,"") -> 01410890542 | C14: =IF('[1]Hoja de pedidos'!$D16>0,'[1]Hoja de pedidos'!E16,"") -> CUREX C.A. | D14: =IF('[1]Hoja de pedidos'!$D16>0,'[1]Hoja de pedidos'!F16,"") -> LAMINACIÓN DECOCEL UNICOLOR SOLIDO AZUL P-300 | E14: =IF('[1]Hoja de pedidos'!$D16>0,'[1]Hoja de pedidos'!G16,"") -> CX | F14: =IF('[1]Hoja de pedidos'!$D16>0,'[1]Hoja de pedidos'!H16,"") -> LAMINACION
... A217: =IF('[1]Hoja de pedidos'!$D219>0,'[1]Hoja de pedidos'!C219,"") -> 32-005959 | B217: =IF('[1]Hoja de pedidos'!$D219>0,'[1]Hoja de pedidos'!D219,"") -> TMCSPS0800001 | C217: =IF('[1]Hoja de pedidos'!$D219>0,'[1]Hoja de pedidos'!E219,"") -> COOPERATIVA FABRICA DE PRODUCTOS MEDICOS SANIPAD | D217: =IF('[1]Hoja de pedidos'!$D219>0,'[1]Hoja de pedidos'!F219,"") -> POLYPOUCH SIN IMPRESIÓN | E217: =IF('[1]Hoja de pedidos'!$D219>0,'[1]Hoja de pedidos'!G219,"") -> MCL | F217: =IF('[1]Hoja de pedidos'!$D219>0,'[1]Hoja de pedidos'!H219,"") -> CORTE
A218: =IF('[1]Hoja de pedidos'!$D219>0,'[1]Hoja de pedidos'!C219,"") -> 32-005959 | B218: =IF('[1]Hoja de pedidos'!$D219>0,'[1]Hoja de pedidos'!D219,"") -> TMCSPS0800001 | C218: =IF('[1]Hoja de pedidos'!$D219>0,'[1]Hoja de pedidos'!E219,"") -> COOPERATIVA FABRICA DE PRODUCTOS MEDICOS SANIPAD | D218: =IF('[1]Hoja de pedidos'!$D219>0,'[1]Hoja de pedidos'!F219,"") -> POLYPOUCH SIN IMPRESIÓN | E218: =IF('[1]Hoja de pedidos'!$D219>0,'[1]Hoja de pedidos'!G219,"") -> MCL | F218: =IF('[1]Hoja de pedidos'!$D219>0,'[1]Hoja de pedidos'!H219,"") -> CORTE
A219: =IF('[1]Hoja de pedidos'!$D220>0,'[1]Hoja de pedidos'!C220,"") -> 01-2046 | B219: =IF('[1]Hoja de pedidos'!$D220>0,'[1]Hoja de pedidos'!D220,"") -> TXHMBI078A001 | C219: =IF('[1]Hoja de pedidos'!$D220>0,'[1]Hoja de pedidos'!E220,"") -> H.M.D MEDICAL, C.A | D219: =IF('[1]Hoja de pedidos'!$D220>0,'[1]Hoja de pedidos'!F220,"") -> LAMINACION IMPRESA BIOSCRUB AZUL SOLUCION IODADA | E219: =IF('[1]Hoja de pedidos'!$D220>0,'[1]Hoja de pedidos'!G220,"") -> CX | F219: =IF('[1]Hoja de pedidos'!$D220>0,'[1]Hoja de pedidos'!H220,"") -> LAMINACION
A220: =IF('[1]Hoja de pedidos'!$D221>0,'[1]Hoja de pedidos'!C221,"") -> 01-2047 | B220: =IF('[1]Hoja de pedidos'!$D221>0,'[1]Hoja de pedidos'!D221,"") -> TXHMRO024A001 | C220: =IF('[1]Hoja de pedidos'!$D221>0,'[1]Hoja de pedidos'!E221,"") -> H.M.D MEDICAL, C.A | D220: =IF('[1]Hoja de pedidos'!$D221>0,'[1]Hoja de pedidos'!F221,"") -> ENVOLTORIO IMPRESO RECOLECTOR DE ORINA | E220: =IF('[1]Hoja de pedidos'!$D221>0,'[1]Hoja de pedidos'!G221,"") -> CX | F220: =IF('[1]Hoja de pedidos'!$D221>0,'[1]Hoja de pedidos'!H221,"") -> CORTE
A221: =IF('[1]Hoja de pedidos'!$D222>0,'[1]Hoja de pedidos'!C222,"") -> 01-2055 | B221: =IF('[1]Hoja de pedidos'!$D222>0,'[1]Hoja de pedidos'!D222,"") -> TXPACT040A001 | C221: =IF('[1]Hoja de pedidos'!$D222>0,'[1]Hoja de pedidos'!E222,"") -> PEPSICO ALIMENTOS, S.C.A. | D221: =IF('[1]Hoja de pedidos'!$D222>0,'[1]Hoja de pedidos'!F222,"") -> LAMINACION IMPRESA CHEESE TRIS 150g | E221: =IF('[1]Hoja de pedidos'!$D222>0,'[1]Hoja de pedidos'!G222,"") -> CX | F221: =IF('[1]Hoja de pedidos'!$D222>0,'[1]Hoja de pedidos'!H222,"") -> LAMINACION
A222: =IF('[1]Hoja de pedidos'!$D223>0,'[1]Hoja de pedidos'!C223,"") -> 01-2042 | B222: =IF('[1]Hoja de pedidos'!$D223>0,'[1]Hoja de pedidos'!D223,"") -> TXPAPD040A001 | C222: =IF('[1]Hoja de pedidos'!$D223>0,'[1]Hoja de pedidos'!E223,"") -> PEPSICO ALIMENTOS, S.C.A. | D222: =IF('[1]Hoja de pedidos'!$D223>0,'[1]Hoja de pedidos'!F223,"") -> LAMINACION IMPRESA PEPITO DINOSAURIO 65g | E222: =IF('[1]Hoja de pedidos'!$D223>0,'[1]Hoja de pedidos'!G223,"") -> CX | F222: =IF('[1]Hoja de pedidos'!$D223>0,'[1]Hoja de pedidos'!H223,"") -> LAMINACION
A223: =IF('[1]Hoja de pedidos'!$D224>0,'[1]Hoja de pedidos'!C224,"") -> 01-2041 | B223: =IF('[1]Hoja de pedidos'!$D224>0,'[1]Hoja de pedidos'!D224,"") -> TXPAPD040B001 | C223: =IF('[1]Hoja de pedidos'!$D224>0,'[1]Hoja de pedidos'!E224,"") -> PEPSICO ALIMENTOS, S.C.A. | D223: =IF('[1]Hoja de pedidos'!$D224>0,'[1]Hoja de pedidos'!F224,"") -> LAMINACION IMPRESA PEPITO DINOSAURIO 22g | E223: =IF('[1]Hoja de pedidos'!$D224>0,'[1]Hoja de pedidos'!G224,"") -> CX | F223: =IF('[1]Hoja de pedidos'!$D224>0,'[1]Hoja de pedidos'!H224,"") -> LAMINACION
A224: =IF('[1]Hoja de pedidos'!$D225>0,'[1]Hoja de pedidos'!C225,"") -> 01-2056 | B224: =IF('[1]Hoja de pedidos'!$D225>0,'[1]Hoja de pedidos'!D225,"") -> TXPACC040B001 | C224: =IF('[1]Hoja de pedidos'!$D225>0,'[1]Hoja de pedidos'!E225,"") -> PEPSICO ALIMENTOS, S.C.A. | D224: =IF('[1]Hoja de pedidos'!$D225>0,'[1]Hoja de pedidos'!F225,"") -> LAMINACION IMPRESA CHEETOS CRUNCHY 145g | E224: =IF('[1]Hoja de pedidos'!$D225>0,'[1]Hoja de pedidos'!G225,"") -> CX | F224: =IF('[1]Hoja de pedidos'!$D225>0,'[1]Hoja de pedidos'!H225,"") -> LAMINACION
A225: =IF('[1]Hoja de pedidos'!$D226>0,'[1]Hoja de pedidos'!C226,"") -> 01-1997 | B225: =IF('[1]Hoja de pedidos'!$D226>0,'[1]Hoja de pedidos'!D226,"") -> TXABCA041A001 | C225: =IF('[1]Hoja de pedidos'!$D226>0,'[1]Hoja de pedidos'!E226,"") -> MONTALAR DE VENEZUELA, S.A. | D225: =IF('[1]Hoja de pedidos'!$D226>0,'[1]Hoja de pedidos'!F226,"") -> LAMINACION ENDULZANTE 500g | E225: =IF('[1]Hoja de pedidos'!$D226>0,'[1]Hoja de pedidos'!G226,"") -> CX | F225: =IF('[1]Hoja de pedidos'!$D226>0,'[1]Hoja de pedidos'!H226,"") -> LAMINACION
A226: =IF('[1]Hoja de pedidos'!$D227>0,'[1]Hoja de pedidos'!C227,"") -> 01-2052 | B226: =IF('[1]Hoja de pedidos'!$D227>0,'[1]Hoja de pedidos'!D227,"") -> TMAWAA064A002 | C226: =IF('[1]Hoja de pedidos'!$D227>0,'[1]Hoja de pedidos'!E227,"") -> ALUM-WARE PRODUCTOS DE ALUMINIO C.A. | D226: =IF('[1]Hoja de pedidos'!$D227>0,'[1]Hoja de pedidos'!F227,"") -> POLYPOUCH IMPRESO ANTIGRASO ALUM-WARE | E226: =IF('[1]Hoja de pedidos'!$D227>0,'[1]Hoja de pedidos'!G227,"") -> MCL | F226: =IF('[1]Hoja de pedidos'!$D227>0,'[1]Hoja de pedidos'!H227,"") -> LAMINACION
A227: =IF('[1]Hoja de pedidos'!$D228>0,'[1]Hoja de pedidos'!C228,"") -> 01-2057 | B227: =IF('[1]Hoja de pedidos'!$D228>0,'[1]Hoja de pedidos'!D228,"") -> TXPAJS040B001 | C227: =IF('[1]Hoja de pedidos'!$D228>0,'[1]Hoja de pedidos'!E228,"") -> PEPSICO ALIMENTOS, S.C.A. | D227: =IF('[1]Hoja de pedidos'!$D228>0,'[1]Hoja de pedidos'!F228,"") -> LAMINACION IMPRESA PAPAS JACKS SAL 100 g | E227: =IF('[1]Hoja de pedidos'!$D228>0,'[1]Hoja de pedidos'!G228,"") -> CX | F227: =IF('[1]Hoja de pedidos'!$D228>0,'[1]Hoja de pedidos'!H228,"") -> LAMINACION
A228: =IF('[1]Hoja de pedidos'!$D229>0,'[1]Hoja de pedidos'!C229,"") -> 01-2058 | B228: =IF('[1]Hoja de pedidos'!$D229>0,'[1]Hoja de pedidos'!D229,"") -> TXPANP040A001 | C228: =IF('[1]Hoja de pedidos'!$D229>0,'[1]Hoja de pedidos'!E229,"") -> PEPSICO ALIMENTOS, S.C.A. | D228: =IF('[1]Hoja de pedidos'!$D229>0,'[1]Hoja de pedidos'!F229,"") -> LAMINACION IMPRESA NATUCHIPS PLATANITOS 80g | E228: =IF('[1]Hoja de pedidos'!$D229>0,'[1]Hoja de pedidos'!G229,"") -> CX | F228: =IF('[1]Hoja de pedidos'!$D229>0,'[1]Hoja de pedidos'!H229,"") -> LAMINACION
A229: =IF('[1]Hoja de pedidos'!$D230>0,'[1]Hoja de pedidos'!C230,"") -> 01-2048 | B229: =IF('[1]Hoja de pedidos'!$D230>0,'[1]Hoja de pedidos'!D230,"") -> TMAWAA064A010 | C229: =IF('[1]Hoja de pedidos'!$D230>0,'[1]Hoja de pedidos'!E230,"") -> ALUM-WARE PRODUCTOS DE ALUMINIO C.A. | D229: =IF('[1]Hoja de pedidos'!$D230>0,'[1]Hoja de pedidos'!F230,"") -> POLYPOUCH IMPRESO ANTIGRASO ALUM-WARE | E229: =IF('[1]Hoja de pedidos'!$D230>0,'[1]Hoja de pedidos'!G230,"") -> MCL | F229: =IF('[1]Hoja de pedidos'!$D230>0,'[1]Hoja de pedidos'!H230,"") -> LAMINACION
... A1169: =IF('[1]Hoja de pedidos'!$D1170>0,'[1]Hoja de pedidos'!C1170,"") -> 32-006210 | B1169: =IF('[1]Hoja de pedidos'!$D1170>0,'[1]Hoja de pedidos'!D1170,"") -> TMFFLU2400001 | C1169: =IF('[1]Hoja de pedidos'!$D1170>0,'[1]Hoja de pedidos'!E1170,"") -> FABRICA FESTA S.A. | D1169: =IF('[1]Hoja de pedidos'!$D1170>0,'[1]Hoja de pedidos'!F1170,"") -> LAMINACION LINER INDUCCION UNIVERSAL SIN IMPRESIÓN | E1169: =IF('[1]Hoja de pedidos'!$D1170>0,'[1]Hoja de pedidos'!G1170,"") -> MCL | F1169: =IF('[1]Hoja de pedidos'!$D1170>0,'[1]Hoja de pedidos'!H1170,"") -> CORTE
A1170: =IF('[1]Hoja de pedidos'!$D1171>0,'[1]Hoja de pedidos'!C1171,"") -> 32-006211 | B1170: TMAJBF110A001 | C1170: =IF('[1]Hoja de pedidos'!$D1171>0,'[1]Hoja de pedidos'!E1171,"") -> ALFONZO RIVAS & CIA, C.A. | D1170: =IF('[1]Hoja de pedidos'!$D1171>0,'[1]Hoja de pedidos'!F1171,"") -> LAMINACION IMPRESA YELIGHT SIN SABOR 9g | E1170: =IF('[1]Hoja de pedidos'!$D1171>0,'[1]Hoja de pedidos'!G1171,"") -> MCL | F1170: =IF('[1]Hoja de pedidos'!$D1171>0,'[1]Hoja de pedidos'!H1171,"") -> LAMINACION
A1171: =IF('[1]Hoja de pedidos'!$D1172>0,'[1]Hoja de pedidos'!C1172,"") -> 01-2814 | B1171: =IF('[1]Hoja de pedidos'!$D1172>0,'[1]Hoja de pedidos'!D1172,"") -> TMAPAL1190010 | C1171: =IF('[1]Hoja de pedidos'!$D1172>0,'[1]Hoja de pedidos'!E1172,"") -> ALIMENTOS POLAR COMERCIAL, C.A. | D1171: =IF('[1]Hoja de pedidos'!$D1172>0,'[1]Hoja de pedidos'!F1172,"") -> ALUMINIO LAMINADO SIN IMPRESIÓN | E1171: =IF('[1]Hoja de pedidos'!$D1172>0,'[1]Hoja de pedidos'!G1172,"") -> MCL | F1171: =IF('[1]Hoja de pedidos'!$D1172>0,'[1]Hoja de pedidos'!H1172,"") -> LAMINACION
A1172: =IF('[1]Hoja de pedidos'!$D1173>0,'[1]Hoja de pedidos'!C1173,"") -> 01-2797 | B1172: =IF('[1]Hoja de pedidos'!$D1173>0,'[1]Hoja de pedidos'!D1173,"") -> TXPARO040A001 | C1172: =IF('[1]Hoja de pedidos'!$D1173>0,'[1]Hoja de pedidos'!E1173,"") -> PEPSICO ALIMENTOS, S.C.A. | D1172: =IF('[1]Hoja de pedidos'!$D1173>0,'[1]Hoja de pedidos'!F1173,"") -> LAMINACION IMPRESA RUFFLES ORIGINAL 125g | E1172: =IF('[1]Hoja de pedidos'!$D1173>0,'[1]Hoja de pedidos'!G1173,"") -> CX | F1172: =IF('[1]Hoja de pedidos'!$D1173>0,'[1]Hoja de pedidos'!H1173,"") -> LAMINACION
A1173: =IF('[1]Hoja de pedidos'!$D1174>0,'[1]Hoja de pedidos'!C1174,"") -> 01-2819 | B1173: =IF('[1]Hoja de pedidos'!$D1174>0,'[1]Hoja de pedidos'!D1174,"") -> TMAPAL1190010 | C1173: =IF('[1]Hoja de pedidos'!$D1174>0,'[1]Hoja de pedidos'!E1174,"") -> ALIMENTOS POLAR COMERCIAL, C.A. | D1173: =IF('[1]Hoja de pedidos'!$D1174>0,'[1]Hoja de pedidos'!F1174,"") -> ALUMINIO LAMINADO SIN IMPRESIÓN | E1173: =IF('[1]Hoja de pedidos'!$D1174>0,'[1]Hoja de pedidos'!G1174,"") -> MCL | F1173: =IF('[1]Hoja de pedidos'!$D1174>0,'[1]Hoja de pedidos'!H1174,"") -> LAMINACION
A1174: =IF('[1]Hoja de pedidos'!$D1175>0,'[1]Hoja de pedidos'!C1175,"") -> 01-2811 | B1174: =IF('[1]Hoja de pedidos'!$D1175>0,'[1]Hoja de pedidos'!D1175,"") -> TMSVLM0940001 | C1174: =IF('[1]Hoja de pedidos'!$D1175>0,'[1]Hoja de pedidos'!E1175,"") -> SONOCO VENEZOLANA, C.A. | D1174: =IF('[1]Hoja de pedidos'!$D1175>0,'[1]Hoja de pedidos'!F1175,"") -> LAMINACION LINER RM 511 SIN IMPRESIÓN | E1174: =IF('[1]Hoja de pedidos'!$D1175>0,'[1]Hoja de pedidos'!G1175,"") -> MCL | F1174: =IF('[1]Hoja de pedidos'!$D1175>0,'[1]Hoja de pedidos'!H1175,"") -> LAMINACION
A1175: =IF('[1]Hoja de pedidos'!$D1176>0,'[1]Hoja de pedidos'!C1176,"") -> 01-2816 | B1175: =IF('[1]Hoja de pedidos'!$D1176>0,'[1]Hoja de pedidos'!D1176,"") -> TMPPLU2400001 | C1175: =IF('[1]Hoja de pedidos'!$D1176>0,'[1]Hoja de pedidos'!E1176,"") -> PLASTIPRODUCTOS PINCORD, C.A. | D1175: =IF('[1]Hoja de pedidos'!$D1176>0,'[1]Hoja de pedidos'!F1176,"") -> LAMINACION LINNER DE INDUCCION UNIVERSAL SIN IMPRESIÓN | E1175: =IF('[1]Hoja de pedidos'!$D1176>0,'[1]Hoja de pedidos'!G1176,"") -> MCL | F1175: =IF('[1]Hoja de pedidos'!$D1176>0,'[1]Hoja de pedidos'!H1176,"") -> LAMINACION
A1176: =IF('[1]Hoja de pedidos'!$D1177>0,'[1]Hoja de pedidos'!C1177,"") -> 01-2818 | B1176: =IF('[1]Hoja de pedidos'!$D1177>0,'[1]Hoja de pedidos'!D1177,"") -> TMAYGP207A003 | C1176: =IF('[1]Hoja de pedidos'!$D1177>0,'[1]Hoja de pedidos'!E1177,"") -> ANAYANSI,C.A. | D1176: =IF('[1]Hoja de pedidos'!$D1177>0,'[1]Hoja de pedidos'!F1177,"") -> LINER TERMOSELLABLE MTP IMPRESO GARANTIA DE PUREZA | E1176: =IF('[1]Hoja de pedidos'!$D1177>0,'[1]Hoja de pedidos'!G1177,"") -> MCL | F1176: =IF('[1]Hoja de pedidos'!$D1177>0,'[1]Hoja de pedidos'!H1177,"") -> LAMINACION
